Workbook

Sheet resumen_metricas_dinamico
A1: id_cuentas | B1: nombre_campaña | C1: fecha_inicio | D1: fecha_fin | E1: eje | F1: area | G1: estado | H1: {={"digital_impresiones";SUMIF(DIGITAL!A2:A1000,A2:A1000,DIGITAL!C2:C1000)}} -> digital_impresiones | I1: {={"digital_visualizaciones";SUMIF(DIGITAL!A2:A1000,A2:A1000,DIGITAL!D2:D1000)}} -> digital_visualizaciones | J1: {={"digital_clics";SUMIF(DIGITAL!A2:A1000,A2:A1000,DIGITAL!E2:E1000)}} -> digital_clics | K1: {={"meta_alcance";IFERROR(VLOOKUP(A2:A1000,ALCANCE!$A$2:$C1000,2,0),0)}} -> meta_alcance | L1: {={"meta_frecuencia";IFERROR(VLOOKUP(A2:A1000,ALCANCE!$A$2:$C1000,3,0),0)}} -> meta_frecuencia | M1: {={"frecuencia_total";IFERROR(H2:H1000/K2:K1000,0)}} -> frecuencia_total | N1: {={"mails_enviados";SUMIF(MAIL!A2:A1000,A2:A1000,MAIL!B2:B1000)}} -> mails_enviados | O1: {={"mails_entregados";SUMIF(MAIL!A2:A1000,A2:A1000,MAIL!C2:C1000)}} -> mails_entregados | P1: {={"mails_aperturas";SUMIF(MAIL!A2:A1000,A2:A1000,MAIL!D2:D1000)}} -> mails_aperturas | Q1: {={"mails_clics";SUMIF(MAIL!A2:A1000,A2:A1000,MAIL!E2:E1000)}} -> mails_clics | R1: {={"call_enviado";SUMIF(CC!A2:A1000,A2:A1000,CC!B2:B1000)}} -> call_enviado | S1: {={"call_discado";SUMIF(CC!A2:A1000,A2:A1000,CC!C2:C1000)}} -> call_discado | T1: {={"call_contactados";SUMIF(CC!A2:A1000,A2:A1000,CC!D2:D1000)}} -> call_contactados | U1: {={"call_efectivos";SUMIF(CC!A2:A1000,A2:A1000,CC!E2:E1000)}} -> call_efectivos | V1: {={"ivr_audiencia";SUMIF(IVR!A2:A1000,A2:A1000,IVR!B2:B1000)}} -> ivr_audiencia | W1: {={"ivr_realizados";SUMIF(IVR!A2:A1000,A2:A1000,IVR!C2:C1000)}} -> ivr_realizados | X1: {={"ivr_atendidos";SUMIF(IVR!A2:A1000,A2:A1000,IVR!D2:D1000)}} -> ivr_atendidos | Y1: {={"ivr_escucha75";SUMIF(IVR!A2:A1000,A2:A1000,IVR!E2:E1000)}} -> ivr_escucha75 | Z1: {={"ivr_marque1";SUMIF(IVR!A2:A1000,A2:A1000,IVR!F2:F1000)}} -> ivr_marque1 | AA1: {={"sms_enviados";SUMIF(SMS!A2:A1000,A2:A1000,SMS!B2:B1000)}} -> sms_enviados | AB1: {={"sms_entregados";SUMIF(SMS!A2:A1000,A2:A1000,SMS!C2:C1000)}} -> sms_entregados | AC1: {={"sms_clics";SUMIF(SMS!A2:A1000,A2:A1000,SMS!D2:D1000)}} -> sms_clics | AD1: {={"pieza_meta";IFERROR(VLOOKUP(A2:A1000,URLs!D1:F1000,3,0),"")}} -> pieza_meta | AE1: {={"pieza_mail";IFERROR(VLOOKUP(A2:A1000,URLs!A1:C1000,3,0),"")}} -> pieza_mail
A2: =IFERROR(__xludf.DUMMYFUNCTION("QUERY(Cuentas!A2:G1000,""SELECT * WHERE Col1 is not null AND Col7 <> 'Pendiente'"",0)"),"1871-AGOEDUGC") -> 1871-AGOEDUGC | B2: =IFERROR(__xludf.DUMMYFUNCTION("""COMPUTED_VALUE"""),"Campaña GCBA | Educación | TUMO") -> Campaña GCBA | Educación | TUMO | C2: =IFERROR(__xludf.DUMMYFUNCTION("""COMPUTED_VALUE"""),45959.0) -> 45959 | D2: =IFERROR(__xludf.DUMMYFUNCTION("""COMPUTED_VALUE"""),46203.0) -> 46203 | E2: =IFERROR(__xludf.DUMMYFUNCTION("""COMPUTED_VALUE"""),"Cuidado") -> Cuidado | F2: =IFERROR(__xludf.DUMMYFUNCTION("""COMPUTED_VALUE"""),"Educación") -> Educación | G2: =IFERROR(__xludf.DUMMYFUNCTION("""COMPUTED_VALUE"""),"Finalizada") -> Finalizada | H2: 201273767 | I2: 21618564 | J2: 2637230 | K2: 9405671 | L2: 1.211467 | M2: 21.399193 | N2: 858783 | O2: 844304 | P2: 285060 | Q2: 8156 | R2: 4476 | S2: 4476 | T2: 1117 | U2: 854 | V2: 0 | W2: 0 | X2: 0 | Y2: 0 | Z2: 0 | AA2: 0 | AB2: 0 | AC2: 0 | AD2: https://www.facebook.com/reel/818777800864033
A3: =IFERROR(__xludf.DUMMYFUNCTION("""COMPUTED_VALUE"""),"1895-SEPEPHGC") -> 1895-SEPEPHGC | B3: =IFERROR(__xludf.DUMMYFUNCTION("""COMPUTED_VALUE"""),"PIEZAS M2 | MEPHU | REPAVIMENTACIÓN") -> PIEZAS M2 | MEPHU | REPAVIMENTACIÓN | C3: =IFERROR(__xludf.DUMMYFUNCTION("""COMPUTED_VALUE"""),46052.0) -> 46052 | D3: =IFERROR(__xludf.DUMMYFUNCTION("""COMPUTED_VALUE"""),46178.0) -> 46178 | E3: =IFERROR(__xludf.DUMMYFUNCTION("""COMPUTED_VALUE"""),"M2") -> M2 | F3: =IFERROR(__xludf.DUMMYFUNCTION("""COMPUTED_VALUE"""),"Espacio Público e Higiene Urbana") -> Espacio Público e Higiene Urbana | G3: =IFERROR(__xludf.DUMMYFUNCTION("""COMPUTED_VALUE"""),"Finalizada") -> Finalizada | H3: 0 | I3: 0 | J3: 0 | K3: 0 | L3: 0 | M3: 0 | N3: 21556 | O3: 21228 | P3: 7666 | Q3: 393 | R3: 0 | S3: 0 | T3: 0 | U3: 0 | V3: 0 | W3: 0 | X3: 0 | Y3: 0 | Z3: 0 | AA3: 0 | AB3: 0 | AC3: 0 | AE3: Pieza
A4: =IFERROR(__xludf.DUMMYFUNCTION("""COMPUTED_VALUE"""),"1896-SEPEPHGC") -> 1896-SEPEPHGC | B4: =IFERROR(__xludf.DUMMYFUNCTION("""COMPUTED_VALUE"""),"PIEZAS M2 | MEPHU | LIMPIEZA INTENSIVA") -> PIEZAS M2 | MEPHU | LIMPIEZA INTENSIVA | C4: =IFERROR(__xludf.DUMMYFUNCTION("""COMPUTED_VALUE"""),46031.0) -> 46031 | D4: =IFERROR(__xludf.DUMMYFUNCTION("""COMPUTED_VALUE"""),46136.0) -> 46136 | E4: =IFERROR(__xludf.DUMMYFUNCTION("""COMPUTED_VALUE"""),"M2") -> M2 | F4: =IFERROR(__xludf.DUMMYFUNCTION("""COMPUTED_VALUE"""),"Espacio Público e Higiene Urbana") -> Espacio Público e Higiene Urbana | G4: =IFERROR(__xludf.DUMMYFUNCTION("""COMPUTED_VALUE"""),"Finalizada") -> Finalizada | H4: 0 | I4: 0 | J4: 0 | K4: 0 | L4: 0 | M4: 0 | N4: 648150 | O4: 634433 | P4: 181275 | Q4: 1540 | R4: 0 | S4: 0 | T4: 0 | U4: 0 | V4: 0 | W4: 0 | X4: 0 | Y4: 0 | Z4: 0 | AA4: 0 | AB4: 0 | AC4: 0 | AE4: Pieza
A5: =IFERROR(__xludf.DUMMYFUNCTION("""COMPUTED_VALUE"""),"1933-SEPINFGC") -> 1933-SEPINFGC | B5: =IFERROR(__xludf.DUMMYFUNCTION("""COMPUTED_VALUE"""),"CAMPAÑA GCBA | INFRAESTRUCTURA | Campaña 360° Movilidad 2025") -> CAMPAÑA GCBA | INFRAESTRUCTURA | Campaña 360° Movilidad 2025 | C5: =IFERROR(__xludf.DUMMYFUNCTION("""COMPUTED_VALUE"""),45936.0) -> 45936 | D5: =IFERROR(__xludf.DUMMYFUNCTION("""COMPUTED_VALUE"""),46081.0) -> 46081 | E5: =IFERROR(__xludf.DUMMYFUNCTION("""COMPUTED_VALUE"""),"Movilidad") -> Movilidad | F5: =IFERROR(__xludf.DUMMYFUNCTION("""COMPUTED_VALUE"""),"Infraestructura") -> Infraestructura | G5: =IFERROR(__xludf.DUMMYFUNCTION("""COMPUTED_VALUE"""),"Finalizada") -> Finalizada | H5: 120265231 | I5: 14353067 | J5: 530499 | K5: 6681997 | L5: 0.9273355 | M5: 17.998396 | N5: 2962736 | O5: 3124082 | P5: 1008617 | Q5: 19835 | R5: 0 | S5: 0 | T5: 0 | U5: 0 | V5: 0 | W5: 0 | X5: 0 | Y5: 0 | Z5: 0 | AA5: 16505 | AB5: 15794 | AC5: 82 | AD5: https://www.facebook.com/GCBA/posts/pfbid02ySETv8mbLPx3NFrrHh1eRhVRmMimid99iTcJQu2RtwUS7KCAiwKP9qoSStF1cMSml | AE5: Pieza
A6: =IFERROR(__xludf.DUMMYFUNCTION("""COMPUTED_VALUE"""),"1942-SEPEPHGC") -> 1942-SEPEPHGC | B6: =IFERROR(__xludf.DUMMYFUNCTION("""COMPUTED_VALUE"""),"DGPLES | MEPHU | REPARACIÓN DE VEREDAS") -> DGPLES | MEPHU | REPARACIÓN DE VEREDAS | C6: =IFERROR(__xludf.DUMMYFUNCTION("""COMPUTED_VALUE"""),46031.0) -> 46031 | D6: =IFERROR(__xludf.DUMMYFUNCTION("""COMPUTED_VALUE"""),46223.0) -> 46223 | E6: =IFERROR(__xludf.DUMMYFUNCTION("""COMPUTED_VALUE"""),"M2") -> M2 | F6: =IFERROR(__xludf.DUMMYFUNCTION("""COMPUTED_VALUE"""),"Espacio Público e Higiene Urbana") -> Espacio Público e Higiene Urbana | G6: =IFERROR(__xludf.DUMMYFUNCTION("""COMPUTED_VALUE"""),"Finalizada") -> Finalizada | H6: 0 | I6: 0 | J6: 0 | K6: 0 | L6: 0 | M6: 0 | N6: 69878 | O6: 68815 | P6: 23523 | Q6: 1379 | R6: 0 | S6: 0 | T6: 0 | U6: 0 | V6: 0 | W6: 0 | X6: 0 | Y6: 0 | Z6: 0 | AA6: 0 | AB6: 0 | AC6: 0 | AE6: Pieza
A7: =IFERROR(__xludf.DUMMYFUNCTION("""COMPUTED_VALUE"""),"1943-SEPEPHGC") -> 1943-SEPEPHGC | B7: =IFERROR(__xludf.DUMMYFUNCTION("""COMPUTED_VALUE"""),"DGPLES | MEPHU | READOQUINADO") -> DGPLES | MEPHU | READOQUINADO | C7: =IFERROR(__xludf.DUMMYFUNCTION("""COMPUTED_VALUE"""),46031.0) -> 46031 | D7: =IFERROR(__xludf.DUMMYFUNCTION("""COMPUTED_VALUE"""),46223.0) -> 46223 | E7: =IFERROR(__xludf.DUMMYFUNCTION("""COMPUTED_VALUE"""),"M2") -> M2 | F7: =IFERROR(__xludf.DUMMYFUNCTION("""COMPUTED_VALUE"""),"Espacio Público e Higiene Urbana") -> Espacio Público e Higiene Urbana | G7: =IFERROR(__xludf.DUMMYFUNCTION("""COMPUTED_VALUE"""),"Finalizada") -> Finalizada | H7: 0 | I7: 0 | J7: 0 | K7: 0 | L7: 0 | M7: 0 | N7: 15590 | O7: 15371 | P7: 5329 | Q7: 415 | R7: 0 | S7: 0 | T7: 0 | U7: 0 | V7: 0 | W7: 0 | X7: 0 | Y7: 0 | Z7: 0 | AA7: 0 | AB7: 0 | AC7: 0 | AE7: Pieza
A8: =IFERROR(__xludf.DUMMYFUNCTION("""COMPUTED_VALUE"""),"1946-SEPEPHGC") -> 1946-SEPEPHGC | B8: =IFERROR(__xludf.DUMMYFUNCTION("""COMPUTED_VALUE"""),"CAMPAÑA GCBA | MEPHU | PLUVIALES") -> CAMPAÑA GCBA | MEPHU | PLUVIALES | C8: =IFERROR(__xludf.DUMMYFUNCTION("""COMPUTED_VALUE"""),46038.0) -> 46038 | D8: =IFERROR(__xludf.DUMMYFUNCTION("""COMPUTED_VALUE"""),46223.0) -> 46223 | E8: =IFERROR(__xludf.DUMMYFUNCTION("""COMPUTED_VALUE"""),"M2") -> M2 | F8: =IFERROR(__xludf.DUMMYFUNCTION("""COMPUTED_VALUE"""),"Espacio Público e Higiene Urbana") -> Espacio Público e Higiene Urbana | G8: =IFERROR(__xludf.DUMMYFUNCTION("""COMPUTED_VALUE"""),"Finalizada") -> Finalizada | H8: 0 | I8: 0 | J8: 0 | K8: 0 | L8: 0 | M8: 0 | N8: 18528 | O8: 18309 | P8: 6404 | Q8: 426 | R8: 0 | S8: 0 | T8: 0 | U8: 0 | V8: 0 | W8: 0 | X8: 0 | Y8: 0 | Z8: 0 | AA8: 0 | AB8: 0 | AC8: 0 | AE8: Pieza
A9: =IFERROR(__xludf.DUMMYFUNCTION("""COMPUTED_VALUE"""),"1964-SEPEPHGC") -> 1964-SEPEPHGC | B9: =IFERROR(__xludf.DUMMYFUNCTION("""COMPUTED_VALUE"""),"MEPHU RECAMBIO TECNOLÓGICO M2") -> MEPHU RECAMBIO TECNOLÓGICO M2 | C9: =IFERROR(__xludf.DUMMYFUNCTION("""COMPUTED_VALUE"""),46071.0) -> 46071 | D9: =IFERROR(__xludf.DUMMYFUNCTION("""COMPUTED_VALUE"""),46220.0) -> 46220 | E9: =IFERROR(__xludf.DUMMYFUNCTION("""COMPUTED_VALUE"""),"M2") -> M2 | F9: =IFERROR(__xludf.DUMMYFUNCTION("""COMPUTED_VALUE"""),"Espacio Público e Higiene Urbana") -> Espacio Público e Higiene Urbana | G9: =IFERROR(__xludf.DUMMYFUNCTION("""COMPUTED_VALUE"""),"Finalizada") -> Finalizada | H9: 0 | I9: 0 | J9: 0 | K9: 0 | L9: 0 | M9: 0 | N9: 444872 | O9: 439325 | P9: 133653 | Q9: 3043 | R9: 0 | S9: 0 | T9: 0 | U9: 0 | V9: 0 | W9: 0 | X9: 0 | Y9: 0 | Z9: 0 | AA9: 0 | AB9: 0 | AC9: 0 | AE9: Pieza
A10: =IFERROR(__xludf.DUMMYFUNCTION("""COMPUTED_VALUE"""),"2033-SEPEPHGC") -> 2033-SEPEPHGC | B10: =IFERROR(__xludf.DUMMYFUNCTION("""COMPUTED_VALUE"""),"M2 PODA") -> M2 PODA | C10: =IFERROR(__xludf.DUMMYFUNCTION("""COMPUTED_VALUE"""),46035.0) -> 46035 | D10: =IFERROR(__xludf.DUMMYFUNCTION("""COMPUTED_VALUE"""),46216.0) -> 46216 | E10: =IFERROR(__xludf.DUMMYFUNCTION("""COMPUTED_VALUE"""),"M2") -> M2 | F10: =IFERROR(__xludf.DUMMYFUNCTION("""COMPUTED_VALUE"""),"Espacio Público e Higiene Urbana") -> Espacio Público e Higiene Urbana | G10: =IFERROR(__xludf.DUMMYFUNCTION("""COMPUTED_VALUE"""),"Finalizada") -> Finalizada | H10: 0 | I10: 0 | J10: 0 | K10: 0 | L10: 0 | M10: 0 | N10: 145204 | O10: 141927 | P10: 46936 | Q10: 2044 | R10: 0 | S10: 0 | T10: 0 | U10: 0 | V10: 0 | W10: 0 | X10: 0 | Y10: 0 | Z10: 0 | AA10: 0 | AB10: 0 | AC10: 0 | AE10: Pieza
A11: =IFERROR(__xludf.DUMMYFUNCTION("""COMPUTED_VALUE"""),"2100-OCTSALGC") -> 2100-OCTSALGC | B11: =IFERROR(__xludf.DUMMYFUNCTION("""COMPUTED_VALUE"""),"Cesac 12 - Más consultorios") -> Cesac 12 - Más consultorios | C11: =IFERROR(__xludf.DUMMYFUNCTION("""COMPUTED_VALUE"""),46013.0) -> 46013 | D11: =IFERROR(__xludf.DUMMYFUNCTION("""COMPUTED_VALUE"""),46027.0) -> 46027 | E11: =IFERROR(__xludf.DUMMYFUNCTION("""COMPUTED_VALUE"""),"Cuidado") -> Cuidado | F11: =IFERROR(__xludf.DUMMYFUNCTION("""COMPUTED_VALUE"""),"Salud") -> Salud | G11: =IFERROR(__xludf.DUMMYFUNCTION("""COMPUTED_VALUE"""),"Finalizada") -> Finalizada | H11: 5541119 | I11: 634751 | J11: 14536 | K11: 0 | L11: 0 | M11: 0 | N11: 81077 | O11: 79591 | P11: 31217 | Q11: 1060 | R11: 0 | S11: 0 | T11: 0 | U11: 0 | V11: 0 | W11: 0 | X11: 0 | Y11: 0 | Z11: 0 | AA11: 0 | AB11: 0 | AC11: 0
A12: =IFERROR(__xludf.DUMMYFUNCTION("""COMPUTED_VALUE"""),"2108-OCTEDUGC") -> 2108-OCTEDUGC | B12: =IFERROR(__xludf.DUMMYFUNCTION("""COMPUTED_VALUE"""),"Inscripción 2025 a Profesorados de la Ciudad") -> Inscripción 2025 a Profesorados de la Ciudad | C12: =IFERROR(__xludf.DUMMYFUNCTION("""COMPUTED_VALUE"""),45952.0) -> 45952 | D12: =IFERROR(__xludf.DUMMYFUNCTION("""COMPUTED_VALUE"""),46073.0) -> 46073 | E12: =IFERROR(__xludf.DUMMYFUNCTION("""COMPUTED_VALUE"""),"Cuidado") -> Cuidado | F12: =IFERROR(__xludf.DUMMYFUNCTION("""COMPUTED_VALUE"""),"Educación") -> Educación | G12: =IFERROR(__xludf.DUMMYFUNCTION("""COMPUTED_VALUE"""),"Finalizada") -> Finalizada | H12: 24528982 | I12: 0 | J12: 555619 | K12: 1745904 | L12: 1.3171446 | M12: 14.049445 | N12: 132413 | O12: 130535 | P12: 87400 | Q12: 8263 | R12: 0 | S12: 0 | T12: 0 | U12: 0 | V12: 0 | W12: 0 | X12: 0 | Y12: 0 | Z12: 0 | AA12: 0 | AB12: 0 | AC12: 0 | AD12: https://www.facebook.com/GCBA/posts/1295953569230956
A13: =IFERROR(__xludf.DUMMYFUNCTION("""COMPUTED_VALUE"""),"2109-OCTEPHGC") -> 2109-OCTEPHGC | B13: =IFERROR(__xludf.DUMMYFUNCTION("""COMPUTED_VALUE"""),"LIMPIEZA DE FACHADAS | M2") -> LIMPIEZA DE FACHADAS | M2 | C13: =IFERROR(__xludf.DUMMYFUNCTION("""COMPUTED_VALUE"""),46028.0) -> 46028 | D13: =IFERROR(__xludf.DUMMYFUNCTION("""COMPUTED_VALUE"""),46099.0) -> 46099 | E13: =IFERROR(__xludf.DUMMYFUNCTION("""COMPUTED_VALUE"""),"M2") -> M2 | F13: =IFERROR(__xludf.DUMMYFUNCTION("""COMPUTED_VALUE"""),"Espacio Público e Higiene Urbana") -> Espacio Público e Higiene Urbana | G13: =IFERROR(__xludf.DUMMYFUNCTION("""COMPUTED_VALUE"""),"Finalizada") -> Finalizada | H13: 0 | I13: 0 | J13: 0 | K13: 0 | L13: 0 | M13: 0 | N13: 923 | O13: 898 | P13: 294 | Q13: 38 | R13: 0 | S13: 0 | T13: 0 | U13: 0 | V13: 0 | W13: 0 | X13: 0 | Y13: 0 | Z13: 0 | AA13: 0 | AB13: 0 | AC13: 0 | AE13: Pieza
A14: =IFERROR(__xludf.DUMMYFUNCTION("""COMPUTED_VALUE"""),"2130-OCTSALGC") -> 2130-OCTSALGC | B14: =IFERROR(__xludf.DUMMYFUNCTION("""COMPUTED_VALUE"""),"Hospital Pirovano: Remodelaciones") -> Hospital Pirovano: Remodelaciones | C14: =IFERROR(__xludf.DUMMYFUNCTION("""COMPUTED_VALUE"""),46050.0) -> 46050 | D14: =IFERROR(__xludf.DUMMYFUNCTION("""COMPUTED_VALUE"""),46066.0) -> 46066 | E14: =IFERROR(__xludf.DUMMYFUNCTION("""COMPUTED_VALUE"""),"Cuidado") -> Cuidado | F14: =IFERROR(__xludf.DUMMYFUNCTION("""COMPUTED_VALUE"""),"Salud") -> Salud | G14: =IFERROR(__xludf.DUMMYFUNCTION("""COMPUTED_VALUE"""),"Finalizada") -> Finalizada | H14: 3945078 | I14: 0 | J14: 9197 | K14: 1208470 | L14: 1.0665105 | M14: 3.2645229 | N14: 100614 | O14: 99157 | P14: 42370 | Q14: 787 | R14: 0 | S14: 0 | T14: 0 | U14: 0 | V14: 0 | W14: 0 | X14: 0 | Y14: 0 | Z14: 0 | AA14: 0 | AB14: 0 | AC14: 0 | AE14: Pieza
A15: =IFERROR(__xludf.DUMMYFUNCTION("""COMPUTED_VALUE"""),"2145-OCTVINGC") -> 2145-OCTVINGC | B15: =IFERROR(__xludf.DUMMYFUNCTION("""COMPUTED_VALUE"""),"PIEZAS M2 | VINCULO CIUDADANO (GESTIÓN COMUNAL) | OBRAS EN PARQUES Y PLAZAS (PATIOS DE JUEGOS) Plan 2025") -> PIEZAS M2 | VINCULO CIUDADANO (GESTIÓN COMUNAL) | OBRAS EN PARQUES Y PLAZAS (PATIOS DE JUEGOS) Plan 2025 | C15: =IFERROR(__xludf.DUMMYFUNCTION("""COMPUTED_VALUE"""),46020.0) -> 46020 | D15: =IFERROR(__xludf.DUMMYFUNCTION("""COMPUTED_VALUE"""),46174.0) -> 46174 | E15: =IFERROR(__xludf.DUMMYFUNCTION("""COMPUTED_VALUE"""),"M2") -> M2 | F15: =IFERROR(__xludf.DUMMYFUNCTION("""COMPUTED_VALUE"""),"Vínculo Ciudadano") -> Vínculo Ciudadano | G15: =IFERROR(__xludf.DUMMYFUNCTION("""COMPUTED_VALUE"""),"Finalizada") -> Finalizada | H15: 2352745 | I15: 0 | J15: 7138 | K15: 1084144 | L15: 1.9502769 | M15: 2.1701407 | N15: 1136573 | O15: 1111059 | P15: 368628 | Q15: 9109 | R15: 0 | S15: 0 | T15: 0 | U15: 0 | V15: 0 | W15: 0 | X15: 0 | Y15: 0 | Z15: 0 | AA15: 0 | AB15: 0 | AC15: 0 | AD15: https://www.facebook.com/GCBA/posts/pfbid02j9NjjKC7QJSSUrKxkX55nDiWFRmCpVKSS3w7J3VpQA3DakuvLQQ5B3z96orCNRMUl | AE15: Pieza
A16: =IFERROR(__xludf.DUMMYFUNCTION("""COMPUTED_VALUE"""),"2183-OCTSALGC") -> 2183-OCTSALGC | B16: =IFERROR(__xludf.DUMMYFUNCTION("""COMPUTED_VALUE"""),"Sistema de Salud Público - Genérico") -> Sistema de Salud Público - Genérico | C16: =IFERROR(__xludf.DUMMYFUNCTION("""COMPUTED_VALUE"""),45992.0) -> 45992 | D16: =IFERROR(__xludf.DUMMYFUNCTION("""COMPUTED_VALUE"""),46068.0) -> 46068 | E16: =IFERROR(__xludf.DUMMYFUNCTION("""COMPUTED_VALUE"""),"Cuidado") -> Cuidado | F16: =IFERROR(__xludf.DUMMYFUNCTION("""COMPUTED_VALUE"""),"Salud") -> Salud | G16: =IFERROR(__xludf.DUMMYFUNCTION("""COMPUTED_VALUE"""),"Finalizada") -> Finalizada | H16: 63685126 | I16: 11819633 | J16: 218716 | K16: 2510514 | L16: 2.9775759 | M16: 25.367365 | N16: 0 | O16: 0 | P16: 0 | Q16: 0 | R16: 0 | S16: 0 | T16: 0 | U16: 0 | V16: 0 | W16: 0 | X16: 0 | Y16: 0 | Z16: 0 | AA16: 44842 | AB16: 43029 | AC16: 724 | AD16: https://www.facebook.com/GCBA/posts/pfbid02QwxLwyKnw9PCTX9BXhgSSH5hJ3u56noy7igZq9orxmSsVPqjj4MMUZ5SD9xXWWQ3l
A17: =IFERROR(__xludf.DUMMYFUNCTION("""COMPUTED_VALUE"""),"2227-NOVINFGC") -> 2227-NOVINFGC | B17: =IFERROR(__xludf.DUMMYFUNCTION("""COMPUTED_VALUE"""),"Infraestructura - SBASE | Campaña GCBA | Seguridad en Subte") -> Infraestructura - SBASE | Campaña GCBA | Seguridad en Subte | C17: =IFERROR(__xludf.DUMMYFUNCTION("""COMPUTED_VALUE"""),45981.0) -> 45981 | D17: =IFERROR(__xludf.DUMMYFUNCTION("""COMPUTED_VALUE"""),46037.0) -> 46037 | E17: =IFERROR(__xludf.DUMMYFUNCTION("""COMPUTED_VALUE"""),"Movilidad") -> Movilidad | F17: =IFERROR(__xludf.DUMMYFUNCTION("""COMPUTED_VALUE"""),"Infraestructura") -> Infraestructura | G17: =IFERROR(__xludf.DUMMYFUNCTION("""COMPUTED_VALUE"""),"Finalizada") -> Finalizada | H17: 56510666 | I17: 13306488 | J17: 109062 | K17: 2996348 | L17: 1.9993095 | M17: 18.859847 | N17: 448806 | O17: 441370 | P17: 157871 | Q17: 1073 | R17: 0 | S17: 0 | T17: 0 | U17: 0 | V17: 0 | W17: 0 | X17: 0 | Y17: 0 | Z17: 0 | AA17: 0 | AB17: 0 | AC17: 0 | AD17: https://www.facebook.com/GCBA/posts/pfbid0swuyoC42Lys1AAsD6UQ7EPU5B43KXVdVXxxXU4X9oHEJ7DjKXtavLAdDHd6BpccBl | AE17: Pieza
A18: =IFERROR(__xludf.DUMMYFUNCTION("""COMPUTED_VALUE"""),"2239-NOVSALGC") -> 2239-NOVSALGC | B18: =IFERROR(__xludf.DUMMYFUNCTION("""COMPUTED_VALUE"""),"Cuidados del Calor 2025 - Prevención") -> Cuidados del Calor 2025 - Prevención | C18: =IFERROR(__xludf.DUMMYFUNCTION("""COMPUTED_VALUE"""),45996.0) -> 45996 | D18: =IFERROR(__xludf.DUMMYFUNCTION("""COMPUTED_VALUE"""),46081.0) -> 46081 | E18: =IFERROR(__xludf.DUMMYFUNCTION("""COMPUTED_VALUE"""),"Cuidado") -> Cuidado | F18: =IFERROR(__xludf.DUMMYFUNCTION("""COMPUTED_VALUE"""),"Salud") -> Salud | G18: =IFERROR(__xludf.DUMMYFUNCTION("""COMPUTED_VALUE"""),"Finalizada") -> Finalizada | H18: 44318251 | I18: 7628858 | J18: 207888 | K18: 3270088 | L18: 3.1020116 | M18: 13.552617 | N18: 393084 | O18: 386497 | P18: 128673 | Q18: 1026 | R18: 0 | S18: 0 | T18: 0 | U18: 0 | V18: 60114 | W18: 60114 | X18: 50294 | Y18: 14803 | Z18: 0 | AA18: 44261 | AB18: 42094 | AC18: 432 | AD18: https://www.facebook.com/GCBA/posts/pfbid02fZ6eoJSg8zqDVE3RogP3nnn5hqo9sxTPxRzzs7HgyWNUmM6XZmtSLLNohgBDJZ2xl | AE18: Pieza
A19: =IFERROR(__xludf.DUMMYFUNCTION("""COMPUTED_VALUE"""),"2240-NOVSALGC") -> 2240-NOVSALGC | B19: =IFERROR(__xludf.DUMMYFUNCTION("""COMPUTED_VALUE"""),"Cuidados del Calor 2025 - Síntomas") -> Cuidados del Calor 2025 - Síntomas | C19: =IFERROR(__xludf.DUMMYFUNCTION("""COMPUTED_VALUE"""),46009.0) -> 46009 | D19: =IFERROR(__xludf.DUMMYFUNCTION("""COMPUTED_VALUE"""),46081.0) -> 46081 | E19: =IFERROR(__xludf.DUMMYFUNCTION("""COMPUTED_VALUE"""),"Cuidado") -> Cuidado | F19: =IFERROR(__xludf.DUMMYFUNCTION("""COMPUTED_VALUE"""),"Salud") -> Salud | G19: =IFERROR(__xludf.DUMMYFUNCTION("""COMPUTED_VALUE"""),"Finalizada") -> Finalizada | H19: 37792450 | I19: 5153493 | J19: 136800 | K19: 1979868 | L19: 3.4276906 | M19: 19.088369 | N19: 202759 | O19: 198265 | P19: 46872 | Q19: 167 | R19: 0 | S19: 0 | T19: 0 | U19: 0 | V19: 0 | W19: 0 | X19: 0 | Y19: 0 | Z19: 0 | AA19: 0 | AB19: 0 | AC19: 0 | AD19: https://www.facebook.com/GCBA/posts/pfbid02XEqLAZ3ja1iUkCQ1AFBkuUXwxFv9zsX5K86BwUhreM4wjGsmh9yx8x8cEFwBnwo1l | AE19: Pieza
A20: =IFERROR(__xludf.DUMMYFUNCTION("""COMPUTED_VALUE"""),"2241-NOVSALGC") -> 2241-NOVSALGC | B20: =IFERROR(__xludf.DUMMYFUNCTION("""COMPUTED_VALUE"""),"Cuidados del Calor 2025 - Alertas Meteorológicas") -> Cuidados del Calor 2025 - Alertas Meteorológicas | C20: =IFERROR(__xludf.DUMMYFUNCTION("""COMPUTED_VALUE"""),46020.0) -> 46020 | D20: =IFERROR(__xludf.DUMMYFUNCTION("""COMPUTED_VALUE"""),46058.0) -> 46058 | E20: =IFERROR(__xludf.DUMMYFUNCTION("""COMPUTED_VALUE"""),"Cuidado") -> Cuidado | F20: =IFERROR(__xludf.DUMMYFUNCTION("""COMPUTED_VALUE"""),"Salud") -> Salud | G20: =IFERROR(__xludf.DUMMYFUNCTION("""COMPUTED_VALUE"""),"Finalizada") -> Finalizada | H20: 6328947 | I20: 0 | J20: 50769 | K20: 2394484 | L20: 1.3164298 | M20: 2.6431361 | N20: 246623 | O20: 243978 | P20: 116854 | Q20: 114 | R20: 0 | S20: 0 | T20: 0 | U20: 0 | V20: 0 | W20: 0 | X20: 0 | Y20: 0 | Z20: 0 | AA20: 62485 | AB20: 59237 | AC20: 372 | AD20: https://www.facebook.com/GCBA/posts/pfbid02j9NjjKC7QJSSUrKxkX55nDiWFRmCpVKSS3w7J3VpQA3DakuvLQQ5B3z96orCNRMUl
A21: =IFERROR(__xludf.DUMMYFUNCTION("""COMPUTED_VALUE"""),"2255-NOVSALGC") -> 2255-NOVSALGC | B21: =IFERROR(__xludf.DUMMYFUNCTION("""COMPUTED_VALUE"""),"Sistema de Salud Público - Geolocalizado") -> Sistema de Salud Público - Geolocalizado | C21: =IFERROR(__xludf.DUMMYFUNCTION("""COMPUTED_VALUE"""),46008.0) -> 46008 | D21: =IFERROR(__xludf.DUMMYFUNCTION("""COMPUTED_VALUE"""),46068.0) -> 46068 | E21: =IFERROR(__xludf.DUMMYFUNCTION("""COMPUTED_VALUE"""),"Cuidado") -> Cuidado | F21: =IFERROR(__xludf.DUMMYFUNCTION("""COMPUTED_VALUE"""),"Salud") -> Salud | G21: =IFERROR(__xludf.DUMMYFUNCTION("""COMPUTED_VALUE"""),"Finalizada") -> Finalizada | H21: 38197009 | I21: 0 | J21: 552532 | K21: 1566896 | L21: 3.6226406 | M21: 24.377501 | N21: 907590 | O21: 862876 | P21: 284653 | Q21: 624 | R21: 0 | S21: 0 | T21: 0 | U21: 0 | V21: 0 | W21: 0 | X21: 0 | Y21: 0 | Z21: 0 | AA21: 0 | AB21: 0 | AC21: 0 | AD21: https://www.facebook.com/GCBA/posts/pfbid02dx5PKW9dhfnoR52qjj3Cxnq9opfoRmH6HwTJx9uacynmmZet5vn1FL6Xavv3J8ZXl | AE21: Pieza
A22: =IFERROR(__xludf.DUMMYFUNCTION("""COMPUTED_VALUE"""),"2256-NOVSALGC") -> 2256-NOVSALGC | B22: =IFERROR(__xludf.DUMMYFUNCTION("""COMPUTED_VALUE"""),"Sistema de Salud Público - Diferenciado x Audiencias") -> Sistema de Salud Público - Diferenciado x Audiencias | C22: =IFERROR(__xludf.DUMMYFUNCTION("""COMPUTED_VALUE"""),46010.0) -> 46010 | D22: =IFERROR(__xludf.DUMMYFUNCTION("""COMPUTED_VALUE"""),46068.0) -> 46068 | E22: =IFERROR(__xludf.DUMMYFUNCTION("""COMPUTED_VALUE"""),"Cuidado") -> Cuidado | F22: =IFERROR(__xludf.DUMMYFUNCTION("""COMPUTED_VALUE"""),"Salud") -> Salud | G22: =IFERROR(__xludf.DUMMYFUNCTION("""COMPUTED_VALUE"""),"Finalizada") -> Finalizada | H22: 28261480 | I22: 5404995 | J22: 94248 | K22: 1318610 | L22: 2.6421224 | M22: 21.432781 | N22: 348034 | O22: 344435 | P22: 178103 | Q22: 356 | R22: 0 | S22: 0 | T22: 0 | U22: 0 | V22: 0 | W22: 0 | X22: 0 | Y22: 0 | Z22: 0 | AA22: 0 | AB22: 0 | AC22: 0 | AD22: https://www.facebook.com/GCBA/posts/pfbid02SB5PG237gJvSQGMPLHpQAP5b6uxqxh8AqRUS3csVWmCnYyvd77i8d67LSBMnBtg8l | AE22: Pieza
A23: =IFERROR(__xludf.DUMMYFUNCTION("""COMPUTED_VALUE"""),"2293-NOVFESGC") -> 2293-NOVFESGC | B23: =IFERROR(__xludf.DUMMYFUNCTION("""COMPUTED_VALUE"""),"LA CIUDAD MAS LINDA DEL MUNDO") -> LA CIUDAD MAS LINDA DEL MUNDO | C23: =IFERROR(__xludf.DUMMYFUNCTION("""COMPUTED_VALUE"""),45994.0) -> 45994 | D23: =IFERROR(__xludf.DUMMYFUNCTION("""COMPUTED_VALUE"""),46053.0) -> 46053 | E23: =IFERROR(__xludf.DUMMYFUNCTION("""COMPUTED_VALUE"""),"Ciudad Atractiva") -> Ciudad Atractiva | F23: =IFERROR(__xludf.DUMMYFUNCTION("""COMPUTED_VALUE"""),"Festivales y Eventos") -> Festivales y Eventos | G23: =IFERROR(__xludf.DUMMYFUNCTION("""COMPUTED_VALUE"""),"Finalizada") -> Finalizada | H23: 75245249 | I23: 13466546 | J23: 799082 | K23: 7843297 | L23: 1.9541976 | M23: 9.5935739 | N23: 657996 | O23: 645327 | P23: 198939 | Q23: 10076 | R23: 0 | S23: 0 | T23: 0 | U23: 0 | V23: 0 | W23: 0 | X23: 0 | Y23: 0 | Z23: 0 | AA23: 0 | AB23: 0 | AC23: 0 | AD23: https://www.facebook.com/GCBA/posts/pfbid0yZFqpziwsSvEpGHnbKnvgTkMNo6Ys8gfLmUBqRKhRCH71tiHcf1cXzt2RhCmokjMl
A24: =IFERROR(__xludf.DUMMYFUNCTION("""COMPUTED_VALUE"""),"2318-ENEINFGC") -> 2318-ENEINFGC | B24: =IFERROR(__xludf.DUMMYFUNCTION("""COMPUTED_VALUE"""),"Infraestructura I Cambio de sentido Avelino Díaz y Las Casas") -> Infraestructura I Cambio de sentido Avelino Díaz y Las Casas | C24: =IFERROR(__xludf.DUMMYFUNCTION("""COMPUTED_VALUE"""),46040.0) -> 46040 | D24: =IFERROR(__xludf.DUMMYFUNCTION("""COMPUTED_VALUE"""),46053.0) -> 46053 | E24: =IFERROR(__xludf.DUMMYFUNCTION("""COMPUTED_VALUE"""),"M2") -> M2 | F24: =IFERROR(__xludf.DUMMYFUNCTION("""COMPUTED_VALUE"""),"Infraestructura") -> Infraestructura | G24: =IFERROR(__xludf.DUMMYFUNCTION("""COMPUTED_VALUE"""),"Finalizada") -> Finalizada | H24: 656152 | I24: 0 | J24: 4677 | K24: 293307 | L24: 2.2370826 | M24: 2.2370826 | N24: 34125 | O24: 33543 | P24: 11623 | Q24: 221 | R24: 0 | S24: 0 | T24: 0 | U24: 0 | V24: 0 | W24: 0 | X24: 0 | Y24: 0 | Z24: 0 | AA24: 0 | AB24: 0 | AC24: 0 | AD24: https://www.facebook.com/GCBA/posts/pfbid02fhrsXdCgnCn19Gs1k1PTjbTdAfYLBMqW3w4zhQLgJqH8r8uW4azYikpQk6Js8WNcl | AE24: Pieza
A25: =IFERROR(__xludf.DUMMYFUNCTION("""COMPUTED_VALUE"""),"2322-NOVEDUGC") -> 2322-NOVEDUGC | B25: =IFERROR(__xludf.DUMMYFUNCTION("""COMPUTED_VALUE"""),"TUMO Parque de la Innovación") -> TUMO Parque de la Innovación | C25: =IFERROR(__xludf.DUMMYFUNCTION("""COMPUTED_VALUE"""),46006.0) -> 46006 | D25: =IFERROR(__xludf.DUMMYFUNCTION("""COMPUTED_VALUE"""),46265.0) -> 46265 | E25: =IFERROR(__xludf.DUMMYFUNCTION("""COMPUTED_VALUE"""),"Cuidado") -> Cuidado | F25: =IFERROR(__xludf.DUMMYFUNCTION("""COMPUTED_VALUE"""),"Educación") -> Educación | G25: =IFERROR(__xludf.DUMMYFUNCTION("""COMPUTED_VALUE"""),"Activa") -> Activa | H25: 37630874 | I25: 2298580 | J25: 197893 | K25: 845956 | L25: 2.7451924 | M25: 44.483252 | N25: 390326 | O25: 382880 | P25: 132608 | Q25: 2847 | R25: 2471 | S25: 2471 | T25: 938 | U25: 695 | V25: 0 | W25: 0 | X25: 0 | Y25: 0 | Z25: 0 | AA25: 0 | AB25: 0 | AC25: 0 | AD25: https://www.facebook.com/reel/1259490412867632 | AE25: Pieza
A26: =IFERROR(__xludf.DUMMYFUNCTION("""COMPUTED_VALUE"""),"2407-DICDHHGC") -> 2407-DICDHHGC | B26: =IFERROR(__xludf.DUMMYFUNCTION("""COMPUTED_VALUE"""),"Red de atención - Comuna 14") -> Red de atención - Comuna 14 | C26: =IFERROR(__xludf.DUMMYFUNCTION("""COMPUTED_VALUE"""),46009.0) -> 46009 | D26: =IFERROR(__xludf.DUMMYFUNCTION("""COMPUTED_VALUE"""),46035.0) -> 46035 | E26: =IFERROR(__xludf.DUMMYFUNCTION("""COMPUTED_VALUE"""),"Cuidado") -> Cuidado | F26: =IFERROR(__xludf.DUMMYFUNCTION("""COMPUTED_VALUE"""),"Desarrollo Humano y Hábitat") -> Desarrollo Humano y Hábitat | G26: =IFERROR(__xludf.DUMMYFUNCTION("""COMPUTED_VALUE"""),"Finalizada") -> Finalizada | H26: 5648733 | I26: 908168 | J26: 31911 | K26: 345688 | L26: 1.5532706 | M26: 16.340553 | N26: 82291 | O26: 80644 | P26: 34390 | Q26: 427 | R26: 41000 | S26: 38657 | T26: 7137 | U26: 4305 | V26: 0 | W26: 0 | X26: 0 | Y26: 0 | Z26: 0 | AA26: 0 | AB26: 0 | AC26: 0 | AD26: https://www.facebook.com/GCBA/posts/pfbid034rFdFhu5CMuLHbUxCF393aMxjQ6Uzsq6seyeRjcjNKtzSymPzkApKt81BUxEeVj3l | AE26: Pieza
A27: =IFERROR(__xludf.DUMMYFUNCTION("""COMPUTED_VALUE"""),"2410-DICJDGAG") -> 2410-DICJDGAG | B27: =IFERROR(__xludf.DUMMYFUNCTION("""COMPUTED_VALUE"""),"RDV JM | Villa Devoto 15/12") -> RDV JM | Villa Devoto 15/12 | C27: =IFERROR(__xludf.DUMMYFUNCTION("""COMPUTED_VALUE"""),46013.0) -> 46013 | D27: =IFERROR(__xludf.DUMMYFUNCTION("""COMPUTED_VALUE"""),46024.0) -> 46024 | E27: =IFERROR(__xludf.DUMMYFUNCTION("""COMPUTED_VALUE"""),"Cercanía") -> Cercanía | F27: =IFERROR(__xludf.DUMMYFUNCTION("""COMPUTED_VALUE"""),"Jefatura de Gobierno") -> Jefatura de Gobierno | G27: =IFERROR(__xludf.DUMMYFUNCTION("""COMPUTED_VALUE"""),"Finalizada") -> Finalizada | H27: 14229634 | I27: 322142 | J27: 29184 | K27: 0 | L27: 0 | M27: 0 | N27: 30540 | O27: 30402 | P27: 9314 | Q27: 336 | R27: 0 | S27: 0 | T27: 0 | U27: 0 | V27: 20067.047 | W27: 20067.047 | X27: 18323.305 | Y27: 7084.077 | Z27: 180 | AA27: 0 | AB27: 0 | AC27: 0
A28: =IFERROR(__xludf.DUMMYFUNCTION("""COMPUTED_VALUE"""),"2412-DICJDGAG") -> 2412-DICJDGAG | B28: =IFERROR(__xludf.DUMMYFUNCTION("""COMPUTED_VALUE"""),"RDV JM | Colegiales 19/12") -> RDV JM | Colegiales 19/12 | C28: =IFERROR(__xludf.DUMMYFUNCTION("""COMPUTED_VALUE"""),46014.0) -> 46014 | D28: =IFERROR(__xludf.DUMMYFUNCTION("""COMPUTED_VALUE"""),46025.0) -> 46025 | E28: =IFERROR(__xludf.DUMMYFUNCTION("""COMPUTED_VALUE"""),"Cercanía") -> Cercanía | F28: =IFERROR(__xludf.DUMMYFUNCTION("""COMPUTED_VALUE"""),"Jefatura de Gobierno") -> Jefatura de Gobierno | G28: =IFERROR(__xludf.DUMMYFUNCTION("""COMPUTED_VALUE"""),"Finalizada") -> Finalizada | H28: 1782381 | I28: 139137 | J28: 7011 | K28: 0 | L28: 0 | M28: 0 | N28: 24878 | O28: 24515 | P28: 6879 | Q28: 163 | R28: 6770 | S28: 6769 | T28: 1751 | U28: 1295 | V28: 26545.519 | W28: 26545.519 | X28: 23902.879 | Y28: 10339.329 | Z28: 126 | AA28: 0 | AB28: 0 | AC28: 0
A29: =IFERROR(__xludf.DUMMYFUNCTION("""COMPUTED_VALUE"""),"2423-DICJDGGC") -> 2423-DICJDGGC | B29: =IFERROR(__xludf.DUMMYFUNCTION("""COMPUTED_VALUE"""),"Festejos Responsables 2025") -> Festejos Responsables 2025 | C29: =IFERROR(__xludf.DUMMYFUNCTION("""COMPUTED_VALUE"""),46014.0) -> 46014 | D29: =IFERROR(__xludf.DUMMYFUNCTION("""COMPUTED_VALUE"""),46023.0) -> 46023 | E29: =IFERROR(__xludf.DUMMYFUNCTION("""COMPUTED_VALUE"""),"Cuidado") -> Cuidado | F29: =IFERROR(__xludf.DUMMYFUNCTION("""COMPUTED_VALUE"""),"Jefatura de Gobierno") -> Jefatura de Gobierno | G29: =IFERROR(__xludf.DUMMYFUNCTION("""COMPUTED_VALUE"""),"Finalizada") -> Finalizada | H29: 113032 | I29: 0 | J29: 5003 | K29: 0 | L29: 0 | M29: 0 | N29: 497431 | O29: 490986 | P29: 208233 | Q29: 1469 | R29: 12000 | S29: 11037 | T29: 2752 | U29: 2052 | V29: 0 | W29: 0 | X29: 0 | Y29: 0 | Z29: 0 | AA29: 0 | AB29: 0 | AC29: 0
A30: =IFERROR(__xludf.DUMMYFUNCTION("""COMPUTED_VALUE"""),"2424-DICFESGC") -> 2424-DICFESGC | B30: =IFERROR(__xludf.DUMMYFUNCTION("""COMPUTED_VALUE"""),"Verano en Buenos Aires 2026 | Generico") -> Verano en Buenos Aires 2026 | Generico | C30: =IFERROR(__xludf.DUMMYFUNCTION("""COMPUTED_VALUE"""),46029.0) -> 46029 | D30: =IFERROR(__xludf.DUMMYFUNCTION("""COMPUTED_VALUE"""),46081.0) -> 46081 | E30: =IFERROR(__xludf.DUMMYFUNCTION("""COMPUTED_VALUE"""),"Ciudad Atractiva") -> Ciudad Atractiva | F30: =IFERROR(__xludf.DUMMYFUNCTION("""COMPUTED_VALUE"""),"Festivales y Eventos") -> Festivales y Eventos | G30: =IFERROR(__xludf.DUMMYFUNCTION("""COMPUTED_VALUE"""),"Finalizada") -> Finalizada | H30: 32919907 | I30: 2721109 | J30: 164357 | K30: 3975434 | L30: 2.6766625 | M30: 8.2808335 | N30: 306526 | O30: 303199 | P30: 151566 | Q30: 7233 | R30: 0 | S30: 0 | T30: 0 | U30: 0 | V30: 0 | W30: 0 | X30: 0 | Y30: 0 | Z30: 0 | AA30: 0 | AB30: 0 | AC30: 0 | AD30: https://www.facebook.com/GCBA/posts/pfbid02PmAtvdzD176mjzPpPRZmFQTNXzNjqoKr7o9wByEVUtzkzYpigMPqtXRGysNDa6Wjl | AE30: Pieza
A31: =IFERROR(__xludf.DUMMYFUNCTION("""COMPUTED_VALUE"""),"2425-DICEPHGC") -> 2425-DICEPHGC | B31: =IFERROR(__xludf.DUMMYFUNCTION("""COMPUTED_VALUE"""),"Parques Iluminados M2") -> Parques Iluminados M2 | C31: =IFERROR(__xludf.DUMMYFUNCTION("""COMPUTED_VALUE"""),46163.0) -> 46163 | D31: =IFERROR(__xludf.DUMMYFUNCTION("""COMPUTED_VALUE"""),46190.0) -> 46190 | E31: =IFERROR(__xludf.DUMMYFUNCTION("""COMPUTED_VALUE"""),"M2") -> M2 | F31: =IFERROR(__xludf.DUMMYFUNCTION("""COMPUTED_VALUE"""),"Espacio Público e Higiene Urbana") -> Espacio Público e Higiene Urbana | G31: =IFERROR(__xludf.DUMMYFUNCTION("""COMPUTED_VALUE"""),"Finalizada") -> Finalizada | H31: 0 | I31: 0 | J31: 0 | K31: 0 | L31: 0 | M31: 0 | N31: 21456 | O31: 21233 | P31: 7139 | Q31: 191 | R31: 0 | S31: 0 | T31: 0 | U31: 0 | V31: 0 | W31: 0 | X31: 0 | Y31: 0 | Z31: 0 | AA31: 0 | AB31: 0 | AC31: 0 | AE31: Pieza
A32: =IFERROR(__xludf.DUMMYFUNCTION("""COMPUTED_VALUE"""),"2426-DICSALGC") -> 2426-DICSALGC | B32: =IFERROR(__xludf.DUMMYFUNCTION("""COMPUTED_VALUE"""),"Deploy HIS Ambulatorio") -> Deploy HIS Ambulatorio | C32: =IFERROR(__xludf.DUMMYFUNCTION("""COMPUTED_VALUE"""),46030.0) -> 46030 | D32: =IFERROR(__xludf.DUMMYFUNCTION("""COMPUTED_VALUE"""),46030.0) -> 46030 | E32: =IFERROR(__xludf.DUMMYFUNCTION("""COMPUTED_VALUE"""),"Cuidado") -> Cuidado | F32: =IFERROR(__xludf.DUMMYFUNCTION("""COMPUTED_VALUE"""),"Salud") -> Salud | G32: =IFERROR(__xludf.DUMMYFUNCTION("""COMPUTED_VALUE"""),"Finalizada") -> Finalizada | H32: 0 | I32: 0 | J32: 0 | K32: 0 | L32: 0 | M32: 0 | N32: 3471 | O32: 3443 | P32: 1477 | Q32: 169 | R32: 0 | S32: 0 | T32: 0 | U32: 0 | V32: 0 | W32: 0 | X32: 0 | Y32: 0 | Z32: 0 | AA32: 0 | AB32: 0 | AC32: 0 | AE32: Pieza
A33: =IFERROR(__xludf.DUMMYFUNCTION("""COMPUTED_VALUE"""),"2430-DICPCCVC") -> 2430-DICPCCVC | B33: =IFERROR(__xludf.DUMMYFUNCTION("""COMPUTED_VALUE"""),"DGPCyC | Verano 2026 - Misión Bomberos: Un día en la estación") -> DGPCyC | Verano 2026 - Misión Bomberos: Un día en la estación | C33: =IFERROR(__xludf.DUMMYFUNCTION("""COMPUTED_VALUE"""),46029.0) -> 46029 | D33: =IFERROR(__xludf.DUMMYFUNCTION("""COMPUTED_VALUE"""),46029.0) -> 46029 | E33: =IFERROR(__xludf.DUMMYFUNCTION("""COMPUTED_VALUE"""),"Cercanía") -> Cercanía | F33: =IFERROR(__xludf.DUMMYFUNCTION("""COMPUTED_VALUE"""),"Cercanía y PC") -> Cercanía y PC | G33: =IFERROR(__xludf.DUMMYFUNCTION("""COMPUTED_VALUE"""),"Finalizada") -> Finalizada | H33: 0 | I33: 0 | J33: 0 | K33: 0 | L33: 0 | M33: 0 | N33: 26990 | O33: 26313 | P33: 4518 | Q33: 419 | R33: 0 | S33: 0 | T33: 0 | U33: 0 | V33: 0 | W33: 0 | X33: 0 | Y33: 0 | Z33: 0 | AA33: 0 | AB33: 0 | AC33: 0 | AE33: Pieza
A34: =IFERROR(__xludf.DUMMYFUNCTION("""COMPUTED_VALUE"""),"2433-DICFESGC") -> 2433-DICFESGC | B34: =IFERROR(__xludf.DUMMYFUNCTION("""COMPUTED_VALUE"""),"Verano en la Ciudad | AftersBA") -> Verano en la Ciudad | AftersBA | C34: =IFERROR(__xludf.DUMMYFUNCTION("""COMPUTED_VALUE"""),46035.0) -> 46035 | D34: =IFERROR(__xludf.DUMMYFUNCTION("""COMPUTED_VALUE"""),46071.0) -> 46071 | E34: =IFERROR(__xludf.DUMMYFUNCTION("""COMPUTED_VALUE"""),"Ciudad Atractiva") -> Ciudad Atractiva | F34: =IFERROR(__xludf.DUMMYFUNCTION("""COMPUTED_VALUE"""),"Festivales y Eventos") -> Festivales y Eventos | G34: =IFERROR(__xludf.DUMMYFUNCTION("""COMPUTED_VALUE"""),"Finalizada") -> Finalizada | H34: 31715868 | I34: 6079572 | J34: 33441 | K34: 103786 | L34: 81.182549 | M34: 305.58908 | N34: 231781 | O34: 227305 | P34: 76967 | Q34: 3329 | R34: 0 | S34: 0 | T34: 0 | U34: 0 | V34: 0 | W34: 0 | X34: 0 | Y34: 0 | Z34: 0 | AA34: 0 | AB34: 0 | AC34: 0 | AD34: https://www.facebook.com/reel/1401103571662551 | AE34: Pieza
A35: =IFERROR(__xludf.DUMMYFUNCTION("""COMPUTED_VALUE"""),"2434-DICFESGC") -> 2434-DICFESGC | B35: =IFERROR(__xludf.DUMMYFUNCTION("""COMPUTED_VALUE"""),"Verano en la Ciudad | Billboard Summer") -> Verano en la Ciudad | Billboard Summer | C35: =IFERROR(__xludf.DUMMYFUNCTION("""COMPUTED_VALUE"""),46031.0) -> 46031 | D35: =IFERROR(__xludf.DUMMYFUNCTION("""COMPUTED_VALUE"""),46039.0) -> 46039 | E35: =IFERROR(__xludf.DUMMYFUNCTION("""COMPUTED_VALUE"""),"Ciudad Atractiva") -> Ciudad Atractiva | F35: =IFERROR(__xludf.DUMMYFUNCTION("""COMPUTED_VALUE"""),"Festivales y Eventos") -> Festivales y Eventos | G35: =IFERROR(__xludf.DUMMYFUNCTION("""COMPUTED_VALUE"""),"Finalizada") -> Finalizada | H35: 12944042 | I35: 2874187 | J35: 12481 | K35: 29161 | L35: 137.44429 | M35: 443.88197 | N35: 175380 | O35: 172038 | P35: 58466 | Q35: 3201 | R35: 0 | S35: 0 | T35: 0 | U35: 0 | V35: 0 | W35: 0 | X35: 0 | Y35: 0 | Z35: 0 | AA35: 0 | AB35: 0 | AC35: 0 | AD35: https://www.facebook.com/reel/1385888349747054/ | AE35: Pieza
A36: =IFERROR(__xludf.DUMMYFUNCTION("""COMPUTED_VALUE"""),"2435-DICFESGC") -> 2435-DICFESGC | B36: =IFERROR(__xludf.DUMMYFUNCTION("""COMPUTED_VALUE"""),"Verano en la Ciudad | Atardeceres en los parques") -> Verano en la Ciudad | Atardeceres en los parques | C36: =IFERROR(__xludf.DUMMYFUNCTION("""COMPUTED_VALUE"""),46041.0) -> 46041 | D36: =IFERROR(__xludf.DUMMYFUNCTION("""COMPUTED_VALUE"""),46062.0) -> 46062 | E36: =IFERROR(__xludf.DUMMYFUNCTION("""COMPUTED_VALUE"""),"Ciudad Atractiva") -> Ciudad Atractiva | F36: =IFERROR(__xludf.DUMMYFUNCTION("""COMPUTED_VALUE"""),"Festivales y Eventos") -> Festivales y Eventos | G36: =IFERROR(__xludf.DUMMYFUNCTION("""COMPUTED_VALUE"""),"Finalizada") -> Finalizada | H36: 18780836 | I36: 4407686 | J36: 26564 | K36: 2036212 | L36: 2.9967616 | M36: 9.2234188 | N36: 107518 | O36: 86557 | P36: 31980 | Q36: 2402 | R36: 6925 | S36: 6908 | T36: 1374 | U36: 1022 | V36: 0 | W36: 0 | X36: 0 | Y36: 0 | Z36: 0 | AA36: 0 | AB36: 0 | AC36: 0 | AD36: https://www.facebook.com/GCBA/posts/pfbid0rLEuW4M93zccXsLKxEbAgdx71UvEEJJusTpaAfZzdSBaQDr7KZx36ckPuiwG1Rhql | AE36: Pieza
A37: =IFERROR(__xludf.DUMMYFUNCTION("""COMPUTED_VALUE"""),"2437-DICFESGC") -> 2437-DICFESGC | B37: =IFERROR(__xludf.DUMMYFUNCTION("""COMPUTED_VALUE"""),"Verano en la Ciudad | Verano en las plazas") -> Verano en la Ciudad | Verano en las plazas | C37: =IFERROR(__xludf.DUMMYFUNCTION("""COMPUTED_VALUE"""),46038.0) -> 46038 | D37: =IFERROR(__xludf.DUMMYFUNCTION("""COMPUTED_VALUE"""),46073.0) -> 46073 | E37: =IFERROR(__xludf.DUMMYFUNCTION("""COMPUTED_VALUE"""),"Ciudad Atractiva") -> Ciudad Atractiva | F37: =IFERROR(__xludf.DUMMYFUNCTION("""COMPUTED_VALUE"""),"Festivales y Eventos") -> Festivales y Eventos | G37: =IFERROR(__xludf.DUMMYFUNCTION("""COMPUTED_VALUE"""),"Finalizada") -> Finalizada | H37: 18930747 | I37: 5099312 | J37: 20844 | K37: 1292752 | L37: 5.5283542 | M37: 14.643758 | N37: 710718 | O37: 674580 | P37: 197102 | Q37: 16421 | R37: 0 | S37: 0 | T37: 0 | U37: 0 | V37: 0 | W37: 0 | X37: 0 | Y37: 0 | Z37: 0 | AA37: 0 | AB37: 0 | AC37: 0 | AD37: https://www.facebook.com/GCBA/posts/pfbid032UmvaRZ3eAJNRC4zHziYpyXVaPbbTucP4LKQNEh1BSxa3mTrzNz6mZGgDzRqYkTel | AE37: Pieza
A38: =IFERROR(__xludf.DUMMYFUNCTION("""COMPUTED_VALUE"""),"2439-DICINFGC") -> 2439-DICINFGC | B38: =IFERROR(__xludf.DUMMYFUNCTION("""COMPUTED_VALUE""")," Infraestructura I Bus Eléctricos: extensión recorrido") -> Infraestructura I Bus Eléctricos: extensión recorrido | C38: =IFERROR(__xludf.DUMMYFUNCTION("""COMPUTED_VALUE"""),46028.0) -> 46028 | D38: =IFERROR(__xludf.DUMMYFUNCTION("""COMPUTED_VALUE"""),46042.0) -> 46042 | E38: =IFERROR(__xludf.DUMMYFUNCTION("""COMPUTED_VALUE"""),"Movilidad") -> Movilidad | F38: =IFERROR(__xludf.DUMMYFUNCTION("""COMPUTED_VALUE"""),"Infraestructura") -> Infraestructura | G38: =IFERROR(__xludf.DUMMYFUNCTION("""COMPUTED_VALUE"""),"Finalizada") -> Finalizada | H38: 665162 | I38: 3616 | J38: 2743 | K38: 355350 | L38: 1.8718503 | M38: 1.8718503 | N38: 90056 | O38: 88895 | P38: 43812 | Q38: 2567 | R38: 0 | S38: 0 | T38: 0 | U38: 0 | V38: 0 | W38: 0 | X38: 0 | Y38: 0 | Z38: 0 | AA38: 0 | AB38: 0 | AC38: 0 | AD38: https://www.facebook.com/GCBA/posts/pfbid08jZno8hyH4wUURfHDj5eKgWYFcmdn1Lqh1sjbw1zmwZJ4dSZGEmpAeit2EdCjTLal | AE38: Pieza
A39: =IFERROR(__xludf.DUMMYFUNCTION("""COMPUTED_VALUE"""),"2441-DICINFGC") -> 2441-DICINFGC | B39: =IFERROR(__xludf.DUMMYFUNCTION("""COMPUTED_VALUE"""),"Infraestructura I Obras M2: Trambus ENERO") -> Infraestructura I Obras M2: Trambus ENERO | C39: =IFERROR(__xludf.DUMMYFUNCTION("""COMPUTED_VALUE"""),46035.0) -> 46035 | D39: =IFERROR(__xludf.DUMMYFUNCTION("""COMPUTED_VALUE"""),46053.0) -> 46053 | E39: =IFERROR(__xludf.DUMMYFUNCTION("""COMPUTED_VALUE"""),"Movilidad") -> Movilidad | F39: =IFERROR(__xludf.DUMMYFUNCTION("""COMPUTED_VALUE"""),"Infraestructura") -> Infraestructura | G39: =IFERROR(__xludf.DUMMYFUNCTION("""COMPUTED_VALUE"""),"Finalizada") -> Finalizada | H39: 3270390 | I39: 0 | J39: 47102 | K39: 469739 | L39: 2.0681974 | M39: 6.9621428 | N39: 56667 | O39: 55627 | P39: 19152 | Q39: 1989 | R39: 0 | S39: 0 | T39: 0 | U39: 0 | V39: 0 | W39: 0 | X39: 0 | Y39: 0 | Z39: 0 | AA39: 0 | AB39: 0 | AC39: 0 | AD39: https://www.facebook.com/GCBA/posts/pfbid0nA1q3xBcy1eJcYdmUe5hTkrG2zrbURY6VnDCqEubzKtTg6UhWBiGjhgYWJQUsK86l | AE39: Pieza
A40: =IFERROR(__xludf.DUMMYFUNCTION("""COMPUTED_VALUE"""),"2443-DICNEWAN") -> 2443-DICNEWAN | B40: =IFERROR(__xludf.DUMMYFUNCTION("""COMPUTED_VALUE"""),"Acciones de la Ciudad ante el calor extremo") -> Acciones de la Ciudad ante el calor extremo | C40: =IFERROR(__xludf.DUMMYFUNCTION("""COMPUTED_VALUE"""),46027.0) -> 46027 | D40: =IFERROR(__xludf.DUMMYFUNCTION("""COMPUTED_VALUE"""),46035.0) -> 46035 | E40: =IFERROR(__xludf.DUMMYFUNCTION("""COMPUTED_VALUE"""),"Cuidado") -> Cuidado | F40: =IFERROR(__xludf.DUMMYFUNCTION("""COMPUTED_VALUE"""),"Anuncios y Newsletter") -> Anuncios y Newsletter | G40: =IFERROR(__xludf.DUMMYFUNCTION("""COMPUTED_VALUE"""),"Finalizada") -> Finalizada | H40: 8154163 | I40: 0 | J40: 49108 | K40: 682062 | L40: 1.5975703 | M40: 11.955164 | N40: 236590 | O40: 233694 | P40: 54587 | Q40: 2742 | R40: 0 | S40: 0 | T40: 0 | U40: 0 | V40: 0 | W40: 0 | X40: 0 | Y40: 0 | Z40: 0 | AA40: 0 | AB40: 0 | AC40: 0 | AD40: https://www.facebook.com/GCBA/posts/pfbid0N5sbH3engzLHtbfZQM61dN6d9zBMxwsp4N1bpfX76sx6bnCZy4398mqDoXuTfdX5l
A41: =IFERROR(__xludf.DUMMYFUNCTION("""COMPUTED_VALUE"""),"2444-DICINFGC") -> 2444-DICINFGC | B41: =IFERROR(__xludf.DUMMYFUNCTION("""COMPUTED_VALUE"""),"Infraestructura I Cortes en AU Dellepiane por obras") -> Infraestructura I Cortes en AU Dellepiane por obras | C41: =IFERROR(__xludf.DUMMYFUNCTION("""COMPUTED_VALUE"""),46021.0) -> 46021 | D41: =IFERROR(__xludf.DUMMYFUNCTION("""COMPUTED_VALUE"""),46034.0) -> 46034 | E41: =IFERROR(__xludf.DUMMYFUNCTION("""COMPUTED_VALUE"""),"Movilidad") -> Movilidad | F41: =IFERROR(__xludf.DUMMYFUNCTION("""COMPUTED_VALUE"""),"Infraestructura") -> Infraestructura | G41: =IFERROR(__xludf.DUMMYFUNCTION("""COMPUTED_VALUE"""),"Finalizada") -> Finalizada | H41: 210936 | I41: 0 | J41: 31 | K41: 140179 | L41: 1.1381591 | M41: 1.5047618 | N41: 80433 | O41: 79263 | P41: 31500 | Q41: 336 | R41: 0 | S41: 0 | T41: 0 | U41: 0 | V41: 0 | W41: 0 | X41: 0 | Y41: 0 | Z41: 0 | AA41: 0 | AB41: 0 | AC41: 0 | AD41: https://fb.me/adspreview/facebook/1RMCueLZDYjPeIW | AE41: Pieza
A42: =IFERROR(__xludf.DUMMYFUNCTION("""COMPUTED_VALUE"""),"2445-DICPCCVC") -> 2445-DICPCCVC | B42: =IFERROR(__xludf.DUMMYFUNCTION("""COMPUTED_VALUE"""),"Verano 2026 - Expedicion botanica") -> Verano 2026 - Expedicion botanica | C42: =IFERROR(__xludf.DUMMYFUNCTION("""COMPUTED_VALUE"""),46034.0) -> 46034 | D42: =IFERROR(__xludf.DUMMYFUNCTION("""COMPUTED_VALUE"""),46034.0) -> 46034 | E42: =IFERROR(__xludf.DUMMYFUNCTION("""COMPUTED_VALUE"""),"Cercanía") -> Cercanía | F42: =IFERROR(__xludf.DUMMYFUNCTION("""COMPUTED_VALUE"""),"Cercanía y PC") -> Cercanía y PC | G42: =IFERROR(__xludf.DUMMYFUNCTION("""COMPUTED_VALUE"""),"Finalizada") -> Finalizada | H42: 0 | I42: 0 | J42: 0 | K42: 0 | L42: 0 | M42: 0 | N42: 19382 | O42: 19018 | P42: 6067 | Q42: 215 | R42: 0 | S42: 0 | T42: 0 | U42: 0 | V42: 0 | W42: 0 | X42: 0 | Y42: 0 | Z42: 0 | AA42: 0 | AB42: 0 | AC42: 0 | AE42: Pieza
A43: =IFERROR(__xludf.DUMMYFUNCTION("""COMPUTED_VALUE"""),"2447-DICPCCVC") -> 2447-DICPCCVC | B43: =IFERROR(__xludf.DUMMYFUNCTION("""COMPUTED_VALUE"""),"Verano 2026 - La Gran Aventura del Reciclaje | Enero") -> Verano 2026 - La Gran Aventura del Reciclaje | Enero | C43: =IFERROR(__xludf.DUMMYFUNCTION("""COMPUTED_VALUE"""),46031.0) -> 46031 | D43: =IFERROR(__xludf.DUMMYFUNCTION("""COMPUTED_VALUE"""),46031.0) -> 46031 | E43: =IFERROR(__xludf.DUMMYFUNCTION("""COMPUTED_VALUE"""),"Cercanía") -> Cercanía | F43: =IFERROR(__xludf.DUMMYFUNCTION("""COMPUTED_VALUE"""),"Cercanía y PC") -> Cercanía y PC | G43: =IFERROR(__xludf.DUMMYFUNCTION("""COMPUTED_VALUE"""),"Finalizada") -> Finalizada | H43: 0 | I43: 0 | J43: 0 | K43: 0 | L43: 0 | M43: 0 | N43: 22406 | O43: 21763 | P43: 2883 | Q43: 56 | R43: 0 | S43: 0 | T43: 0 | U43: 0 | V43: 0 | W43: 0 | X43: 0 | Y43: 0 | Z43: 0 | AA43: 0 | AB43: 0 | AC43: 0 | AE43: Pieza
A44: =IFERROR(__xludf.DUMMYFUNCTION("""COMPUTED_VALUE"""),"2450-ENEJDGAG") -> 2450-ENEJDGAG | B44: =IFERROR(__xludf.DUMMYFUNCTION("""COMPUTED_VALUE"""),"RDV JM - Boedo 9/1") -> RDV JM - Boedo 9/1 | C44: =IFERROR(__xludf.DUMMYFUNCTION("""COMPUTED_VALUE"""),46024.0) -> 46024 | D44: =IFERROR(__xludf.DUMMYFUNCTION("""COMPUTED_VALUE"""),46052.0) -> 46052 | E44: =IFERROR(__xludf.DUMMYFUNCTION("""COMPUTED_VALUE"""),"Cercanía") -> Cercanía | F44: =IFERROR(__xludf.DUMMYFUNCTION("""COMPUTED_VALUE"""),"Jefatura de Gobierno") -> Jefatura de Gobierno | G44: =IFERROR(__xludf.DUMMYFUNCTION("""COMPUTED_VALUE"""),"Finalizada") -> Finalizada | H44: 1331244 | I44: 773019 | J44: 4155 | K44: 79990 | L44: 4.04008 | M44: 16.64263 | N44: 22300 | O44: 21947 | P44: 5124 | Q44: 185 | R44: 10319 | S44: 9805 | T44: 2224 | U44: 1648 | V44: 12049 | W44: 12049 | X44: 11592 | Y44: 4731 | Z44: 49 | AA44: 0 | AB44: 0 | AC44: 0 | AD44: https://www.facebook.com/reel/850462247854341 | AE44: Pieza
A45: =IFERROR(__xludf.DUMMYFUNCTION("""COMPUTED_VALUE"""),"2451-ENEPCCVC") -> 2451-ENEPCCVC | B45: =IFERROR(__xludf.DUMMYFUNCTION("""COMPUTED_VALUE"""),"Participación Ciudadana - Verano en la Ciudad (Pauta RRSS)") -> Participación Ciudadana - Verano en la Ciudad (Pauta RRSS) | C45: =IFERROR(__xludf.DUMMYFUNCTION("""COMPUTED_VALUE"""),46027.0) -> 46027 | D45: =IFERROR(__xludf.DUMMYFUNCTION("""COMPUTED_VALUE"""),46057.0) -> 46057 | E45: =IFERROR(__xludf.DUMMYFUNCTION("""COMPUTED_VALUE"""),"Cercanía") -> Cercanía | F45: =IFERROR(__xludf.DUMMYFUNCTION("""COMPUTED_VALUE"""),"Cercanía y PC") -> Cercanía y PC | G45: =IFERROR(__xludf.DUMMYFUNCTION("""COMPUTED_VALUE"""),"Finalizada") -> Finalizada | H45: 2493536 | I45: 0 | J45: 1632 | K45: 655062 | L45: 3.8065649 | M45: 3.8065649 | N45: 0 | O45: 0 | P45: 0 | Q45: 0 | R45: 0 | S45: 0 | T45: 0 | U45: 0 | V45: 0 | W45: 0 | X45: 0 | Y45: 0 | Z45: 0 | AA45: 0 | AB45: 0 | AC45: 0 | AD45: https://www.facebook.com/100064853673908/posts/1304262748412169/
A46: =IFERROR(__xludf.DUMMYFUNCTION("""COMPUTED_VALUE"""),"2453-ENEPCCVC") -> 2453-ENEPCCVC | B46: =IFERROR(__xludf.DUMMYFUNCTION("""COMPUTED_VALUE"""),"Verano 2026 - CIFA para chicos") -> Verano 2026 - CIFA para chicos | C46: =IFERROR(__xludf.DUMMYFUNCTION("""COMPUTED_VALUE"""),46043.0) -> 46043 | D46: =IFERROR(__xludf.DUMMYFUNCTION("""COMPUTED_VALUE"""),46049.0) -> 46049 | E46: =IFERROR(__xludf.DUMMYFUNCTION("""COMPUTED_VALUE"""),"Cercanía") -> Cercanía | F46: =IFERROR(__xludf.DUMMYFUNCTION("""COMPUTED_VALUE"""),"Cercanía y PC") -> Cercanía y PC | G46: =IFERROR(__xludf.DUMMYFUNCTION("""COMPUTED_VALUE"""),"Finalizada") -> Finalizada | H46: 0 | I46: 0 | J46: 0 | K46: 0 | L46: 0 | M46: 0 | N46: 65448 | O46: 64031 | P46: 15667 | Q46: 168 | R46: 0 | S46: 0 | T46: 0 | U46: 0 | V46: 0 | W46: 0 | X46: 0 | Y46: 0 | Z46: 0 | AA46: 0 | AB46: 0 | AC46: 0 | AE46: Pieza
A47: =IFERROR(__xludf.DUMMYFUNCTION("""COMPUTED_VALUE"""),"2454-ENEPCCVC") -> 2454-ENEPCCVC | B47: =IFERROR(__xludf.DUMMYFUNCTION("""COMPUTED_VALUE"""),"Verano 2026 - Aventura en el aire") -> Verano 2026 - Aventura en el aire | C47: =IFERROR(__xludf.DUMMYFUNCTION("""COMPUTED_VALUE"""),46038.0) -> 46038 | D47: =IFERROR(__xludf.DUMMYFUNCTION("""COMPUTED_VALUE"""),46038.0) -> 46038 | E47: =IFERROR(__xludf.DUMMYFUNCTION("""COMPUTED_VALUE"""),"Cercanía") -> Cercanía | F47: =IFERROR(__xludf.DUMMYFUNCTION("""COMPUTED_VALUE"""),"Cercanía y PC") -> Cercanía y PC | G47: =IFERROR(__xludf.DUMMYFUNCTION("""COMPUTED_VALUE"""),"Finalizada") -> Finalizada | H47: 0 | I47: 0 | J47: 0 | K47: 0 | L47: 0 | M47: 0 | N47: 33944 | O47: 33452 | P47: 13502 | Q47: 579 | R47: 0 | S47: 0 | T47: 0 | U47: 0 | V47: 0 | W47: 0 | X47: 0 | Y47: 0 | Z47: 0 | AA47: 0 | AB47: 0 | AC47: 0 | AE47: Pieza
A48: =IFERROR(__xludf.DUMMYFUNCTION("""COMPUTED_VALUE"""),"2456-ENEPCCVC") -> 2456-ENEPCCVC | B48: =IFERROR(__xludf.DUMMYFUNCTION("""COMPUTED_VALUE"""),"Dejá tus rueditas") -> Dejá tus rueditas | C48: =IFERROR(__xludf.DUMMYFUNCTION("""COMPUTED_VALUE"""),46035.0) -> 46035 | D48: =IFERROR(__xludf.DUMMYFUNCTION("""COMPUTED_VALUE"""),46035.0) -> 46035 | E48: =IFERROR(__xludf.DUMMYFUNCTION("""COMPUTED_VALUE"""),"Cercanía") -> Cercanía | F48: =IFERROR(__xludf.DUMMYFUNCTION("""COMPUTED_VALUE"""),"Cercanía y PC") -> Cercanía y PC | G48: =IFERROR(__xludf.DUMMYFUNCTION("""COMPUTED_VALUE"""),"Finalizada") -> Finalizada | H48: 0 | I48: 0 | J48: 0 | K48: 0 | L48: 0 | M48: 0 | N48: 25908 | O48: 25161 | P48: 3454 | Q48: 147 | R48: 0 | S48: 0 | T48: 0 | U48: 0 | V48: 0 | W48: 0 | X48: 0 | Y48: 0 | Z48: 0 | AA48: 0 | AB48: 0 | AC48: 0 | AE48: Pieza
A49: =IFERROR(__xludf.DUMMYFUNCTION("""COMPUTED_VALUE"""),"2457-ENEPCCVC") -> 2457-ENEPCCVC | B49: =IFERROR(__xludf.DUMMYFUNCTION("""COMPUTED_VALUE"""),"Verano 2026 - Exploradores del Ecoparque") -> Verano 2026 - Exploradores del Ecoparque | C49: =IFERROR(__xludf.DUMMYFUNCTION("""COMPUTED_VALUE"""),46036.0) -> 46036 | D49: =IFERROR(__xludf.DUMMYFUNCTION("""COMPUTED_VALUE"""),46036.0) -> 46036 | E49: =IFERROR(__xludf.DUMMYFUNCTION("""COMPUTED_VALUE"""),"Cercanía") -> Cercanía | F49: =IFERROR(__xludf.DUMMYFUNCTION("""COMPUTED_VALUE"""),"Cercanía y PC") -> Cercanía y PC | G49: =IFERROR(__xludf.DUMMYFUNCTION("""COMPUTED_VALUE"""),"Finalizada") -> Finalizada | H49: 0 | I49: 0 | J49: 0 | K49: 0 | L49: 0 | M49: 0 | N49: 36289 | O49: 35904 | P49: 19164 | Q49: 240 | R49: 0 | S49: 0 | T49: 0 | U49: 0 | V49: 0 | W49: 0 | X49: 0 | Y49: 0 | Z49: 0 | AA49: 0 | AB49: 0 | AC49: 0 | AE49: Pieza
A50: =IFERROR(__xludf.DUMMYFUNCTION("""COMPUTED_VALUE"""),"2458-ENESEGGC") -> 2458-ENESEGGC | B50: =IFERROR(__xludf.DUMMYFUNCTION("""COMPUTED_VALUE"""),"Campaña GCBA I Seguridad I Desalojo edificio San Telmo") -> Campaña GCBA I Seguridad I Desalojo edificio San Telmo | C50: =IFERROR(__xludf.DUMMYFUNCTION("""COMPUTED_VALUE"""),46029.0) -> 46029 | D50: =IFERROR(__xludf.DUMMYFUNCTION("""COMPUTED_VALUE"""),46044.0) -> 46044 | E50: =IFERROR(__xludf.DUMMYFUNCTION("""COMPUTED_VALUE"""),"M2") -> M2 | F50: =IFERROR(__xludf.DUMMYFUNCTION("""COMPUTED_VALUE"""),"Seguridad") -> Seguridad | G50: =IFERROR(__xludf.DUMMYFUNCTION("""COMPUTED_VALUE"""),"Finalizada") -> Finalizada | H50: 1958412 | I50: 1314287 | J50: 1288 | K50: 208110 | L50: 1.7622507 | M50: 9.4104656 | N50: 126455 | O50: 124209 | P50: 32515 | Q50: 1193 | R50: 0 | S50: 0 | T50: 0 | U50: 0 | V50: 0 | W50: 0 | X50: 0 | Y50: 0 | Z50: 0 | AA50: 0 | AB50: 0 | AC50: 0 | AD50: facebook.com/reel/654304614371554/ | AE50: Pieza
A51: =IFERROR(__xludf.DUMMYFUNCTION("""COMPUTED_VALUE"""),"2459-ENESEGGC") -> 2459-ENESEGGC | B51: =IFERROR(__xludf.DUMMYFUNCTION("""COMPUTED_VALUE"""),"Campaña GCBA I Seguridad I Desalojo predio Parque Avellaneda") -> Campaña GCBA I Seguridad I Desalojo predio Parque Avellaneda | C51: =IFERROR(__xludf.DUMMYFUNCTION("""COMPUTED_VALUE"""),46030.0) -> 46030 | D51: =IFERROR(__xludf.DUMMYFUNCTION("""COMPUTED_VALUE"""),46045.0) -> 46045 | E51: =IFERROR(__xludf.DUMMYFUNCTION("""COMPUTED_VALUE"""),"M2") -> M2 | F51: =IFERROR(__xludf.DUMMYFUNCTION("""COMPUTED_VALUE"""),"Seguridad") -> Seguridad | G51: =IFERROR(__xludf.DUMMYFUNCTION("""COMPUTED_VALUE"""),"Finalizada") -> Finalizada | H51: 2545129 | I51: 1397894 | J51: 2481 | K51: 550772 | L51: 1.8618212 | M51: 4.621021 | N51: 199955 | O51: 196224 | P51: 45064 | Q51: 964 | R51: 0 | S51: 0 | T51: 0 | U51: 0 | V51: 0 | W51: 0 | X51: 0 | Y51: 0 | Z51: 0 | AA51: 0 | AB51: 0 | AC51: 0 | AD51: facebook.com/reel/1964189401115594/ | AE51: Pieza
A52: =IFERROR(__xludf.DUMMYFUNCTION("""COMPUTED_VALUE"""),"2460-ENEFESGC") -> 2460-ENEFESGC | B52: =IFERROR(__xludf.DUMMYFUNCTION("""COMPUTED_VALUE"""),"Campaña verano en la ciudad | Verano en los anfiteatros") -> Campaña verano en la ciudad | Verano en los anfiteatros | C52: =IFERROR(__xludf.DUMMYFUNCTION("""COMPUTED_VALUE"""),46057.0) -> 46057 | D52: =IFERROR(__xludf.DUMMYFUNCTION("""COMPUTED_VALUE"""),46080.0) -> 46080 | E52: =IFERROR(__xludf.DUMMYFUNCTION("""COMPUTED_VALUE"""),"Ciudad Atractiva") -> Ciudad Atractiva | F52: =IFERROR(__xludf.DUMMYFUNCTION("""COMPUTED_VALUE"""),"Festivales y Eventos") -> Festivales y Eventos | G52: =IFERROR(__xludf.DUMMYFUNCTION("""COMPUTED_VALUE"""),"Finalizada") -> Finalizada | H52: 10431799 | I52: 0 | J52: 45286 | K52: 297850 | L52: 8.6866577 | M52: 35.023666 | N52: 165205 | O52: 161928 | P52: 45115 | Q52: 4265 | R52: 0 | S52: 0 | T52: 0 | U52: 0 | V52: 0 | W52: 0 | X52: 0 | Y52: 0 | Z52: 0 | AA52: 0 | AB52: 0 | AC52: 0 | AE52: Pieza
A53: =IFERROR(__xludf.DUMMYFUNCTION("""COMPUTED_VALUE"""),"2463-ENETURGC") -> 2463-ENETURGC | B53: =IFERROR(__xludf.DUMMYFUNCTION("""COMPUTED_VALUE"""),"Elegí Argentina 2026 | Registro de Prestadores Turísticos | Viernes 9/1") -> Elegí Argentina 2026 | Registro de Prestadores Turísticos | Viernes 9/1 | C53: =IFERROR(__xludf.DUMMYFUNCTION("""COMPUTED_VALUE"""),46031.0) -> 46031 | D53: =IFERROR(__xludf.DUMMYFUNCTION("""COMPUTED_VALUE"""),46031.0) -> 46031 | E53: =IFERROR(__xludf.DUMMYFUNCTION("""COMPUTED_VALUE"""),"Otros") -> Otros | F53: =IFERROR(__xludf.DUMMYFUNCTION("""COMPUTED_VALUE"""),"Turismo") -> Turismo | G53: =IFERROR(__xludf.DUMMYFUNCTION("""COMPUTED_VALUE"""),"Finalizada") -> Finalizada | H53: 0 | I53: 0 | J53: 0 | K53: 0 | L53: 0 | M53: 0 | N53: 575 | O53: 552 | P53: 217 | Q53: 52 | R53: 0 | S53: 0 | T53: 0 | U53: 0 | V53: 0 | W53: 0 | X53: 0 | Y53: 0 | Z53: 0 | AA53: 0 | AB53: 0 | AC53: 0 | AE53: Pieza
A54: =IFERROR(__xludf.DUMMYFUNCTION("""COMPUTED_VALUE"""),"2464-ENEINFGC") -> 2464-ENEINFGC | B54: =IFERROR(__xludf.DUMMYFUNCTION("""COMPUTED_VALUE"""),"CAMPAÑA GCBA | INFRAESTRUCTURA | PBN García Lorca: durante de obra") -> CAMPAÑA GCBA | INFRAESTRUCTURA | PBN García Lorca: durante de obra | C54: =IFERROR(__xludf.DUMMYFUNCTION("""COMPUTED_VALUE"""),46036.0) -> 46036 | D54: =IFERROR(__xludf.DUMMYFUNCTION("""COMPUTED_VALUE"""),46056.0) -> 46056 | E54: =IFERROR(__xludf.DUMMYFUNCTION("""COMPUTED_VALUE"""),"Movilidad") -> Movilidad | F54: =IFERROR(__xludf.DUMMYFUNCTION("""COMPUTED_VALUE"""),"Infraestructura") -> Infraestructura | G54: =IFERROR(__xludf.DUMMYFUNCTION("""COMPUTED_VALUE"""),"Finalizada") -> Finalizada | H54: 4636754 | I54: 23533 | J54: 13640 | K54: 484653 | L54: 1.4793739 | M54: 9.5671625 | N54: 71838 | O54: 70767 | P54: 28370 | Q54: 747 | R54: 0 | S54: 0 | T54: 0 | U54: 0 | V54: 0 | W54: 0 | X54: 0 | Y54: 0 | Z54: 0 | AA54: 0 | AB54: 0 | AC54: 0 | AD54: https://www.facebook.com/GCBA/posts/pfbid036pqFXR7zAF8PvFnxngTEwxPE9PqKmWq4AHHELyLosNtsxKY2jxKJRGQJxGk3ecSbl | AE54: Pieza
A55: =IFERROR(__xludf.DUMMYFUNCTION("""COMPUTED_VALUE"""),"2465-ENEJDGAG") -> 2465-ENEJDGAG | B55: =IFERROR(__xludf.DUMMYFUNCTION("""COMPUTED_VALUE"""),"Cafe JM - Puerto Madero 16/1") -> Cafe JM - Puerto Madero 16/1 | C55: =IFERROR(__xludf.DUMMYFUNCTION("""COMPUTED_VALUE"""),46031.0) -> 46031 | D55: =IFERROR(__xludf.DUMMYFUNCTION("""COMPUTED_VALUE"""),46053.0) -> 46053 | E55: =IFERROR(__xludf.DUMMYFUNCTION("""COMPUTED_VALUE"""),"Cercanía") -> Cercanía | F55: =IFERROR(__xludf.DUMMYFUNCTION("""COMPUTED_VALUE"""),"Jefatura de Gobierno") -> Jefatura de Gobierno | G55: =IFERROR(__xludf.DUMMYFUNCTION("""COMPUTED_VALUE"""),"Finalizada") -> Finalizada | H55: 2758449 | I55: 903317 | J55: 4118 | K55: 31114 | L55: 2.8909494 | M55: 88.6562 | N55: 2567 | O55: 2526 | P55: 990 | Q55: 81 | R55: 0 | S55: 0 | T55: 0 | U55: 0 | V55: 0 | W55: 0 | X55: 0 | Y55: 0 | Z55: 0 | AA55: 0 | AB55: 0 | AC55: 0 | AD55: https://www.facebook.com/GCBA/posts/pfbid0BsWeHieuJG1uGtxTuMBe5GYGU77PsY829qhF8HeGWpSsWmLpxTT9CTzWTUa3pxfbl | AE55: Pieza
A56: =IFERROR(__xludf.DUMMYFUNCTION("""COMPUTED_VALUE"""),"2466-ENEFESGC") -> 2466-ENEFESGC | B56: =IFERROR(__xludf.DUMMYFUNCTION("""COMPUTED_VALUE"""),"Verano en la Ciudad | Parque de la Ciudad") -> Verano en la Ciudad | Parque de la Ciudad | C56: =IFERROR(__xludf.DUMMYFUNCTION("""COMPUTED_VALUE"""),46041.0) -> 46041 | D56: =IFERROR(__xludf.DUMMYFUNCTION("""COMPUTED_VALUE"""),46066.0) -> 46066 | E56: =IFERROR(__xludf.DUMMYFUNCTION("""COMPUTED_VALUE"""),"Ciudad Atractiva") -> Ciudad Atractiva | F56: =IFERROR(__xludf.DUMMYFUNCTION("""COMPUTED_VALUE"""),"Festivales y Eventos") -> Festivales y Eventos | G56: =IFERROR(__xludf.DUMMYFUNCTION("""COMPUTED_VALUE"""),"Finalizada") -> Finalizada | H56: 7612586 | I56: 230619 | J56: 9111 | L56: 0 | M56: 0 | N56: 243518 | O56: 238203 | P56: 60526 | Q56: 2710 | R56: 0 | S56: 0 | T56: 0 | U56: 0 | V56: 0 | W56: 0 | X56: 0 | Y56: 0 | Z56: 0 | AA56: 0 | AB56: 0 | AC56: 0 | AD56: https://www.facebook.com/reel/1985348935347886 | AE56: Pieza
A57: =IFERROR(__xludf.DUMMYFUNCTION("""COMPUTED_VALUE"""),"2467-ENEFESGC") -> 2467-ENEFESGC | B57: =IFERROR(__xludf.DUMMYFUNCTION("""COMPUTED_VALUE"""),"Verano en la Ciudad | Verano Joven BA enero") -> Verano en la Ciudad | Verano Joven BA enero | C57: =IFERROR(__xludf.DUMMYFUNCTION("""COMPUTED_VALUE"""),46050.0) -> 46050 | D57: =IFERROR(__xludf.DUMMYFUNCTION("""COMPUTED_VALUE"""),46053.0) -> 46053 | E57: =IFERROR(__xludf.DUMMYFUNCTION("""COMPUTED_VALUE"""),"Ciudad Atractiva") -> Ciudad Atractiva | F57: =IFERROR(__xludf.DUMMYFUNCTION("""COMPUTED_VALUE"""),"Festivales y Eventos") -> Festivales y Eventos | G57: =IFERROR(__xludf.DUMMYFUNCTION("""COMPUTED_VALUE"""),"Finalizada") -> Finalizada | H57: 13260814 | I57: 1700132 | J57: 13721 | K57: 176068 | L57: 40.108441 | M57: 75.316435 | N57: 191896 | O57: 188174 | P57: 63834 | Q57: 1357 | R57: 0 | S57: 0 | T57: 0 | U57: 0 | V57: 0 | W57: 0 | X57: 0 | Y57: 0 | Z57: 0 | AA57: 0 | AB57: 0 | AC57: 0 | AE57: Pieza
A58: =IFERROR(__xludf.DUMMYFUNCTION("""COMPUTED_VALUE"""),"2468-ENEINFGC") -> 2468-ENEINFGC | B58: =IFERROR(__xludf.DUMMYFUNCTION("""COMPUTED_VALUE"""),"CAMPAÑA GCBA | INFRAESTRUCTURA | Cierre estación Piedras - Línea A | 12/1") -> CAMPAÑA GCBA | INFRAESTRUCTURA | Cierre estación Piedras - Línea A | 12/1 | C58: =IFERROR(__xludf.DUMMYFUNCTION("""COMPUTED_VALUE"""),46031.0) -> 46031 | D58: =IFERROR(__xludf.DUMMYFUNCTION("""COMPUTED_VALUE"""),46045.0) -> 46045 | E58: =IFERROR(__xludf.DUMMYFUNCTION("""COMPUTED_VALUE"""),"Movilidad") -> Movilidad | F58: =IFERROR(__xludf.DUMMYFUNCTION("""COMPUTED_VALUE"""),"Infraestructura") -> Infraestructura | G58: =IFERROR(__xludf.DUMMYFUNCTION("""COMPUTED_VALUE"""),"Finalizada") -> Finalizada | H58: 2008143 | I58: 0 | J58: 2313 | K58: 138774 | L58: 1.9878291 | M58: 14.4706 | N58: 69307 | O58: 68518 | P58: 27095 | Q58: 193 | R58: 0 | S58: 0 | T58: 0 | U58: 0 | V58: 0 | W58: 0 | X58: 0 | Y58: 0 | Z58: 0 | AA58: 0 | AB58: 0 | AC58: 0 | AD58: https://www.facebook.com/GCBA/posts/pfbid034yhPZN5yb3JKe4gVWvnfg3JxEqjRYwvE5KVfa8FhtU9xnt4fvGGv6PfcJxxWU5qNl | AE58: Pieza
A59: =IFERROR(__xludf.DUMMYFUNCTION("""COMPUTED_VALUE"""),"2469-ENEPCCVC") -> 2469-ENEPCCVC | B59: =IFERROR(__xludf.DUMMYFUNCTION("""COMPUTED_VALUE"""),"Reunion de Cocreación Parque Ferroviario Palermo") -> Reunion de Cocreación Parque Ferroviario Palermo | C59: =IFERROR(__xludf.DUMMYFUNCTION("""COMPUTED_VALUE"""),46049.0) -> 46049 | D59: =IFERROR(__xludf.DUMMYFUNCTION("""COMPUTED_VALUE"""),46050.0) -> 46050 | E59: =IFERROR(__xludf.DUMMYFUNCTION("""COMPUTED_VALUE"""),"Cercanía") -> Cercanía | F59: =IFERROR(__xludf.DUMMYFUNCTION("""COMPUTED_VALUE"""),"Cercanía y PC") -> Cercanía y PC | G59: =IFERROR(__xludf.DUMMYFUNCTION("""COMPUTED_VALUE"""),"Finalizada") -> Finalizada | H59: 0 | I59: 0 | J59: 0 | K59: 0 | L59: 0 | M59: 0 | N59: 84765 | O59: 83136 | P59: 30285 | Q59: 289 | R59: 0 | S59: 0 | T59: 0 | U59: 0 | V59: 0 | W59: 0 | X59: 0 | Y59: 0 | Z59: 0 | AA59: 0 | AB59: 0 | AC59: 0 | AE59: Pieza
A60: =IFERROR(__xludf.DUMMYFUNCTION("""COMPUTED_VALUE"""),"2470-ENEINFGC") -> 2470-ENEINFGC | B60: =IFERROR(__xludf.DUMMYFUNCTION("""COMPUTED_VALUE"""),"CAMPAÑA GCBA | INFRAESTRUCTURA | Corte AU Illia") -> CAMPAÑA GCBA | INFRAESTRUCTURA | Corte AU Illia | C60: =IFERROR(__xludf.DUMMYFUNCTION("""COMPUTED_VALUE"""),46031.0) -> 46031 | D60: =IFERROR(__xludf.DUMMYFUNCTION("""COMPUTED_VALUE"""),46045.0) -> 46045 | E60: =IFERROR(__xludf.DUMMYFUNCTION("""COMPUTED_VALUE"""),"Movilidad") -> Movilidad | F60: =IFERROR(__xludf.DUMMYFUNCTION("""COMPUTED_VALUE"""),"Infraestructura") -> Infraestructura | G60: =IFERROR(__xludf.DUMMYFUNCTION("""COMPUTED_VALUE"""),"Finalizada") -> Finalizada | H60: 270415 | I60: 0 | J60: 11 | K60: 270165 | L60: 1.0009254 | M60: 1.0009254 | N60: 133380 | O60: 131124 | P60: 51525 | Q60: 206 | R60: 0 | S60: 0 | T60: 0 | U60: 0 | V60: 0 | W60: 0 | X60: 0 | Y60: 0 | Z60: 0 | AA60: 0 | AB60: 0 | AC60: 0 | AD60: https://fb.me/adspreview/facebook/27utMxPibDIBULh | AE60: Pieza
A61: =IFERROR(__xludf.DUMMYFUNCTION("""COMPUTED_VALUE"""),"2471-ENEINFGC") -> 2471-ENEINFGC | B61: =IFERROR(__xludf.DUMMYFUNCTION("""COMPUTED_VALUE"""),"CAMPAÑA GCBA | INFRAESTRUCTURA | PBN Irigoyen: durante de obra") -> CAMPAÑA GCBA | INFRAESTRUCTURA | PBN Irigoyen: durante de obra | C61: =IFERROR(__xludf.DUMMYFUNCTION("""COMPUTED_VALUE"""),46035.0) -> 46035 | D61: =IFERROR(__xludf.DUMMYFUNCTION("""COMPUTED_VALUE"""),46049.0) -> 46049 | E61: =IFERROR(__xludf.DUMMYFUNCTION("""COMPUTED_VALUE"""),"Movilidad") -> Movilidad | F61: =IFERROR(__xludf.DUMMYFUNCTION("""COMPUTED_VALUE"""),"Infraestructura") -> Infraestructura | G61: =IFERROR(__xludf.DUMMYFUNCTION("""COMPUTED_VALUE"""),"Finalizada") -> Finalizada | H61: 5445044 | I61: 1315669 | J61: 12536 | K61: 24740 | L61: 1.1219483 | M61: 220.0907 | N61: 26442 | O61: 26188 | P61: 12713 | Q61: 753 | R61: 0 | S61: 0 | T61: 0 | U61: 0 | V61: 0 | W61: 0 | X61: 0 | Y61: 0 | Z61: 0 | AA61: 0 | AB61: 0 | AC61: 0 | AD61: https://www.facebook.com/GCBA/posts/pfbid02skUdtrbsimuTryUG4RHgFZofPSnLrmz2LKHSqBZbBiyVryTXEaMk43DgH54kd2xbl | AE61: Pieza
A62: =IFERROR(__xludf.DUMMYFUNCTION("""COMPUTED_VALUE"""),"2472-ENEINFGC") -> 2472-ENEINFGC | B62: =IFERROR(__xludf.DUMMYFUNCTION("""COMPUTED_VALUE"""),"CAMPAÑA GCBA | Infraestructura | Cortes y desvíos en Palermo por trabajos en vías") -> CAMPAÑA GCBA | Infraestructura | Cortes y desvíos en Palermo por trabajos en vías | C62: =IFERROR(__xludf.DUMMYFUNCTION("""COMPUTED_VALUE"""),46035.0) -> 46035 | D62: =IFERROR(__xludf.DUMMYFUNCTION("""COMPUTED_VALUE"""),46036.0) -> 46036 | E62: =IFERROR(__xludf.DUMMYFUNCTION("""COMPUTED_VALUE"""),"Movilidad") -> Movilidad | F62: =IFERROR(__xludf.DUMMYFUNCTION("""COMPUTED_VALUE"""),"Infraestructura") -> Infraestructura | G62: =IFERROR(__xludf.DUMMYFUNCTION("""COMPUTED_VALUE"""),"Finalizada") -> Finalizada | H62: 428813 | I62: 0 | J62: 704 | K62: 427850 | L62: 1.0022508 | M62: 1.0022508 | N62: 61921 | O62: 61010 | P62: 27996 | Q62: 209 | R62: 0 | S62: 0 | T62: 0 | U62: 0 | V62: 0 | W62: 0 | X62: 0 | Y62: 0 | Z62: 0 | AA62: 0 | AB62: 0 | AC62: 0 | AD62: https://fb.me/adspreview/facebook/xMT36MnFuXZIDzt | AE62: Pieza
A63: =IFERROR(__xludf.DUMMYFUNCTION("""COMPUTED_VALUE"""),"2474-ENEINFGC") -> 2474-ENEINFGC | B63: =IFERROR(__xludf.DUMMYFUNCTION("""COMPUTED_VALUE"""),"Campaña GCBA I Infraestructura I Nuevo ramal línea 42") -> Campaña GCBA I Infraestructura I Nuevo ramal línea 42 | C63: =IFERROR(__xludf.DUMMYFUNCTION("""COMPUTED_VALUE"""),46041.0) -> 46041 | D63: =IFERROR(__xludf.DUMMYFUNCTION("""COMPUTED_VALUE"""),46055.0) -> 46055 | E63: =IFERROR(__xludf.DUMMYFUNCTION("""COMPUTED_VALUE"""),"Movilidad") -> Movilidad | F63: =IFERROR(__xludf.DUMMYFUNCTION("""COMPUTED_VALUE"""),"Infraestructura") -> Infraestructura | G63: =IFERROR(__xludf.DUMMYFUNCTION("""COMPUTED_VALUE"""),"Finalizada") -> Finalizada | H63: 3771995 | I63: 0 | J63: 17133 | K63: 1236622 | L63: 0.48297297 | M63: 3.0502409 | N63: 99866 | O63: 97981 | P63: 38813 | Q63: 4158 | R63: 0 | S63: 0 | T63: 0 | U63: 0 | V63: 0 | W63: 0 | X63: 0 | Y63: 0 | Z63: 0 | AA63: 0 | AB63: 0 | AC63: 0 | AD63: https://www.facebook.com/GCBA/posts/pfbid0337UG4zRXFbMrDgWhEvo65XfwWurZKf1GK8RZQ5Pka9jErhk36TCLtEoR98b6H6GGl | AE63: Pieza
A64: =IFERROR(__xludf.DUMMYFUNCTION("""COMPUTED_VALUE"""),"2475-ENESEGAG") -> 2475-ENESEGAG | B64: =IFERROR(__xludf.DUMMYFUNCTION("""COMPUTED_VALUE"""),"RECORRIDA POR SERVICIO PENITENCIARIO de Marcos Paz") -> RECORRIDA POR SERVICIO PENITENCIARIO de Marcos Paz | C64: =IFERROR(__xludf.DUMMYFUNCTION("""COMPUTED_VALUE"""),46038.0) -> 46038 | D64: =IFERROR(__xludf.DUMMYFUNCTION("""COMPUTED_VALUE"""),46055.0) -> 46055 | E64: =IFERROR(__xludf.DUMMYFUNCTION("""COMPUTED_VALUE"""),"M2") -> M2 | F64: =IFERROR(__xludf.DUMMYFUNCTION("""COMPUTED_VALUE"""),"Seguridad") -> Seguridad | G64: =IFERROR(__xludf.DUMMYFUNCTION("""COMPUTED_VALUE"""),"Finalizada") -> Finalizada | H64: 4108318 | I64: 362022 | J64: 22820 | K64: 324234 | L64: 2.4565376 | M64: 12.670843 | N64: 79361 | O64: 78087 | P64: 22745 | Q64: 87 | R64: 0 | S64: 0 | T64: 0 | U64: 0 | V64: 0 | W64: 0 | X64: 0 | Y64: 0 | Z64: 0 | AA64: 0 | AB64: 0 | AC64: 0 | AD64: https://www.facebook.com/reel/25959631640339458 | AE64: Pieza
A65: =IFERROR(__xludf.DUMMYFUNCTION("""COMPUTED_VALUE"""),"2476-ENEFESGC") -> 2476-ENEFESGC | B65: =IFERROR(__xludf.DUMMYFUNCTION("""COMPUTED_VALUE"""),"Verano en la Ciudad | Corrientes 24h") -> Verano en la Ciudad | Corrientes 24h | C65: =IFERROR(__xludf.DUMMYFUNCTION("""COMPUTED_VALUE"""),46043.0) -> 46043 | D65: =IFERROR(__xludf.DUMMYFUNCTION("""COMPUTED_VALUE"""),46081.0) -> 46081 | E65: =IFERROR(__xludf.DUMMYFUNCTION("""COMPUTED_VALUE"""),"Ciudad Atractiva") -> Ciudad Atractiva | F65: =IFERROR(__xludf.DUMMYFUNCTION("""COMPUTED_VALUE"""),"Festivales y Eventos") -> Festivales y Eventos | G65: =IFERROR(__xludf.DUMMYFUNCTION("""COMPUTED_VALUE"""),"Finalizada") -> Finalizada | H65: 19987991 | I65: 4636267 | J65: 26588 | K65: 467329 | L65: 6.5961475 | M65: 42.770705 | N65: 131580 | O65: 130254 | P65: 67844 | Q65: 3426 | R65: 0 | S65: 0 | T65: 0 | U65: 0 | V65: 0 | W65: 0 | X65: 0 | Y65: 0 | Z65: 0 | AA65: 0 | AB65: 0 | AC65: 0 | AD65: https://www.facebook.com/reel/1376298900359413 | AE65: Pieza
A66: =IFERROR(__xludf.DUMMYFUNCTION("""COMPUTED_VALUE"""),"2477-ENEPCCVC") -> 2477-ENEPCCVC | B66: =IFERROR(__xludf.DUMMYFUNCTION("""COMPUTED_VALUE"""),"Refuncionalización Calle Necochea y entorno") -> Refuncionalización Calle Necochea y entorno | C66: =IFERROR(__xludf.DUMMYFUNCTION("""COMPUTED_VALUE"""),46041.0) -> 46041 | D66: =IFERROR(__xludf.DUMMYFUNCTION("""COMPUTED_VALUE"""),46041.0) -> 46041 | E66: =IFERROR(__xludf.DUMMYFUNCTION("""COMPUTED_VALUE"""),"Cercanía") -> Cercanía | F66: =IFERROR(__xludf.DUMMYFUNCTION("""COMPUTED_VALUE"""),"Cercanía y PC") -> Cercanía y PC | G66: =IFERROR(__xludf.DUMMYFUNCTION("""COMPUTED_VALUE"""),"Finalizada") -> Finalizada | H66: 0 | I66: 0 | J66: 0 | K66: 0 | L66: 0 | M66: 0 | N66: 13427 | O66: 13123 | P66: 2286 | Q66: 83 | R66: 0 | S66: 0 | T66: 0 | U66: 0 | V66: 0 | W66: 0 | X66: 0 | Y66: 0 | Z66: 0 | AA66: 0 | AB66: 0 | AC66: 0 | AE66: Pieza
A67: =IFERROR(__xludf.DUMMYFUNCTION("""COMPUTED_VALUE"""),"2478-ENEINNGC") -> 2478-ENEINNGC | B67: =IFERROR(__xludf.DUMMYFUNCTION("""COMPUTED_VALUE"""),"Lanzamiento BAX") -> Lanzamiento BAX | C67: =IFERROR(__xludf.DUMMYFUNCTION("""COMPUTED_VALUE"""),46205.0) -> 46205 | D67: =IFERROR(__xludf.DUMMYFUNCTION("""COMPUTED_VALUE"""),46265.0) -> 46265 | E67: =IFERROR(__xludf.DUMMYFUNCTION("""COMPUTED_VALUE"""),"Reforma del Estado") -> Reforma del Estado | F67: =IFERROR(__xludf.DUMMYFUNCTION("""COMPUTED_VALUE"""),"Innovación") -> Innovación | G67: =IFERROR(__xludf.DUMMYFUNCTION("""COMPUTED_VALUE"""),"Activa") -> Activa | H67: 21389768 | I67: 5608558 | J67: 290709 | K67: 1151860 | L67: 3.694521 | M67: 18.569764 | N67: 561058 | O67: 553314 | P67: 168616 | Q67: 10926 | R67: 0 | S67: 0 | T67: 0 | U67: 0 | V67: 0 | W67: 0 | X67: 0 | Y67: 0 | Z67: 0 | AA67: 0 | AB67: 0 | AC67: 0 | AE67: Pieza
A68: =IFERROR(__xludf.DUMMYFUNCTION("""COMPUTED_VALUE"""),"2480-ENEINFGC") -> 2480-ENEINFGC | B68: =IFERROR(__xludf.DUMMYFUNCTION("""COMPUTED_VALUE"""),"Campaña GCBA | Infraestructura: Obras en La Boca: calle Necochea") -> Campaña GCBA | Infraestructura: Obras en La Boca: calle Necochea | C68: =IFERROR(__xludf.DUMMYFUNCTION("""COMPUTED_VALUE"""),46083.0) -> 46083 | D68: =IFERROR(__xludf.DUMMYFUNCTION("""COMPUTED_VALUE"""),46112.0) -> 46112 | E68: =IFERROR(__xludf.DUMMYFUNCTION("""COMPUTED_VALUE"""),"M2") -> M2 | F68: =IFERROR(__xludf.DUMMYFUNCTION("""COMPUTED_VALUE"""),"Infraestructura") -> Infraestructura | G68: =IFERROR(__xludf.DUMMYFUNCTION("""COMPUTED_VALUE"""),"Finalizada") -> Finalizada | H68: 381747 | I68: 0 | J68: 6705 | K68: 78939 | L68: 1.8810221 | M68: 4.8359746 | N68: 10370 | O68: 10174 | P68: 2757 | Q68: 178 | R68: 0 | S68: 0 | T68: 0 | U68: 0 | V68: 0 | W68: 0 | X68: 0 | Y68: 0 | Z68: 0 | AA68: 0 | AB68: 0 | AC68: 0 | AE68: Pieza
A69: =IFERROR(__xludf.DUMMYFUNCTION("""COMPUTED_VALUE"""),"2481-ENETURGC") -> 2481-ENETURGC | B69: =IFERROR(__xludf.DUMMYFUNCTION("""COMPUTED_VALUE"""),"Informe mensual Observatorio | Diciembre 2025 | Viernes 16/01") -> Informe mensual Observatorio | Diciembre 2025 | Viernes 16/01 | C69: =IFERROR(__xludf.DUMMYFUNCTION("""COMPUTED_VALUE"""),46037.0) -> 46037 | D69: =IFERROR(__xludf.DUMMYFUNCTION("""COMPUTED_VALUE"""),46037.0) -> 46037 | E69: =IFERROR(__xludf.DUMMYFUNCTION("""COMPUTED_VALUE"""),"Otros") -> Otros | F69: =IFERROR(__xludf.DUMMYFUNCTION("""COMPUTED_VALUE"""),"Turismo") -> Turismo | G69: =IFERROR(__xludf.DUMMYFUNCTION("""COMPUTED_VALUE"""),"Finalizada") -> Finalizada | H69: 0 | I69: 0 | J69: 0 | K69: 0 | L69: 0 | M69: 0 | N69: 311 | O69: 305 | P69: 146 | Q69: 17 | R69: 0 | S69: 0 | T69: 0 | U69: 0 | V69: 0 | W69: 0 | X69: 0 | Y69: 0 | Z69: 0 | AA69: 0 | AB69: 0 | AC69: 0 | AE69: Pieza
A70: =IFERROR(__xludf.DUMMYFUNCTION("""COMPUTED_VALUE"""),"2482-ENEINFGC") -> 2482-ENEINFGC | B70: =IFERROR(__xludf.DUMMYFUNCTION("""COMPUTED_VALUE"""),"VTV - Recordatorio de turno 2026") -> VTV - Recordatorio de turno 2026 | C70: =IFERROR(__xludf.DUMMYFUNCTION("""COMPUTED_VALUE"""),46042.0) -> 46042 | D70: =IFERROR(__xludf.DUMMYFUNCTION("""COMPUTED_VALUE"""),46205.0) -> 46205 | E70: =IFERROR(__xludf.DUMMYFUNCTION("""COMPUTED_VALUE"""),"M2") -> M2 | F70: =IFERROR(__xludf.DUMMYFUNCTION("""COMPUTED_VALUE"""),"Infraestructura") -> Infraestructura | G70: =IFERROR(__xludf.DUMMYFUNCTION("""COMPUTED_VALUE"""),"Finalizada") -> Finalizada | H70: 0 | I70: 0 | J70: 0 | K70: 0 | L70: 0 | M70: 0 | N70: 236790 | O70: 236474 | P70: 96019 | Q70: 18061 | R70: 0 | S70: 0 | T70: 0 | U70: 0 | V70: 0 | W70: 0 | X70: 0 | Y70: 0 | Z70: 0 | AA70: 0 | AB70: 0 | AC70: 0 | AE70: Pieza
A71: =IFERROR(__xludf.DUMMYFUNCTION("""COMPUTED_VALUE"""),"2483-ENESEGGC") -> 2483-ENESEGGC | B71: =IFERROR(__xludf.DUMMYFUNCTION("""COMPUTED_VALUE"""),"Campaña GCBA I Seguridad | Desalojo Constitución") -> Campaña GCBA I Seguridad | Desalojo Constitución | C71: =IFERROR(__xludf.DUMMYFUNCTION("""COMPUTED_VALUE"""),46038.0) -> 46038 | D71: =IFERROR(__xludf.DUMMYFUNCTION("""COMPUTED_VALUE"""),46056.0) -> 46056 | E71: =IFERROR(__xludf.DUMMYFUNCTION("""COMPUTED_VALUE"""),"M2") -> M2 | F71: =IFERROR(__xludf.DUMMYFUNCTION("""COMPUTED_VALUE"""),"Seguridad") -> Seguridad | G71: =IFERROR(__xludf.DUMMYFUNCTION("""COMPUTED_VALUE"""),"Finalizada") -> Finalizada | H71: 1143474 | I71: 145591 | J71: 2412 | K71: 355943 | L71: 2.8286889 | M71: 3.21252 | N71: 179393 | O71: 176101 | P71: 42189 | Q71: 823 | R71: 0 | S71: 0 | T71: 0 | U71: 0 | V71: 0 | W71: 0 | X71: 0 | Y71: 0 | Z71: 0 | AA71: 0 | AB71: 0 | AC71: 0 | AD71: https://www.facebook.com/reel/1332009022300877 | AE71: Pieza
A72: =IFERROR(__xludf.DUMMYFUNCTION("""COMPUTED_VALUE"""),"2486-ENEDHHGC") -> 2486-ENEDHHGC | B72: =IFERROR(__xludf.DUMMYFUNCTION("""COMPUTED_VALUE"""),"MDHYH | Programa Adolescencia") -> MDHYH | Programa Adolescencia | C72: =IFERROR(__xludf.DUMMYFUNCTION("""COMPUTED_VALUE"""),46049.0) -> 46049 | D72: =IFERROR(__xludf.DUMMYFUNCTION("""COMPUTED_VALUE"""),46049.0) -> 46049 | E72: =IFERROR(__xludf.DUMMYFUNCTION("""COMPUTED_VALUE"""),"Cuidado") -> Cuidado | F72: =IFERROR(__xludf.DUMMYFUNCTION("""COMPUTED_VALUE"""),"Desarrollo Humano y Hábitat") -> Desarrollo Humano y Hábitat | G72: =IFERROR(__xludf.DUMMYFUNCTION("""COMPUTED_VALUE"""),"Finalizada") -> Finalizada | H72: 0 | I72: 0 | J72: 0 | K72: 0 | L72: 0 | M72: 0 | N72: 82441 | O72: 80581 | P72: 22327 | Q72: 5566 | R72: 0 | S72: 0 | T72: 0 | U72: 0 | V72: 0 | W72: 0 | X72: 0 | Y72: 0 | Z72: 0 | AA72: 0 | AB72: 0 | AC72: 0 | AE72: Pieza
A73: =IFERROR(__xludf.DUMMYFUNCTION("""COMPUTED_VALUE"""),"2487-ENEVINGC") -> 2487-ENEVINGC | B73: =IFERROR(__xludf.DUMMYFUNCTION("""COMPUTED_VALUE"""),"CAMPAÑA GCBA | VINCULO CIUDADANO | Mas servicios en tu barrio 2026: Parque Chacabuco 02/02") -> CAMPAÑA GCBA | VINCULO CIUDADANO | Mas servicios en tu barrio 2026: Parque Chacabuco 02/02 | C73: =IFERROR(__xludf.DUMMYFUNCTION("""COMPUTED_VALUE"""),46051.0) -> 46051 | D73: =IFERROR(__xludf.DUMMYFUNCTION("""COMPUTED_VALUE"""),46051.0) -> 46051 | E73: =IFERROR(__xludf.DUMMYFUNCTION("""COMPUTED_VALUE"""),"M2") -> M2 | F73: =IFERROR(__xludf.DUMMYFUNCTION("""COMPUTED_VALUE"""),"Vínculo Ciudadano") -> Vínculo Ciudadano | G73: =IFERROR(__xludf.DUMMYFUNCTION("""COMPUTED_VALUE"""),"Finalizada") -> Finalizada | H73: 0 | I73: 0 | J73: 0 | K73: 0 | L73: 0 | M73: 0 | N73: 15253 | O73: 14992 | P73: 5465 | Q73: 252 | R73: 0 | S73: 0 | T73: 0 | U73: 0 | V73: 0 | W73: 0 | X73: 0 | Y73: 0 | Z73: 0 | AA73: 0 | AB73: 0 | AC73: 0 | AE73: Pieza
A74: =IFERROR(__xludf.DUMMYFUNCTION("""COMPUTED_VALUE"""),"2488-ENEVINGC") -> 2488-ENEVINGC | B74: =IFERROR(__xludf.DUMMYFUNCTION("""COMPUTED_VALUE"""),"CAMPAÑA GCBA | VINCULO CIUDADANO | Mas servicios en tu barrio 2026: Caballito 04/02") -> CAMPAÑA GCBA | VINCULO CIUDADANO | Mas servicios en tu barrio 2026: Caballito 04/02 | C74: =IFERROR(__xludf.DUMMYFUNCTION("""COMPUTED_VALUE"""),46052.0) -> 46052 | D74: =IFERROR(__xludf.DUMMYFUNCTION("""COMPUTED_VALUE"""),46052.0) -> 46052 | E74: =IFERROR(__xludf.DUMMYFUNCTION("""COMPUTED_VALUE"""),"M2") -> M2 | F74: =IFERROR(__xludf.DUMMYFUNCTION("""COMPUTED_VALUE"""),"Vínculo Ciudadano") -> Vínculo Ciudadano | G74: =IFERROR(__xludf.DUMMYFUNCTION("""COMPUTED_VALUE"""),"Finalizada") -> Finalizada | H74: 0 | I74: 0 | J74: 0 | K74: 0 | L74: 0 | M74: 0 | N74: 30581 | O74: 30053 | P74: 10808 | Q74: 399 | R74: 0 | S74: 0 | T74: 0 | U74: 0 | V74: 0 | W74: 0 | X74: 0 | Y74: 0 | Z74: 0 | AA74: 0 | AB74: 0 | AC74: 0 | AE74: Pieza
A75: =IFERROR(__xludf.DUMMYFUNCTION("""COMPUTED_VALUE"""),"2489-ENEVINGC") -> 2489-ENEVINGC | B75: =IFERROR(__xludf.DUMMYFUNCTION("""COMPUTED_VALUE"""),"CAMPAÑA GCBA | VINCULO CIUDADANO | Mas servicios en tu barrio 2026: Villa Riachuelo 06/02") -> CAMPAÑA GCBA | VINCULO CIUDADANO | Mas servicios en tu barrio 2026: Villa Riachuelo 06/02 | C75: =IFERROR(__xludf.DUMMYFUNCTION("""COMPUTED_VALUE"""),46055.0) -> 46055 | D75: =IFERROR(__xludf.DUMMYFUNCTION("""COMPUTED_VALUE"""),46055.0) -> 46055 | E75: =IFERROR(__xludf.DUMMYFUNCTION("""COMPUTED_VALUE"""),"M2") -> M2 | F75: =IFERROR(__xludf.DUMMYFUNCTION("""COMPUTED_VALUE"""),"Vínculo Ciudadano") -> Vínculo Ciudadano | G75: =IFERROR(__xludf.DUMMYFUNCTION("""COMPUTED_VALUE"""),"Finalizada") -> Finalizada | H75: 0 | I75: 0 | J75: 0 | K75: 0 | L75: 0 | M75: 0 | N75: 10310 | O75: 10090 | P75: 2994 | Q75: 170 | R75: 0 | S75: 0 | T75: 0 | U75: 0 | V75: 0 | W75: 0 | X75: 0 | Y75: 0 | Z75: 0 | AA75: 0 | AB75: 0 | AC75: 0 | AE75: Pieza
A76: =IFERROR(__xludf.DUMMYFUNCTION("""COMPUTED_VALUE"""),"2490-ENEVINGC") -> 2490-ENEVINGC | B76: =IFERROR(__xludf.DUMMYFUNCTION("""COMPUTED_VALUE"""),"CAMPAÑA GCBA | VINCULO CIUDADANO | Mas servicios en tu barrio 2026: Villa Devoto 09/02") -> CAMPAÑA GCBA | VINCULO CIUDADANO | Mas servicios en tu barrio 2026: Villa Devoto 09/02 | C76: =IFERROR(__xludf.DUMMYFUNCTION("""COMPUTED_VALUE"""),46062.0) -> 46062 | D76: =IFERROR(__xludf.DUMMYFUNCTION("""COMPUTED_VALUE"""),46062.0) -> 46062 | E76: =IFERROR(__xludf.DUMMYFUNCTION("""COMPUTED_VALUE"""),"M2") -> M2 | F76: =IFERROR(__xludf.DUMMYFUNCTION("""COMPUTED_VALUE"""),"Vínculo Ciudadano") -> Vínculo Ciudadano | G76: =IFERROR(__xludf.DUMMYFUNCTION("""COMPUTED_VALUE"""),"Finalizada") -> Finalizada | H76: 0 | I76: 0 | J76: 0 | K76: 0 | L76: 0 | M76: 0 | N76: 10019 | O76: 9829 | P76: 4405 | Q76: 210 | R76: 0 | S76: 0 | T76: 0 | U76: 0 | V76: 0 | W76: 0 | X76: 0 | Y76: 0 | Z76: 0 | AA76: 0 | AB76: 0 | AC76: 0 | AE76: Pieza
A77: =IFERROR(__xludf.DUMMYFUNCTION("""COMPUTED_VALUE"""),"2491-ENEVINGC") -> 2491-ENEVINGC | B77: =IFERROR(__xludf.DUMMYFUNCTION("""COMPUTED_VALUE"""),"CAMPAÑA GCBA | VINCULO CIUDADANO | Mas servicios en tu barrio 2026: Mataderos 11/02") -> CAMPAÑA GCBA | VINCULO CIUDADANO | Mas servicios en tu barrio 2026: Mataderos 11/02 | C77: =IFERROR(__xludf.DUMMYFUNCTION("""COMPUTED_VALUE"""),46062.0) -> 46062 | D77: =IFERROR(__xludf.DUMMYFUNCTION("""COMPUTED_VALUE"""),46062.0) -> 46062 | E77: =IFERROR(__xludf.DUMMYFUNCTION("""COMPUTED_VALUE"""),"M2") -> M2 | F77: =IFERROR(__xludf.DUMMYFUNCTION("""COMPUTED_VALUE"""),"Vínculo Ciudadano") -> Vínculo Ciudadano | G77: =IFERROR(__xludf.DUMMYFUNCTION("""COMPUTED_VALUE"""),"Finalizada") -> Finalizada | H77: 0 | I77: 0 | J77: 0 | K77: 0 | L77: 0 | M77: 0 | N77: 9931 | O77: 9762 | P77: 3403 | Q77: 223 | R77: 0 | S77: 0 | T77: 0 | U77: 0 | V77: 0 | W77: 0 | X77: 0 | Y77: 0 | Z77: 0 | AA77: 0 | AB77: 0 | AC77: 0 | AE77: Pieza
A78: =IFERROR(__xludf.DUMMYFUNCTION("""COMPUTED_VALUE"""),"2492-ENEVINGC") -> 2492-ENEVINGC | B78: =IFERROR(__xludf.DUMMYFUNCTION("""COMPUTED_VALUE"""),"CAMPAÑA GCBA | VINCULO CIUDADANO | Mas servicios en tu barrio 2026: Villa Crespo 13/02") -> CAMPAÑA GCBA | VINCULO CIUDADANO | Mas servicios en tu barrio 2026: Villa Crespo 13/02 | C78: =IFERROR(__xludf.DUMMYFUNCTION("""COMPUTED_VALUE"""),46063.0) -> 46063 | D78: =IFERROR(__xludf.DUMMYFUNCTION("""COMPUTED_VALUE"""),46063.0) -> 46063 | E78: =IFERROR(__xludf.DUMMYFUNCTION("""COMPUTED_VALUE"""),"M2") -> M2 | F78: =IFERROR(__xludf.DUMMYFUNCTION("""COMPUTED_VALUE"""),"Vínculo Ciudadano") -> Vínculo Ciudadano | G78: =IFERROR(__xludf.DUMMYFUNCTION("""COMPUTED_VALUE"""),"Finalizada") -> Finalizada | H78: 0 | I78: 0 | J78: 0 | K78: 0 | L78: 0 | M78: 0 | N78: 19496 | O78: 19166 | P78: 6746 | Q78: 239 | R78: 0 | S78: 0 | T78: 0 | U78: 0 | V78: 0 | W78: 0 | X78: 0 | Y78: 0 | Z78: 0 | AA78: 0 | AB78: 0 | AC78: 0 | AE78: Pieza
A79: =IFERROR(__xludf.DUMMYFUNCTION("""COMPUTED_VALUE"""),"2493-ENEVINGC") -> 2493-ENEVINGC | B79: =IFERROR(__xludf.DUMMYFUNCTION("""COMPUTED_VALUE"""),"CAMPAÑA GCBA | VINCULO CIUDADANO | Mas servicios en tu barrio 2026: Villa Luro 18/02") -> CAMPAÑA GCBA | VINCULO CIUDADANO | Mas servicios en tu barrio 2026: Villa Luro 18/02 | C79: =IFERROR(__xludf.DUMMYFUNCTION("""COMPUTED_VALUE"""),46067.0) -> 46067 | D79: =IFERROR(__xludf.DUMMYFUNCTION("""COMPUTED_VALUE"""),46067.0) -> 46067 | E79: =IFERROR(__xludf.DUMMYFUNCTION("""COMPUTED_VALUE"""),"M2") -> M2 | F79: =IFERROR(__xludf.DUMMYFUNCTION("""COMPUTED_VALUE"""),"Vínculo Ciudadano") -> Vínculo Ciudadano | G79: =IFERROR(__xludf.DUMMYFUNCTION("""COMPUTED_VALUE"""),"Finalizada") -> Finalizada | H79: 0 | I79: 0 | J79: 0 | K79: 0 | L79: 0 | M79: 0 | N79: 11830 | O79: 11398 | P79: 4126 | Q79: 15 | R79: 0 | S79: 0 | T79: 0 | U79: 0 | V79: 0 | W79: 0 | X79: 0 | Y79: 0 | Z79: 0 | AA79: 0 | AB79: 0 | AC79: 0 | AE79: Pieza
A80: =IFERROR(__xludf.DUMMYFUNCTION("""COMPUTED_VALUE"""),"2496-ENEVINGC") -> 2496-ENEVINGC | B80: =IFERROR(__xludf.DUMMYFUNCTION("""COMPUTED_VALUE"""),"CAMPAÑA GCBA | VINCULO CIUDADANO | Mas servicios en tu barrio 2026: Recoleta 25/02") -> CAMPAÑA GCBA | VINCULO CIUDADANO | Mas servicios en tu barrio 2026: Recoleta 25/02 | C80: =IFERROR(__xludf.DUMMYFUNCTION("""COMPUTED_VALUE"""),46071.0) -> 46071 | D80: =IFERROR(__xludf.DUMMYFUNCTION("""COMPUTED_VALUE"""),46265.0) -> 46265 | E80: =IFERROR(__xludf.DUMMYFUNCTION("""COMPUTED_VALUE"""),"M2") -> M2 | F80: =IFERROR(__xludf.DUMMYFUNCTION("""COMPUTED_VALUE"""),"Vínculo Ciudadano") -> Vínculo Ciudadano | G80: =IFERROR(__xludf.DUMMYFUNCTION("""COMPUTED_VALUE"""),"Activa") -> Activa | H80: 7822741 | I80: 0 | J80: 27788 | K80: 1977609 | L80: 3.955656 | M80: 3.955656 | N80: 0 | O80: 0 | P80: 0 | Q80: 0 | R80: 0 | S80: 0 | T80: 0 | U80: 0 | V80: 0 | W80: 0 | X80: 0 | Y80: 0 | Z80: 0 | AA80: 0 | AB80: 0 | AC80: 0 | AD80: https://www.facebook.com/GCBA/posts/pfbid02BLwc5PnG5EYzbVeS3qNZ6Nb5in3PifakagmTh6BFX3zNQZ1rLsJ3FsQx9JDG2gFdl
A81: =IFERROR(__xludf.DUMMYFUNCTION("""COMPUTED_VALUE"""),"2497-ENEVINGC") -> 2497-ENEVINGC | B81: =IFERROR(__xludf.DUMMYFUNCTION("""COMPUTED_VALUE"""),"CAMPAÑA GCBA | VINCULO CIUDADANO | Mas servicios en tu barrio 2026: Palermo 27/02") -> CAMPAÑA GCBA | VINCULO CIUDADANO | Mas servicios en tu barrio 2026: Palermo 27/02 | C81: =IFERROR(__xludf.DUMMYFUNCTION("""COMPUTED_VALUE"""),46077.0) -> 46077 | D81: =IFERROR(__xludf.DUMMYFUNCTION("""COMPUTED_VALUE"""),46077.0) -> 46077 | E81: =IFERROR(__xludf.DUMMYFUNCTION("""COMPUTED_VALUE"""),"M2") -> M2 | F81: =IFERROR(__xludf.DUMMYFUNCTION("""COMPUTED_VALUE"""),"Vínculo Ciudadano") -> Vínculo Ciudadano | G81: =IFERROR(__xludf.DUMMYFUNCTION("""COMPUTED_VALUE"""),"Finalizada") -> Finalizada | H81: 0 | I81: 0 | J81: 0 | K81: 0 | L81: 0 | M81: 0 | N81: 33785 | O81: 33409 | P81: 13633 | Q81: 347 | R81: 0 | S81: 0 | T81: 0 | U81: 0 | V81: 0 | W81: 0 | X81: 0 | Y81: 0 | Z81: 0 | AA81: 0 | AB81: 0 | AC81: 0 | AE81: Pieza
A82: =IFERROR(__xludf.DUMMYFUNCTION("""COMPUTED_VALUE"""),"2498-ENEEPHGC") -> 2498-ENEEPHGC | B82: =IFERROR(__xludf.DUMMYFUNCTION("""COMPUTED_VALUE"""),"CAMPAÑA GCBA | CONVIVENCIA | Genérica") -> CAMPAÑA GCBA | CONVIVENCIA | Genérica | C82: =IFERROR(__xludf.DUMMYFUNCTION("""COMPUTED_VALUE"""),46063.0) -> 46063 | D82: =IFERROR(__xludf.DUMMYFUNCTION("""COMPUTED_VALUE"""),46112.0) -> 46112 | E82: =IFERROR(__xludf.DUMMYFUNCTION("""COMPUTED_VALUE"""),"M2") -> M2 | F82: =IFERROR(__xludf.DUMMYFUNCTION("""COMPUTED_VALUE"""),"Espacio Público e Higiene Urbana") -> Espacio Público e Higiene Urbana | G82: =IFERROR(__xludf.DUMMYFUNCTION("""COMPUTED_VALUE"""),"Finalizada") -> Finalizada | H82: 11971276 | I82: 4057311 | J82: 70881 | K82: 25626 | L82: 169.10965 | M82: 467.15352 | N82: 103961 | O82: 103286 | P82: 52535 | Q82: 360 | R82: 0 | S82: 0 | T82: 0 | U82: 0 | V82: 0 | W82: 0 | X82: 0 | Y82: 0 | Z82: 0 | AA82: 0 | AB82: 0 | AC82: 0 | AE82: Pieza
A83: =IFERROR(__xludf.DUMMYFUNCTION("""COMPUTED_VALUE"""),"2499-ENEEPHGC") -> 2499-ENEEPHGC | B83: =IFERROR(__xludf.DUMMYFUNCTION("""COMPUTED_VALUE"""),"CAMPAÑA GCBA | CONVIVENCIA | Cuidado de perros") -> CAMPAÑA GCBA | CONVIVENCIA | Cuidado de perros | C83: =IFERROR(__xludf.DUMMYFUNCTION("""COMPUTED_VALUE"""),46063.0) -> 46063 | D83: =IFERROR(__xludf.DUMMYFUNCTION("""COMPUTED_VALUE"""),46112.0) -> 46112 | E83: =IFERROR(__xludf.DUMMYFUNCTION("""COMPUTED_VALUE"""),"M2") -> M2 | F83: =IFERROR(__xludf.DUMMYFUNCTION("""COMPUTED_VALUE"""),"Espacio Público e Higiene Urbana") -> Espacio Público e Higiene Urbana | G83: =IFERROR(__xludf.DUMMYFUNCTION("""COMPUTED_VALUE"""),"Finalizada") -> Finalizada | H83: 6958541 | I83: 0 | J83: 54847 | K83: 421569 | L83: 6.5486148 | M83: 16.506292 | N83: 87630 | O83: 86596 | P83: 33826 | Q83: 192 | R83: 0 | S83: 0 | T83: 0 | U83: 0 | V83: 0 | W83: 0 | X83: 0 | Y83: 0 | Z83: 0 | AA83: 0 | AB83: 0 | AC83: 0 | AE83: Pieza
A84: =IFERROR(__xludf.DUMMYFUNCTION("""COMPUTED_VALUE"""),"2500-ENEEPHGC") -> 2500-ENEEPHGC | B84: =IFERROR(__xludf.DUMMYFUNCTION("""COMPUTED_VALUE"""),"CAMPAÑA GCBA | CONVIVENCIA | Doble Fila") -> CAMPAÑA GCBA | CONVIVENCIA | Doble Fila | C84: =IFERROR(__xludf.DUMMYFUNCTION("""COMPUTED_VALUE"""),46064.0) -> 46064 | D84: =IFERROR(__xludf.DUMMYFUNCTION("""COMPUTED_VALUE"""),46112.0) -> 46112 | E84: =IFERROR(__xludf.DUMMYFUNCTION("""COMPUTED_VALUE"""),"M2") -> M2 | F84: =IFERROR(__xludf.DUMMYFUNCTION("""COMPUTED_VALUE"""),"Espacio Público e Higiene Urbana") -> Espacio Público e Higiene Urbana | G84: =IFERROR(__xludf.DUMMYFUNCTION("""COMPUTED_VALUE"""),"Finalizada") -> Finalizada | H84: 9961877 | I84: 0 | J84: 64850 | K84: 317029 | L84: 17.055843 | M84: 31.422605 | N84: 181226 | O84: 180694 | P84: 113730 | Q84: 1220 | R84: 0 | S84: 0 | T84: 0 | U84: 0 | V84: 0 | W84: 0 | X84: 0 | Y84: 0 | Z84: 0 | AA84: 0 | AB84: 0 | AC84: 0 | AE84: Pieza
A85: =IFERROR(__xludf.DUMMYFUNCTION("""COMPUTED_VALUE"""),"2501-ENEJDGAG") -> 2501-ENEJDGAG | B85: =IFERROR(__xludf.DUMMYFUNCTION("""COMPUTED_VALUE"""),"RDV JM Flores 30/01") -> RDV JM Flores 30/01 | C85: =IFERROR(__xludf.DUMMYFUNCTION("""COMPUTED_VALUE"""),46045.0) -> 46045 | D85: =IFERROR(__xludf.DUMMYFUNCTION("""COMPUTED_VALUE"""),46067.0) -> 46067 | E85: =IFERROR(__xludf.DUMMYFUNCTION("""COMPUTED_VALUE"""),"Cercanía") -> Cercanía | F85: =IFERROR(__xludf.DUMMYFUNCTION("""COMPUTED_VALUE"""),"Jefatura de Gobierno") -> Jefatura de Gobierno | G85: =IFERROR(__xludf.DUMMYFUNCTION("""COMPUTED_VALUE"""),"Finalizada") -> Finalizada | H85: 2825033 | I85: 1642319 | J85: 6937 | K85: 75466 | L85: 3.4477778 | M85: 37.434514 | N85: 118035 | O85: 115928 | P85: 20333 | Q85: 873 | R85: 9405 | S85: 7521 | T85: 1735 | U85: 1312 | V85: 32361 | W85: 32361 | X85: 25759 | Y85: 10328 | Z85: 108 | AA85: 0 | AB85: 0 | AC85: 0 | AD85: https://www.facebook.com/reel/1297793642108690 | AE85: Pieza
A86: =IFERROR(__xludf.DUMMYFUNCTION("""COMPUTED_VALUE"""),"2502-ENEJDGAG") -> 2502-ENEJDGAG | B86: =IFERROR(__xludf.DUMMYFUNCTION("""COMPUTED_VALUE"""),"CAFE JM Versalles 29/01") -> CAFE JM Versalles 29/01 | C86: =IFERROR(__xludf.DUMMYFUNCTION("""COMPUTED_VALUE"""),46048.0) -> 46048 | D86: =IFERROR(__xludf.DUMMYFUNCTION("""COMPUTED_VALUE"""),46073.0) -> 46073 | E86: =IFERROR(__xludf.DUMMYFUNCTION("""COMPUTED_VALUE"""),"Cercanía") -> Cercanía | F86: =IFERROR(__xludf.DUMMYFUNCTION("""COMPUTED_VALUE"""),"Jefatura de Gobierno") -> Jefatura de Gobierno | G86: =IFERROR(__xludf.DUMMYFUNCTION("""COMPUTED_VALUE"""),"Finalizada") -> Finalizada | H86: 124669 | I86: 3423 | J86: 1975 | K86: 17945 | L86: 2.4849262 | M86: 6.9472834 | N86: 6610 | O86: 6518 | P86: 1169 | Q86: 169 | R86: 0 | S86: 0 | T86: 0 | U86: 0 | V86: 0 | W86: 0 | X86: 0 | Y86: 0 | Z86: 0 | AA86: 0 | AB86: 0 | AC86: 0 | AE86: Pieza
A87: =IFERROR(__xludf.DUMMYFUNCTION("""COMPUTED_VALUE"""),"2503-ENEPCCVC") -> 2503-ENEPCCVC | B87: =IFERROR(__xludf.DUMMYFUNCTION("""COMPUTED_VALUE"""),"Reunión de Co-creación - Eventos Masivos Huracán") -> Reunión de Co-creación - Eventos Masivos Huracán | C87: =IFERROR(__xludf.DUMMYFUNCTION("""COMPUTED_VALUE"""),46055.0) -> 46055 | D87: =IFERROR(__xludf.DUMMYFUNCTION("""COMPUTED_VALUE"""),46055.0) -> 46055 | E87: =IFERROR(__xludf.DUMMYFUNCTION("""COMPUTED_VALUE"""),"Cercanía") -> Cercanía | F87: =IFERROR(__xludf.DUMMYFUNCTION("""COMPUTED_VALUE"""),"Cercanía y PC") -> Cercanía y PC | G87: =IFERROR(__xludf.DUMMYFUNCTION("""COMPUTED_VALUE"""),"Finalizada") -> Finalizada | H87: 0 | I87: 0 | J87: 0 | K87: 0 | L87: 0 | M87: 0 | N87: 31878 | O87: 31183 | P87: 5171 | Q87: 112 | R87: 0 | S87: 0 | T87: 0 | U87: 0 | V87: 0 | W87: 0 | X87: 0 | Y87: 0 | Z87: 0 | AA87: 0 | AB87: 0 | AC87: 0 | AE87: Pieza
A88: =IFERROR(__xludf.DUMMYFUNCTION("""COMPUTED_VALUE"""),"2504-ENEFESGC") -> 2504-ENEFESGC | B88: =IFERROR(__xludf.DUMMYFUNCTION("""COMPUTED_VALUE"""),"La Ciudad Más Linda del Mundo | Etapa 2") -> La Ciudad Más Linda del Mundo | Etapa 2 | C88: =IFERROR(__xludf.DUMMYFUNCTION("""COMPUTED_VALUE"""),46087.0) -> 46087 | D88: =IFERROR(__xludf.DUMMYFUNCTION("""COMPUTED_VALUE"""),46112.0) -> 46112 | E88: =IFERROR(__xludf.DUMMYFUNCTION("""COMPUTED_VALUE"""),"Ciudad Atractiva") -> Ciudad Atractiva | F88: =IFERROR(__xludf.DUMMYFUNCTION("""COMPUTED_VALUE"""),"Festivales y Eventos") -> Festivales y Eventos | G88: =IFERROR(__xludf.DUMMYFUNCTION("""COMPUTED_VALUE"""),"Finalizada") -> Finalizada | H88: 26387070 | I88: 1127725 | J88: 16601 | K88: 672600 | L88: 18.517806 | M88: 39.231445 | N88: 0 | O88: 0 | P88: 0 | Q88: 0 | R88: 0 | S88: 0 | T88: 0 | U88: 0 | V88: 0 | W88: 0 | X88: 0 | Y88: 0 | Z88: 0 | AA88: 0 | AB88: 0 | AC88: 0
A89: =IFERROR(__xludf.DUMMYFUNCTION("""COMPUTED_VALUE"""),"2505-ENEPCCVC") -> 2505-ENEPCCVC | B89: =IFERROR(__xludf.DUMMYFUNCTION("""COMPUTED_VALUE"""),"Verano 2026 - Misión Bomberos: Un Día en la Estación FEBRERO") -> Verano 2026 - Misión Bomberos: Un Día en la Estación FEBRERO | C89: =IFERROR(__xludf.DUMMYFUNCTION("""COMPUTED_VALUE"""),46051.0) -> 46051 | D89: =IFERROR(__xludf.DUMMYFUNCTION("""COMPUTED_VALUE"""),46051.0) -> 46051 | E89: =IFERROR(__xludf.DUMMYFUNCTION("""COMPUTED_VALUE"""),"Cercanía") -> Cercanía | F89: =IFERROR(__xludf.DUMMYFUNCTION("""COMPUTED_VALUE"""),"Cercanía y PC") -> Cercanía y PC | G89: =IFERROR(__xludf.DUMMYFUNCTION("""COMPUTED_VALUE"""),"Finalizada") -> Finalizada | H89: 0 | I89: 0 | J89: 0 | K89: 0 | L89: 0 | M89: 0 | N89: 57099 | O89: 56035 | P89: 16960 | Q89: 393 | R89: 0 | S89: 0 | T89: 0 | U89: 0 | V89: 0 | W89: 0 | X89: 0 | Y89: 0 | Z89: 0 | AA89: 0 | AB89: 0 | AC89: 0 | AE89: Pieza
A90: =IFERROR(__xludf.DUMMYFUNCTION("""COMPUTED_VALUE"""),"2506-ENEPCCVC") -> 2506-ENEPCCVC | B90: =IFERROR(__xludf.DUMMYFUNCTION("""COMPUTED_VALUE"""),"Verano 2026 - La Gran Aventura del Reciclaje | Febrero") -> Verano 2026 - La Gran Aventura del Reciclaje | Febrero | C90: =IFERROR(__xludf.DUMMYFUNCTION("""COMPUTED_VALUE"""),46050.0) -> 46050 | D90: =IFERROR(__xludf.DUMMYFUNCTION("""COMPUTED_VALUE"""),46050.0) -> 46050 | E90: =IFERROR(__xludf.DUMMYFUNCTION("""COMPUTED_VALUE"""),"Cercanía") -> Cercanía | F90: =IFERROR(__xludf.DUMMYFUNCTION("""COMPUTED_VALUE"""),"Cercanía y PC") -> Cercanía y PC | G90: =IFERROR(__xludf.DUMMYFUNCTION("""COMPUTED_VALUE"""),"Finalizada") -> Finalizada | H90: 0 | I90: 0 | J90: 0 | K90: 0 | L90: 0 | M90: 0 | N90: 34666 | O90: 33494 | P90: 5167 | Q90: 97 | R90: 0 | S90: 0 | T90: 0 | U90: 0 | V90: 0 | W90: 0 | X90: 0 | Y90: 0 | Z90: 0 | AA90: 0 | AB90: 0 | AC90: 0 | AE90: Pieza
A91: =IFERROR(__xludf.DUMMYFUNCTION("""COMPUTED_VALUE"""),"2507-ENEPCCVC") -> 2507-ENEPCCVC | B91: =IFERROR(__xludf.DUMMYFUNCTION("""COMPUTED_VALUE"""),"Verano 2026 - Expedición Botánica - 2") -> Verano 2026 - Expedición Botánica - 2 | C91: =IFERROR(__xludf.DUMMYFUNCTION("""COMPUTED_VALUE"""),46051.0) -> 46051 | D91: =IFERROR(__xludf.DUMMYFUNCTION("""COMPUTED_VALUE"""),46051.0) -> 46051 | E91: =IFERROR(__xludf.DUMMYFUNCTION("""COMPUTED_VALUE"""),"Cercanía") -> Cercanía | F91: =IFERROR(__xludf.DUMMYFUNCTION("""COMPUTED_VALUE"""),"Cercanía y PC") -> Cercanía y PC | G91: =IFERROR(__xludf.DUMMYFUNCTION("""COMPUTED_VALUE"""),"Finalizada") -> Finalizada | H91: 0 | I91: 0 | J91: 0 | K91: 0 | L91: 0 | M91: 0 | N91: 49880 | O91: 48946 | P91: 15010 | Q91: 433 | R91: 0 | S91: 0 | T91: 0 | U91: 0 | V91: 0 | W91: 0 | X91: 0 | Y91: 0 | Z91: 0 | AA91: 0 | AB91: 0 | AC91: 0 | AE91: Pieza
A92: =IFERROR(__xludf.DUMMYFUNCTION("""COMPUTED_VALUE"""),"2508-ENEINFGC") -> 2508-ENEINFGC | B92: =IFERROR(__xludf.DUMMYFUNCTION("""COMPUTED_VALUE"""),"Infraestructura I AU Dellepiane : durante de obra") -> Infraestructura I AU Dellepiane : durante de obra | C92: =IFERROR(__xludf.DUMMYFUNCTION("""COMPUTED_VALUE"""),46049.0) -> 46049 | D92: =IFERROR(__xludf.DUMMYFUNCTION("""COMPUTED_VALUE"""),46063.0) -> 46063 | E92: =IFERROR(__xludf.DUMMYFUNCTION("""COMPUTED_VALUE"""),"Movilidad") -> Movilidad | F92: =IFERROR(__xludf.DUMMYFUNCTION("""COMPUTED_VALUE"""),"Infraestructura") -> Infraestructura | G92: =IFERROR(__xludf.DUMMYFUNCTION("""COMPUTED_VALUE"""),"Finalizada") -> Finalizada | H92: 2133201 | I92: 0 | J92: 11726 | K92: 810555 | L92: 0.56835378 | M92: 2.6317782 | N92: 150038 | O92: 146815 | P92: 34417 | Q92: 972 | R92: 0 | S92: 0 | T92: 0 | U92: 0 | V92: 0 | W92: 0 | X92: 0 | Y92: 0 | Z92: 0 | AA92: 0 | AB92: 0 | AC92: 0 | AE92: Pieza
A93: =IFERROR(__xludf.DUMMYFUNCTION("""COMPUTED_VALUE"""),"2510-ENEINFGC") -> 2510-ENEINFGC | B93: =IFERROR(__xludf.DUMMYFUNCTION("""COMPUTED_VALUE"""),"Infraestructura I Cambio de sentido calle Reconquista") -> Infraestructura I Cambio de sentido calle Reconquista | C93: =IFERROR(__xludf.DUMMYFUNCTION("""COMPUTED_VALUE"""),46048.0) -> 46048 | D93: =IFERROR(__xludf.DUMMYFUNCTION("""COMPUTED_VALUE"""),46062.0) -> 46062 | E93: =IFERROR(__xludf.DUMMYFUNCTION("""COMPUTED_VALUE"""),"Movilidad") -> Movilidad | F93: =IFERROR(__xludf.DUMMYFUNCTION("""COMPUTED_VALUE"""),"Infraestructura") -> Infraestructura | G93: =IFERROR(__xludf.DUMMYFUNCTION("""COMPUTED_VALUE"""),"Finalizada") -> Finalizada | H93: 194515 | I93: 0 | J93: 13 | K93: 137491 | L93: 1.4147471 | M93: 1.4147471 | N93: 22322 | O93: 21947 | P93: 8823 | Q93: 203 | R93: 0 | S93: 0 | T93: 0 | U93: 0 | V93: 0 | W93: 0 | X93: 0 | Y93: 0 | Z93: 0 | AA93: 0 | AB93: 0 | AC93: 0 | AE93: Pieza
A94: =IFERROR(__xludf.DUMMYFUNCTION("""COMPUTED_VALUE"""),"2511-ENEINFGC") -> 2511-ENEINFGC | B94: =IFERROR(__xludf.DUMMYFUNCTION("""COMPUTED_VALUE"""),"Infraestructura I Cortes por obras TramBus ENERO") -> Infraestructura I Cortes por obras TramBus ENERO | C94: =IFERROR(__xludf.DUMMYFUNCTION("""COMPUTED_VALUE"""),46051.0) -> 46051 | D94: =IFERROR(__xludf.DUMMYFUNCTION("""COMPUTED_VALUE"""),46054.0) -> 46054 | E94: =IFERROR(__xludf.DUMMYFUNCTION("""COMPUTED_VALUE"""),"Movilidad") -> Movilidad | F94: =IFERROR(__xludf.DUMMYFUNCTION("""COMPUTED_VALUE"""),"Infraestructura") -> Infraestructura | G94: =IFERROR(__xludf.DUMMYFUNCTION("""COMPUTED_VALUE"""),"Finalizada") -> Finalizada | H94: 1038637 | I94: 0 | J94: 20 | K94: 635853 | L94: 1.6334546 | M94: 1.6334546 | N94: 218884 | O94: 215091 | P94: 68978 | Q94: 2643 | R94: 0 | S94: 0 | T94: 0 | U94: 0 | V94: 0 | W94: 0 | X94: 0 | Y94: 0 | Z94: 0 | AA94: 38263 | AB94: 35939 | AC94: 182 | AE94: Pieza
A95: =IFERROR(__xludf.DUMMYFUNCTION("""COMPUTED_VALUE"""),"2512-ENESALGC") -> 2512-ENESALGC | B95: =IFERROR(__xludf.DUMMYFUNCTION("""COMPUTED_VALUE""")," Envío Deploy GDE 27.01.2026") -> Envío Deploy GDE 27.01.2026 | C95: =IFERROR(__xludf.DUMMYFUNCTION("""COMPUTED_VALUE"""),46049.0) -> 46049 | D95: =IFERROR(__xludf.DUMMYFUNCTION("""COMPUTED_VALUE"""),46049.0) -> 46049 | E95: =IFERROR(__xludf.DUMMYFUNCTION("""COMPUTED_VALUE"""),"Cuidado") -> Cuidado | F95: =IFERROR(__xludf.DUMMYFUNCTION("""COMPUTED_VALUE"""),"Salud") -> Salud | G95: =IFERROR(__xludf.DUMMYFUNCTION("""COMPUTED_VALUE"""),"Finalizada") -> Finalizada | H95: 0 | I95: 0 | J95: 0 | K95: 0 | L95: 0 | M95: 0 | N95: 7062 | O95: 7019 | P95: 2964 | Q95: 229 | R95: 0 | S95: 0 | T95: 0 | U95: 0 | V95: 0 | W95: 0 | X95: 0 | Y95: 0 | Z95: 0 | AA95: 0 | AB95: 0 | AC95: 0 | AE95: Pieza
A96: =IFERROR(__xludf.DUMMYFUNCTION("""COMPUTED_VALUE"""),"2513-ENEPCCVC") -> 2513-ENEPCCVC | B96: =IFERROR(__xludf.DUMMYFUNCTION("""COMPUTED_VALUE"""),"Priorización de Nombre Paso Bajo Nivel Bosch") -> Priorización de Nombre Paso Bajo Nivel Bosch | C96: =IFERROR(__xludf.DUMMYFUNCTION("""COMPUTED_VALUE"""),46057.0) -> 46057 | D96: =IFERROR(__xludf.DUMMYFUNCTION("""COMPUTED_VALUE"""),46057.0) -> 46057 | E96: =IFERROR(__xludf.DUMMYFUNCTION("""COMPUTED_VALUE"""),"Cercanía") -> Cercanía | F96: =IFERROR(__xludf.DUMMYFUNCTION("""COMPUTED_VALUE"""),"Cercanía y PC") -> Cercanía y PC | G96: =IFERROR(__xludf.DUMMYFUNCTION("""COMPUTED_VALUE"""),"Finalizada") -> Finalizada | H96: 0 | I96: 0 | J96: 0 | K96: 0 | L96: 0 | M96: 0 | N96: 26962 | O96: 26396 | P96: 5693 | Q96: 547 | R96: 0 | S96: 0 | T96: 0 | U96: 0 | V96: 0 | W96: 0 | X96: 0 | Y96: 0 | Z96: 0 | AA96: 0 | AB96: 0 | AC96: 0 | AE96: Pieza
A97: =IFERROR(__xludf.DUMMYFUNCTION("""COMPUTED_VALUE"""),"2514-ENEINFGC") -> 2514-ENEINFGC | B97: =IFERROR(__xludf.DUMMYFUNCTION("""COMPUTED_VALUE"""),"Infraestructura I Nuevo Acceso al Paseo del Bajo") -> Infraestructura I Nuevo Acceso al Paseo del Bajo | C97: =IFERROR(__xludf.DUMMYFUNCTION("""COMPUTED_VALUE"""),46150.0) -> 46150 | D97: =IFERROR(__xludf.DUMMYFUNCTION("""COMPUTED_VALUE"""),46150.0) -> 46150 | E97: =IFERROR(__xludf.DUMMYFUNCTION("""COMPUTED_VALUE"""),"Movilidad") -> Movilidad | F97: =IFERROR(__xludf.DUMMYFUNCTION("""COMPUTED_VALUE"""),"Infraestructura") -> Infraestructura | G97: =IFERROR(__xludf.DUMMYFUNCTION("""COMPUTED_VALUE"""),"Finalizada") -> Finalizada | H97: 0 | I97: 0 | J97: 0 | K97: 0 | L97: 0 | M97: 0 | N97: 155026 | O97: 153885 | P97: 67635 | Q97: 2686 | R97: 0 | S97: 0 | T97: 0 | U97: 0 | V97: 0 | W97: 0 | X97: 0 | Y97: 0 | Z97: 0 | AA97: 0 | AB97: 0 | AC97: 0 | AE97: Pieza
A98: =IFERROR(__xludf.DUMMYFUNCTION("""COMPUTED_VALUE"""),"2515-ENEINFGJ") -> 2515-ENEINFGJ | B98: =IFERROR(__xludf.DUMMYFUNCTION("""COMPUTED_VALUE"""),"Infraestructura I Anillo Pampa: Inicio de obra + Cortes") -> Infraestructura I Anillo Pampa: Inicio de obra + Cortes | C98: =IFERROR(__xludf.DUMMYFUNCTION("""COMPUTED_VALUE"""),46049.0) -> 46049 | D98: =IFERROR(__xludf.DUMMYFUNCTION("""COMPUTED_VALUE"""),46167.0) -> 46167 | E98: =IFERROR(__xludf.DUMMYFUNCTION("""COMPUTED_VALUE"""),"Movilidad") -> Movilidad | F98: =IFERROR(__xludf.DUMMYFUNCTION("""COMPUTED_VALUE"""),"Infraestructura") -> Infraestructura | G98: =IFERROR(__xludf.DUMMYFUNCTION("""COMPUTED_VALUE"""),"Finalizada") -> Finalizada | H98: 10369425 | I98: 3848246 | J98: 31546 | K98: 316958 | L98: 2.6814625 | M98: 32.715454 | N98: 399242 | O98: 394575 | P98: 134230 | Q98: 5084 | R98: 0 | S98: 0 | T98: 0 | U98: 0 | V98: 0 | W98: 0 | X98: 0 | Y98: 0 | Z98: 0 | AA98: 0 | AB98: 0 | AC98: 0 | AD98: https://www.facebook.com/reel/26974859272149704 | AE98: Pieza
A99: =IFERROR(__xludf.DUMMYFUNCTION("""COMPUTED_VALUE"""),"2516-ENESALCG") -> 2516-ENESALCG | B99: =IFERROR(__xludf.DUMMYFUNCTION("""COMPUTED_VALUE"""),"Carrusel Refugios climáticos") -> Carrusel Refugios climáticos | C99: =IFERROR(__xludf.DUMMYFUNCTION("""COMPUTED_VALUE"""),46049.0) -> 46049 | D99: =IFERROR(__xludf.DUMMYFUNCTION("""COMPUTED_VALUE"""),46066.0) -> 46066 | E99: =IFERROR(__xludf.DUMMYFUNCTION("""COMPUTED_VALUE"""),"Cuidado") -> Cuidado | F99: =IFERROR(__xludf.DUMMYFUNCTION("""COMPUTED_VALUE"""),"Salud") -> Salud | G99: =IFERROR(__xludf.DUMMYFUNCTION("""COMPUTED_VALUE"""),"Finalizada") -> Finalizada | H99: 1502590 | I99: 0 | J99: 2460 | K99: 1034589 | L99: 1.4523545 | M99: 1.4523545 | N99: 0 | O99: 0 | P99: 0 | Q99: 0 | R99: 0 | S99: 0 | T99: 0 | U99: 0 | V99: 0 | W99: 0 | X99: 0 | Y99: 0 | Z99: 0 | AA99: 0 | AB99: 0 | AC99: 0
A100: =IFERROR(__xludf.DUMMYFUNCTION("""COMPUTED_VALUE"""),"2517-ENEINFGC") -> 2517-ENEINFGC | B100: =IFERROR(__xludf.DUMMYFUNCTION("""COMPUTED_VALUE""")," Infraestructura I PAN: inicio de obra") -> Infraestructura I PAN: inicio de obra | C100: =IFERROR(__xludf.DUMMYFUNCTION("""COMPUTED_VALUE"""),46052.0) -> 46052 | D100: =IFERROR(__xludf.DUMMYFUNCTION("""COMPUTED_VALUE"""),46072.0) -> 46072 | E100: =IFERROR(__xludf.DUMMYFUNCTION("""COMPUTED_VALUE"""),"Movilidad") -> Movilidad | F100: =IFERROR(__xludf.DUMMYFUNCTION("""COMPUTED_VALUE"""),"Infraestructura") -> Infraestructura | G100: =IFERROR(__xludf.DUMMYFUNCTION("""COMPUTED_VALUE"""),"Finalizada") -> Finalizada | H100: 0 | I100: 0 | J100: 0 | K100: 0 | L100: 0 | M100: 0 | N100: 75358 | O100: 74094 | P100: 27113 | Q100: 1359 | R100: 0 | S100: 0 | T100: 0 | U100: 0 | V100: 0 | W100: 0 | X100: 0 | Y100: 0 | Z100: 0 | AA100: 65784 | AB100: 62454 | AC100: 987 | AE100: Pieza
...

Sheet resumen_metricas
A1: id_cuentas | B1: nombre_campaña | C1: fecha_inicio | D1: fecha_fin | E1: eje | F1: area | G1: estado | H1: digital_impresiones | I1: digital_visualizaciones | J1: digital_clics | K1: meta_alcance | L1: meta_frecuencia | M1: frecuencia_total | N1: mails_enviados | O1: mails_entregados | P1: mails_aperturas | Q1: mails_clics | R1: call_enviado | S1: call_discado | T1: call_contactados | U1: call_efectivos | V1: ivr_audiencia | W1: ivr_realizados | X1: ivr_atendidos | Y1: ivr_escucha75 | Z1: ivr_marque1 | AA1: sms_enviados | AB1: sms_entregados | AC1: sms_clics | AD1: pieza_meta | AE1: pieza_mail
A2: 1871-AGOEDUGC | B2: Campaña GCBA | Educación | TUMO | C2: 45959 | D2: 46203 | E2: Cuidado | F2: Educación | G2: Finalizada | H2: 201273767 | I2: 21618564 | J2: 2637230 | K2: 9405671 | L2: 1.211467 | M2: 21.399193 | N2: 858783 | O2: 844304 | P2: 285060 | Q2: 8156 | R2: 4476 | S2: 4476 | T2: 1117 | U2: 854 | V2: 0 | W2: 0 | X2: 0 | Y2: 0 | Z2: 0 | AA2: 0 | AB2: 0 | AC2: 0 | AD2: https://www.facebook.com/reel/818777800864033
A3: 1895-SEPEPHGC | B3: PIEZAS M2 | MEPHU | REPAVIMENTACIÓN | C3: 46052 | D3: 46178 | E3: M2 | F3: Espacio Público e Higiene Urbana | G3: Finalizada | H3: 0 | I3: 0 | J3: 0 | K3: 0 | L3: 0 | M3: 0 | N3: 21556 | O3: 21228 | P3: 7666 | Q3: 393 | R3: 0 | S3: 0 | T3: 0 | U3: 0 | V3: 0 | W3: 0 | X3: 0 | Y3: 0 | Z3: 0 | AA3: 0 | AB3: 0 | AC3: 0 | AE3: Pieza
A4: 1896-SEPEPHGC | B4: PIEZAS M2 | MEPHU | LIMPIEZA INTENSIVA | C4: 46031 | D4: 46136 | E4: M2 | F4: Espacio Público e Higiene Urbana | G4: Finalizada | H4: 0 | I4: 0 | J4: 0 | K4: 0 | L4: 0 | M4: 0 | N4: 648150 | O4: 634433 | P4: 181275 | Q4: 1540 | R4: 0 | S4: 0 | T4: 0 | U4: 0 | V4: 0 | W4: 0 | X4: 0 | Y4: 0 | Z4: 0 | AA4: 0 | AB4: 0 | AC4: 0 | AE4: Pieza
A5: 1933-SEPINFGC | B5: CAMPAÑA GCBA | INFRAESTRUCTURA | Campaña 360° Movilidad 2025 | C5: 45936 | D5: 46081 | E5: Movilidad | F5: Infraestructura | G5: Finalizada | H5: 120265231 | I5: 14353067 | J5: 530499 | K5: 6681997 | L5: 0.9273355 | M5: 17.998396 | N5: 2962736 | O5: 3124082 | P5: 1008617 | Q5: 19835 | R5: 0 | S5: 0 | T5: 0 | U5: 0 | V5: 0 | W5: 0 | X5: 0 | Y5: 0 | Z5: 0 | AA5: 16505 | AB5: 15794 | AC5: 82 | AD5: https://www.facebook.com/GCBA/posts/pfbid02ySETv8mbLPx3NFrrHh1eRhVRmMimid99iTcJQu2RtwUS7KCAiwKP9qoSStF1cMSml | AE5: Pieza
A6: 1942-SEPEPHGC | B6: DGPLES | MEPHU | REPARACIÓN DE VEREDAS | C6: 46031 | D6: 46223 | E6: M2 | F6: Espacio Público e Higiene Urbana | G6: Finalizada | H6: 0 | I6: 0 | J6: 0 | K6: 0 | L6: 0 | M6: 0 | N6: 69878 | O6: 68815 | P6: 23523 | Q6: 1379 | R6: 0 | S6: 0 | T6: 0 | U6: 0 | V6: 0 | W6: 0 | X6: 0 | Y6: 0 | Z6: 0 | AA6: 0 | AB6: 0 | AC6: 0 | AE6: Pieza
A7: 1943-SEPEPHGC | B7: DGPLES | MEPHU | READOQUINADO | C7: 46031 | D7: 46223 | E7: M2 | F7: Espacio Público e Higiene Urbana | G7: Finalizada | H7: 0 | I7: 0 | J7: 0 | K7: 0 | L7: 0 | M7: 0 | N7: 15590 | O7: 15371 | P7: 5329 | Q7: 415 | R7: 0 | S7: 0 | T7: 0 | U7: 0 | V7: 0 | W7: 0 | X7: 0 | Y7: 0 | Z7: 0 | AA7: 0 | AB7: 0 | AC7: 0 | AE7: Pieza
A8: 1946-SEPEPHGC | B8: CAMPAÑA GCBA | MEPHU | PLUVIALES | C8: 46038 | D8: 46223 | E8: M2 | F8: Espacio Público e Higiene Urbana | G8: Finalizada | H8: 0 | I8: 0 | J8: 0 | K8: 0 | L8: 0 | M8: 0 | N8: 18528 | O8: 18309 | P8: 6404 | Q8: 426 | R8: 0 | S8: 0 | T8: 0 | U8: 0 | V8: 0 | W8: 0 | X8: 0 | Y8: 0 | Z8: 0 | AA8: 0 | AB8: 0 | AC8: 0 | AE8: Pieza
A9: 1964-SEPEPHGC | B9: MEPHU RECAMBIO TECNOLÓGICO M2 | C9: 46071 | D9: 46220 | E9: M2 | F9: Espacio Público e Higiene Urbana | G9: Finalizada | H9: 0 | I9: 0 | J9: 0 | K9: 0 | L9: 0 | M9: 0 | N9: 444872 | O9: 439325 | P9: 133653 | Q9: 3043 | R9: 0 | S9: 0 | T9: 0 | U9: 0 | V9: 0 | W9: 0 | X9: 0 | Y9: 0 | Z9: 0 | AA9: 0 | AB9: 0 | AC9: 0 | AE9: Pieza
A10: 2033-SEPEPHGC | B10: M2 PODA | C10: 46035 | D10: 46216 | E10: M2 | F10: Espacio Público e Higiene Urbana | G10: Finalizada | H10: 0 | I10: 0 | J10: 0 | K10: 0 | L10: 0 | M10: 0 | N10: 145204 | O10: 141927 | P10: 46936 | Q10: 2044 | R10: 0 | S10: 0 | T10: 0 | U10: 0 | V10: 0 | W10: 0 | X10: 0 | Y10: 0 | Z10: 0 | AA10: 0 | AB10: 0 | AC10: 0 | AE10: Pieza
A11: 2100-OCTSALGC | B11: Cesac 12 - Más consultorios | C11: 46013 | D11: 46027 | E11: Cuidado | F11: Salud | G11: Finalizada | H11: 5541119 | I11: 634751 | J11: 14536 | K11: 0 | L11: 0 | M11: 0 | N11: 81077 | O11: 79591 | P11: 31217 | Q11: 1060 | R11: 0 | S11: 0 | T11: 0 | U11: 0 | V11: 0 | W11: 0 | X11: 0 | Y11: 0 | Z11: 0 | AA11: 0 | AB11: 0 | AC11: 0
A12: 2108-OCTEDUGC | B12: Inscripción 2025 a Profesorados de la Ciudad | C12: 45952 | D12: 46073 | E12: Cuidado | F12: Educación | G12: Finalizada | H12: 24528982 | I12: 0 | J12: 555619 | K12: 1745904 | L12: 1.3171446 | M12: 14.049445 | N12: 132413 | O12: 130535 | P12: 87400 | Q12: 8263 | R12: 0 | S12: 0 | T12: 0 | U12: 0 | V12: 0 | W12: 0 | X12: 0 | Y12: 0 | Z12: 0 | AA12: 0 | AB12: 0 | AC12: 0 | AD12: https://www.facebook.com/GCBA/posts/1295953569230956
A13: 2109-OCTEPHGC | B13: LIMPIEZA DE FACHADAS | M2 | C13: 46028 | D13: 46099 | E13: M2 | F13: Espacio Público e Higiene Urbana | G13: Finalizada | H13: 0 | I13: 0 | J13: 0 | K13: 0 | L13: 0 | M13: 0 | N13: 923 | O13: 898 | P13: 294 | Q13: 38 | R13: 0 | S13: 0 | T13: 0 | U13: 0 | V13: 0 | W13: 0 | X13: 0 | Y13: 0 | Z13: 0 | AA13: 0 | AB13: 0 | AC13: 0 | AE13: Pieza
A14: 2130-OCTSALGC | B14: Hospital Pirovano: Remodelaciones | C14: 46050 | D14: 46066 | E14: Cuidado | F14: Salud | G14: Finalizada | H14: 3945078 | I14: 0 | J14: 9197 | K14: 1208470 | L14: 1.0665105 | M14: 3.2645229 | N14: 100614 | O14: 99157 | P14: 42370 | Q14: 787 | R14: 0 | S14: 0 | T14: 0 | U14: 0 | V14: 0 | W14: 0 | X14: 0 | Y14: 0 | Z14: 0 | AA14: 0 | AB14: 0 | AC14: 0 | AE14: Pieza
A15: 2145-OCTVINGC | B15: PIEZAS M2 | VINCULO CIUDADANO (GESTIÓN COMUNAL) | OBRAS EN PARQUES Y PLAZAS (PATIOS DE JUEGOS) Plan 2025 | C15: 46020 | D15: 46174 | E15: M2 | F15: Vínculo Ciudadano | G15: Finalizada | H15: 2352745 | I15: 0 | J15: 7138 | K15: 1084144 | L15: 1.9502769 | M15: 2.1701407 | N15: 1136573 | O15: 1111059 | P15: 368628 | Q15: 9109 | R15: 0 | S15: 0 | T15: 0 | U15: 0 | V15: 0 | W15: 0 | X15: 0 | Y15: 0 | Z15: 0 | AA15: 0 | AB15: 0 | AC15: 0 | AD15: https://www.facebook.com/GCBA/posts/pfbid02j9NjjKC7QJSSUrKxkX55nDiWFRmCpVKSS3w7J3VpQA3DakuvLQQ5B3z96orCNRMUl | AE15: Pieza
A16: 2183-OCTSALGC | B16: Sistema de Salud Público - Genérico | C16: 45992 | D16: 46068 | E16: Cuidado | F16: Salud | G16: Finalizada | H16: 63685126 | I16: 11819633 | J16: 218716 | K16: 2510514 | L16: 2.9775759 | M16: 25.367365 | N16: 0 | O16: 0 | P16: 0 | Q16: 0 | R16: 0 | S16: 0 | T16: 0 | U16: 0 | V16: 0 | W16: 0 | X16: 0 | Y16: 0 | Z16: 0 | AA16: 44842 | AB16: 43029 | AC16: 724 | AD16: https://www.facebook.com/GCBA/posts/pfbid02QwxLwyKnw9PCTX9BXhgSSH5hJ3u56noy7igZq9orxmSsVPqjj4MMUZ5SD9xXWWQ3l
A17: 2227-NOVINFGC | B17: Infraestructura - SBASE | Campaña GCBA | Seguridad en Subte | C17: 45981 | D17: 46037 | E17: Movilidad | F17: Infraestructura | G17: Finalizada | H17: 56510666 | I17: 13306488 | J17: 109062 | K17: 2996348 | L17: 1.9993095 | M17: 18.859847 | N17: 448806 | O17: 441370 | P17: 157871 | Q17: 1073 | R17: 0 | S17: 0 | T17: 0 | U17: 0 | V17: 0 | W17: 0 | X17: 0 | Y17: 0 | Z17: 0 | AA17: 0 | AB17: 0 | AC17: 0 | AD17: https://www.facebook.com/GCBA/posts/pfbid0swuyoC42Lys1AAsD6UQ7EPU5B43KXVdVXxxXU4X9oHEJ7DjKXtavLAdDHd6BpccBl | AE17: Pieza
A18: 2239-NOVSALGC | B18: Cuidados del Calor 2025 - Prevención | C18: 45996 | D18: 46081 | E18: Cuidado | F18: Salud | G18: Finalizada | H18: 44318251 | I18: 7628858 | J18: 207888 | K18: 3270088 | L18: 3.1020116 | M18: 13.552617 | N18: 393084 | O18: 386497 | P18: 128673 | Q18: 1026 | R18: 0 | S18: 0 | T18: 0 | U18: 0 | V18: 60114 | W18: 60114 | X18: 50294 | Y18: 14803 | Z18: 0 | AA18: 44261 | AB18: 42094 | AC18: 432 | AD18: https://www.facebook.com/GCBA/posts/pfbid02fZ6eoJSg8zqDVE3RogP3nnn5hqo9sxTPxRzzs7HgyWNUmM6XZmtSLLNohgBDJZ2xl | AE18: Pieza
A19: 2240-NOVSALGC | B19: Cuidados del Calor 2025 - Síntomas | C19: 46009 | D19: 46081 | E19: Cuidado | F19: Salud | G19: Finalizada | H19: 37792450 | I19: 5153493 | J19: 136800 | K19: 1979868 | L19: 3.4276906 | M19: 19.088369 | N19: 202759 | O19: 198265 | P19: 46872 | Q19: 167 | R19: 0 | S19: 0 | T19: 0 | U19: 0 | V19: 0 | W19: 0 | X19: 0 | Y19: 0 | Z19: 0 | AA19: 0 | AB19: 0 | AC19: 0 | AD19: https://www.facebook.com/GCBA/posts/pfbid02XEqLAZ3ja1iUkCQ1AFBkuUXwxFv9zsX5K86BwUhreM4wjGsmh9yx8x8cEFwBnwo1l | AE19: Pieza
A20: 2241-NOVSALGC | B20: Cuidados del Calor 2025 - Alertas Meteorológicas | C20: 46020 | D20: 46058 | E20: Cuidado | F20: Salud | G20: Finalizada | H20: 6328947 | I20: 0 | J20: 50769 | K20: 2394484 | L20: 1.3164298 | M20: 2.6431361 | N20: 246623 | O20: 243978 | P20: 116854 | Q20: 114 | R20: 0 | S20: 0 | T20: 0 | U20: 0 | V20: 0 | W20: 0 | X20: 0 | Y20: 0 | Z20: 0 | AA20: 62485 | AB20: 59237 | AC20: 372 | AD20: https://www.facebook.com/GCBA/posts/pfbid02j9NjjKC7QJSSUrKxkX55nDiWFRmCpVKSS3w7J3VpQA3DakuvLQQ5B3z96orCNRMUl
A21: 2255-NOVSALGC | B21: Sistema de Salud Público - Geolocalizado | C21: 46008 | D21: 46068 | E21: Cuidado | F21: Salud | G21: Finalizada | H21: 38197009 | I21: 0 | J21: 552532 | K21: 1566896 | L21: 3.6226406 | M21: 24.377501 | N21: 907590 | O21: 862876 | P21: 284653 | Q21: 624 | R21: 0 | S21: 0 | T21: 0 | U21: 0 | V21: 0 | W21: 0 | X21: 0 | Y21: 0 | Z21: 0 | AA21: 0 | AB21: 0 | AC21: 0 | AD21: https://www.facebook.com/GCBA/posts/pfbid02dx5PKW9dhfnoR52qjj3Cxnq9opfoRmH6HwTJx9uacynmmZet5vn1FL6Xavv3J8ZXl | AE21: Pieza
A22: 2256-NOVSALGC | B22: Sistema de Salud Público - Diferenciado x Audiencias | C22: 46010 | D22: 46068 | E22: Cuidado | F22: Salud | G22: Finalizada | H22: 28261480 | I22: 5404995 | J22: 94248 | K22: 1318610 | L22: 2.6421224 | M22: 21.432781 | N22: 348034 | O22: 344435 | P22: 178103 | Q22: 356 | R22: 0 | S22: 0 | T22: 0 | U22: 0 | V22: 0 | W22: 0 | X22: 0 | Y22: 0 | Z22: 0 | AA22: 0 | AB22: 0 | AC22: 0 | AD22: https://www.facebook.com/GCBA/posts/pfbid02SB5PG237gJvSQGMPLHpQAP5b6uxqxh8AqRUS3csVWmCnYyvd77i8d67LSBMnBtg8l | AE22: Pieza
A23: 2293-NOVFESGC | B23: LA CIUDAD MAS LINDA DEL MUNDO | C23: 45994 | D23: 46053 | E23: Ciudad Atractiva | F23: Festivales y Eventos | G23: Finalizada | H23: 75245249 | I23: 13466546 | J23: 799082 | K23: 7843297 | L23: 1.9541976 | M23: 9.5935739 | N23: 657996 | O23: 645327 | P23: 198939 | Q23: 10076 | R23: 0 | S23: 0 | T23: 0 | U23: 0 | V23: 0 | W23: 0 | X23: 0 | Y23: 0 | Z23: 0 | AA23: 0 | AB23: 0 | AC23: 0 | AD23: https://www.facebook.com/GCBA/posts/pfbid0yZFqpziwsSvEpGHnbKnvgTkMNo6Ys8gfLmUBqRKhRCH71tiHcf1cXzt2RhCmokjMl
A24: 2318-ENEINFGC | B24: Infraestructura I Cambio de sentido Avelino Díaz y Las Casas | C24: 46040 | D24: 46053 | E24: M2 | F24: Infraestructura | G24: Finalizada | H24: 656152 | I24: 0 | J24: 4677 | K24: 293307 | L24: 2.2370826 | M24: 2.2370826 | N24: 34125 | O24: 33543 | P24: 11623 | Q24: 221 | R24: 0 | S24: 0 | T24: 0 | U24: 0 | V24: 0 | W24: 0 | X24: 0 | Y24: 0 | Z24: 0 | AA24: 0 | AB24: 0 | AC24: 0 | AD24: https://www.facebook.com/GCBA/posts/pfbid02fhrsXdCgnCn19Gs1k1PTjbTdAfYLBMqW3w4zhQLgJqH8r8uW4azYikpQk6Js8WNcl | AE24: Pieza
A25: 2322-NOVEDUGC | B25: TUMO Parque de la Innovación | C25: 46006 | D25: 46265 | E25: Cuidado | F25: Educación | G25: Activa | H25: 37630874 | I25: 2298580 | J25: 197893 | K25: 845956 | L25: 2.7451924 | M25: 44.483252 | N25: 390326 | O25: 382880 | P25: 132608 | Q25: 2847 | R25: 2471 | S25: 2471 | T25: 938 | U25: 695 | V25: 0 | W25: 0 | X25: 0 | Y25: 0 | Z25: 0 | AA25: 0 | AB25: 0 | AC25: 0 | AD25: https://www.facebook.com/reel/1259490412867632 | AE25: Pieza
A26: 2407-DICDHHGC | B26: Red de atención - Comuna 14 | C26: 46009 | D26: 46035 | E26: Cuidado | F26: Desarrollo Humano y Hábitat | G26: Finalizada | H26: 5648733 | I26: 908168 | J26: 31911 | K26: 345688 | L26: 1.5532706 | M26: 16.340553 | N26: 82291 | O26: 80644 | P26: 34390 | Q26: 427 | R26: 41000 | S26: 38657 | T26: 7137 | U26: 4305 | V26: 0 | W26: 0 | X26: 0 | Y26: 0 | Z26: 0 | AA26: 0 | AB26: 0 | AC26: 0 | AD26: https://www.facebook.com/GCBA/posts/pfbid034rFdFhu5CMuLHbUxCF393aMxjQ6Uzsq6seyeRjcjNKtzSymPzkApKt81BUxEeVj3l | AE26: Pieza
A27: 2410-DICJDGAG | B27: RDV JM | Villa Devoto 15/12 | C27: 46013 | D27: 46024 | E27: Cercanía | F27: Jefatura de Gobierno | G27: Finalizada | H27: 14229634 | I27: 322142 | J27: 29184 | K27: 0 | L27: 0 | M27: 0 | N27: 30540 | O27: 30402 | P27: 9314 | Q27: 336 | R27: 0 | S27: 0 | T27: 0 | U27: 0 | V27: 20067.047 | W27: 20067.047 | X27: 18323.305 | Y27: 7084.077 | Z27: 180 | AA27: 0 | AB27: 0 | AC27: 0
A28: 2412-DICJDGAG | B28: RDV JM | Colegiales 19/12 | C28: 46014 | D28: 46025 | E28: Cercanía | F28: Jefatura de Gobierno | G28: Finalizada | H28: 1782381 | I28: 139137 | J28: 7011 | K28: 0 | L28: 0 | M28: 0 | N28: 24878 | O28: 24515 | P28: 6879 | Q28: 163 | R28: 6770 | S28: 6769 | T28: 1751 | U28: 1295 | V28: 26545.519 | W28: 26545.519 | X28: 23902.879 | Y28: 10339.329 | Z28: 126 | AA28: 0 | AB28: 0 | AC28: 0
A29: 2423-DICJDGGC | B29: Festejos Responsables 2025 | C29: 46014 | D29: 46023 | E29: Cuidado | F29: Jefatura de Gobierno | G29: Finalizada | H29: 113032 | I29: 0 | J29: 5003 | K29: 0 | L29: 0 | M29: 0 | N29: 497431 | O29: 490986 | P29: 208233 | Q29: 1469 | R29: 12000 | S29: 11037 | T29: 2752 | U29: 2052 | V29: 0 | W29: 0 | X29: 0 | Y29: 0 | Z29: 0 | AA29: 0 | AB29: 0 | AC29: 0
A30: 2424-DICFESGC | B30: Verano en Buenos Aires 2026 | Generico | C30: 46029 | D30: 46081 | E30: Ciudad Atractiva | F30: Festivales y Eventos | G30: Finalizada | H30: 32919907 | I30: 2721109 | J30: 164357 | K30: 3975434 | L30: 2.6766625 | M30: 8.2808335 | N30: 306526 | O30: 303199 | P30: 151566 | Q30: 7233 | R30: 0 | S30: 0 | T30: 0 | U30: 0 | V30: 0 | W30: 0 | X30: 0 | Y30: 0 | Z30: 0 | AA30: 0 | AB30: 0 | AC30: 0 | AD30: https://www.facebook.com/GCBA/posts/pfbid02PmAtvdzD176mjzPpPRZmFQTNXzNjqoKr7o9wByEVUtzkzYpigMPqtXRGysNDa6Wjl | AE30: Pieza
A31: 2425-DICEPHGC | B31: Parques Iluminados M2 | C31: 46163 | D31: 46190 | E31: M2 | F31: Espacio Público e Higiene Urbana | G31: Finalizada | H31: 0 | I31: 0 | J31: 0 | K31: 0 | L31: 0 | M31: 0 | N31: 21456 | O31: 21233 | P31: 7139 | Q31: 191 | R31: 0 | S31: 0 | T31: 0 | U31: 0 | V31: 0 | W31: 0 | X31: 0 | Y31: 0 | Z31: 0 | AA31: 0 | AB31: 0 | AC31: 0 | AE31: Pieza
A32: 2426-DICSALGC | B32: Deploy HIS Ambulatorio | C32: 46030 | D32: 46030 | E32: Cuidado | F32: Salud | G32: Finalizada | H32: 0 | I32: 0 | J32: 0 | K32: 0 | L32: 0 | M32: 0 | N32: 3471 | O32: 3443 | P32: 1477 | Q32: 169 | R32: 0 | S32: 0 | T32: 0 | U32: 0 | V32: 0 | W32: 0 | X32: 0 | Y32: 0 | Z32: 0 | AA32: 0 | AB32: 0 | AC32: 0 | AE32: Pieza
A33: 2430-DICPCCVC | B33: DGPCyC | Verano 2026 - Misión Bomberos: Un día en la estación | C33: 46029 | D33: 46029 | E33: Cercanía | F33: Cercanía y PC | G33: Finalizada | H33: 0 | I33: 0 | J33: 0 | K33: 0 | L33: 0 | M33: 0 | N33: 26990 | O33: 26313 | P33: 4518 | Q33: 419 | R33: 0 | S33: 0 | T33: 0 | U33: 0 | V33: 0 | W33: 0 | X33: 0 | Y33: 0 | Z33: 0 | AA33: 0 | AB33: 0 | AC33: 0 | AE33: Pieza
A34: 2433-DICFESGC | B34: Verano en la Ciudad | AftersBA | C34: 46035 | D34: 46071 | E34: Ciudad Atractiva | F34: Festivales y Eventos | G34: Finalizada | H34: 31715868 | I34: 6079572 | J34: 33441 | K34: 103786 | L34: 81.182549 | M34: 305.58908 | N34: 231781 | O34: 227305 | P34: 76967 | Q34: 3329 | R34: 0 | S34: 0 | T34: 0 | U34: 0 | V34: 0 | W34: 0 | X34: 0 | Y34: 0 | Z34: 0 | AA34: 0 | AB34: 0 | AC34: 0 | AD34: https://www.facebook.com/reel/1401103571662551 | AE34: Pieza
A35: 2434-DICFESGC | B35: Verano en la Ciudad | Billboard Summer | C35: 46031 | D35: 46039 | E35: Ciudad Atractiva | F35: Festivales y Eventos | G35: Finalizada | H35: 12944042 | I35: 2874187 | J35: 12481 | K35: 29161 | L35: 137.44429 | M35: 443.88197 | N35: 175380 | O35: 172038 | P35: 58466 | Q35: 3201 | R35: 0 | S35: 0 | T35: 0 | U35: 0 | V35: 0 | W35: 0 | X35: 0 | Y35: 0 | Z35: 0 | AA35: 0 | AB35: 0 | AC35: 0 | AD35: https://www.facebook.com/reel/1385888349747054/ | AE35: Pieza
A36: 2435-DICFESGC | B36: Verano en la Ciudad | Atardeceres en los parques | C36: 46041 | D36: 46062 | E36: Ciudad Atractiva | F36: Festivales y Eventos | G36: Finalizada | H36: 18780836 | I36: 4407686 | J36: 26564 | K36: 2036212 | L36: 2.9967616 | M36: 9.2234188 | N36: 107518 | O36: 86557 | P36: 31980 | Q36: 2402 | R36: 6925 | S36: 6908 | T36: 1374 | U36: 1022 | V36: 0 | W36: 0 | X36: 0 | Y36: 0 | Z36: 0 | AA36: 0 | AB36: 0 | AC36: 0 | AD36: https://www.facebook.com/GCBA/posts/pfbid0rLEuW4M93zccXsLKxEbAgdx71UvEEJJusTpaAfZzdSBaQDr7KZx36ckPuiwG1Rhql | AE36: Pieza
A37: 2437-DICFESGC | B37: Verano en la Ciudad | Verano en las plazas | C37: 46038 | D37: 46073 | E37: Ciudad Atractiva | F37: Festivales y Eventos | G37: Finalizada | H37: 18930747 | I37: 5099312 | J37: 20844 | K37: 1292752 | L37: 5.5283542 | M37: 14.643758 | N37: 710718 | O37: 674580 | P37: 197102 | Q37: 16421 | R37: 0 | S37: 0 | T37: 0 | U37: 0 | V37: 0 | W37: 0 | X37: 0 | Y37: 0 | Z37: 0 | AA37: 0 | AB37: 0 | AC37: 0 | AD37: https://www.facebook.com/GCBA/posts/pfbid032UmvaRZ3eAJNRC4zHziYpyXVaPbbTucP4LKQNEh1BSxa3mTrzNz6mZGgDzRqYkTel | AE37: Pieza
A38: 2439-DICINFGC | B38: Infraestructura I Bus Eléctricos: extensión recorrido | C38: 46028 | D38: 46042 | E38: Movilidad | F38: Infraestructura | G38: Finalizada | H38: 665162 | I38: 3616 | J38: 2743 | K38: 355350 | L38: 1.8718503 | M38: 1.8718503 | N38: 90056 | O38: 88895 | P38: 43812 | Q38: 2567 | R38: 0 | S38: 0 | T38: 0 | U38: 0 | V38: 0 | W38: 0 | X38: 0 | Y38: 0 | Z38: 0 | AA38: 0 | AB38: 0 | AC38: 0 | AD38: https://www.facebook.com/GCBA/posts/pfbid08jZno8hyH4wUURfHDj5eKgWYFcmdn1Lqh1sjbw1zmwZJ4dSZGEmpAeit2EdCjTLal | AE38: Pieza
A39: 2441-DICINFGC | B39: Infraestructura I Obras M2: Trambus ENERO | C39: 46035 | D39: 46053 | E39: Movilidad | F39: Infraestructura | G39: Finalizada | H39: 3270390 | I39: 0 | J39: 47102 | K39: 469739 | L39: 2.0681974 | M39: 6.9621428 | N39: 56667 | O39: 55627 | P39: 19152 | Q39: 1989 | R39: 0 | S39: 0 | T39: 0 | U39: 0 | V39: 0 | W39: 0 | X39: 0 | Y39: 0 | Z39: 0 | AA39: 0 | AB39: 0 | AC39: 0 | AD39: https://www.facebook.com/GCBA/posts/pfbid0nA1q3xBcy1eJcYdmUe5hTkrG2zrbURY6VnDCqEubzKtTg6UhWBiGjhgYWJQUsK86l | AE39: Pieza
A40: 2443-DICNEWAN | B40: Acciones de la Ciudad ante el calor extremo | C40: 46027 | D40: 46035 | E40: Cuidado | F40: Anuncios y Newsletter | G40: Finalizada | H40: 8154163 | I40: 0 | J40: 49108 | K40: 682062 | L40: 1.5975703 | M40: 11.955164 | N40: 236590 | O40: 233694 | P40: 54587 | Q40: 2742 | R40: 0 | S40: 0 | T40: 0 | U40: 0 | V40: 0 | W40: 0 | X40: 0 | Y40: 0 | Z40: 0 | AA40: 0 | AB40: 0 | AC40: 0 | AD40: https://www.facebook.com/GCBA/posts/pfbid0N5sbH3engzLHtbfZQM61dN6d9zBMxwsp4N1bpfX76sx6bnCZy4398mqDoXuTfdX5l
A41: 2444-DICINFGC | B41: Infraestructura I Cortes en AU Dellepiane por obras | C41: 46021 | D41: 46034 | E41: Movilidad | F41: Infraestructura | G41: Finalizada | H41: 210936 | I41: 0 | J41: 31 | K41: 140179 | L41: 1.1381591 | M41: 1.5047618 | N41: 80433 | O41: 79263 | P41: 31500 | Q41: 336 | R41: 0 | S41: 0 | T41: 0 | U41: 0 | V41: 0 | W41: 0 | X41: 0 | Y41: 0 | Z41: 0 | AA41: 0 | AB41: 0 | AC41: 0 | AD41: https://fb.me/adspreview/facebook/1RMCueLZDYjPeIW | AE41: Pieza
A42: 2445-DICPCCVC | B42: Verano 2026 - Expedicion botanica | C42: 46034 | D42: 46034 | E42: Cercanía | F42: Cercanía y PC | G42: Finalizada | H42: 0 | I42: 0 | J42: 0 | K42: 0 | L42: 0 | M42: 0 | N42: 19382 | O42: 19018 | P42: 6067 | Q42: 215 | R42: 0 | S42: 0 | T42: 0 | U42: 0 | V42: 0 | W42: 0 | X42: 0 | Y42: 0 | Z42: 0 | AA42: 0 | AB42: 0 | AC42: 0 | AE42: Pieza
A43: 2447-DICPCCVC | B43: Verano 2026 - La Gran Aventura del Reciclaje | Enero | C43: 46031 | D43: 46031 | E43: Cercanía | F43: Cercanía y PC | G43: Finalizada | H43: 0 | I43: 0 | J43: 0 | K43: 0 | L43: 0 | M43: 0 | N43: 22406 | O43: 21763 | P43: 2883 | Q43: 56 | R43: 0 | S43: 0 | T43: 0 | U43: 0 | V43: 0 | W43: 0 | X43: 0 | Y43: 0 | Z43: 0 | AA43: 0 | AB43: 0 | AC43: 0 | AE43: Pieza
A44: 2450-ENEJDGAG | B44: RDV JM - Boedo 9/1 | C44: 46024 | D44: 46052 | E44: Cercanía | F44: Jefatura de Gobierno | G44: Finalizada | H44: 1331244 | I44: 773019 | J44: 4155 | K44: 79990 | L44: 4.04008 | M44: 16.64263 | N44: 22300 | O44: 21947 | P44: 5124 | Q44: 185 | R44: 10319 | S44: 9805 | T44: 2224 | U44: 1648 | V44: 12049 | W44: 12049 | X44: 11592 | Y44: 4731 | Z44: 49 | AA44: 0 | AB44: 0 | AC44: 0 | AD44: https://www.facebook.com/reel/850462247854341 | AE44: Pieza
A45: 2451-ENEPCCVC | B45: Participación Ciudadana - Verano en la Ciudad (Pauta RRSS) | C45: 46027 | D45: 46057 | E45: Cercanía | F45: Cercanía y PC | G45: Finalizada | H45: 2493536 | I45: 0 | J45: 1632 | K45: 655062 | L45: 3.8065649 | M45: 3.8065649 | N45: 0 | O45: 0 | P45: 0 | Q45: 0 | R45: 0 | S45: 0 | T45: 0 | U45: 0 | V45: 0 | W45: 0 | X45: 0 | Y45: 0 | Z45: 0 | AA45: 0 | AB45: 0 | AC45: 0 | AD45: https://www.facebook.com/100064853673908/posts/1304262748412169/
A46: 2453-ENEPCCVC | B46: Verano 2026 - CIFA para chicos | C46: 46043 | D46: 46049 | E46: Cercanía | F46: Cercanía y PC | G46: Finalizada | H46: 0 | I46: 0 | J46: 0 | K46: 0 | L46: 0 | M46: 0 | N46: 65448 | O46: 64031 | P46: 15667 | Q46: 168 | R46: 0 | S46: 0 | T46: 0 | U46: 0 | V46: 0 | W46: 0 | X46: 0 | Y46: 0 | Z46: 0 | AA46: 0 | AB46: 0 | AC46: 0 | AE46: Pieza
A47: 2454-ENEPCCVC | B47: Verano 2026 - Aventura en el aire | C47: 46038 | D47: 46038 | E47: Cercanía | F47: Cercanía y PC | G47: Finalizada | H47: 0 | I47: 0 | J47: 0 | K47: 0 | L47: 0 | M47: 0 | N47: 33944 | O47: 33452 | P47: 13502 | Q47: 579 | R47: 0 | S47: 0 | T47: 0 | U47: 0 | V47: 0 | W47: 0 | X47: 0 | Y47: 0 | Z47: 0 | AA47: 0 | AB47: 0 | AC47: 0 | AE47: Pieza
A48: 2456-ENEPCCVC | B48: Dejá tus rueditas | C48: 46035 | D48: 46035 | E48: Cercanía | F48: Cercanía y PC | G48: Finalizada | H48: 0 | I48: 0 | J48: 0 | K48: 0 | L48: 0 | M48: 0 | N48: 25908 | O48: 25161 | P48: 3454 | Q48: 147 | R48: 0 | S48: 0 | T48: 0 | U48: 0 | V48: 0 | W48: 0 | X48: 0 | Y48: 0 | Z48: 0 | AA48: 0 | AB48: 0 | AC48: 0 | AE48: Pieza
A49: 2457-ENEPCCVC | B49: Verano 2026 - Exploradores del Ecoparque | C49: 46036 | D49: 46036 | E49: Cercanía | F49: Cercanía y PC | G49: Finalizada | H49: 0 | I49: 0 | J49: 0 | K49: 0 | L49: 0 | M49: 0 | N49: 36289 | O49: 35904 | P49: 19164 | Q49: 240 | R49: 0 | S49: 0 | T49: 0 | U49: 0 | V49: 0 | W49: 0 | X49: 0 | Y49: 0 | Z49: 0 | AA49: 0 | AB49: 0 | AC49: 0 | AE49: Pieza
A50: 2458-ENESEGGC | B50: Campaña GCBA I Seguridad I Desalojo edificio San Telmo | C50: 46029 | D50: 46044 | E50: M2 | F50: Seguridad | G50: Finalizada | H50: 1958412 | I50: 1314287 | J50: 1288 | K50: 208110 | L50: 1.7622507 | M50: 9.4104656 | N50: 126455 | O50: 124209 | P50: 32515 | Q50: 1193 | R50: 0 | S50: 0 | T50: 0 | U50: 0 | V50: 0 | W50: 0 | X50: 0 | Y50: 0 | Z50: 0 | AA50: 0 | AB50: 0 | AC50: 0 | AD50: facebook.com/reel/654304614371554/ | AE50: Pieza
A51: 2459-ENESEGGC | B51: Campaña GCBA I Seguridad I Desalojo predio Parque Avellaneda | C51: 46030 | D51: 46045 | E51: M2 | F51: Seguridad | G51: Finalizada | H51: 2545129 | I51: 1397894 | J51: 2481 | K51: 550772 | L51: 1.8618212 | M51: 4.621021 | N51: 199955 | O51: 196224 | P51: 45064 | Q51: 964 | R51: 0 | S51: 0 | T51: 0 | U51: 0 | V51: 0 | W51: 0 | X51: 0 | Y51: 0 | Z51: 0 | AA51: 0 | AB51: 0 | AC51: 0 | AD51: facebook.com/reel/1964189401115594/ | AE51: Pieza
A52: 2460-ENEFESGC | B52: Campaña verano en la ciudad | Verano en los anfiteatros | C52: 46057 | D52: 46080 | E52: Ciudad Atractiva | F52: Festivales y Eventos | G52: Finalizada | H52: 10431799 | I52: 0 | J52: 45286 | K52: 297850 | L52: 8.6866577 | M52: 35.023666 | N52: 165205 | O52: 161928 | P52: 45115 | Q52: 4265 | R52: 0 | S52: 0 | T52: 0 | U52: 0 | V52: 0 | W52: 0 | X52: 0 | Y52: 0 | Z52: 0 | AA52: 0 | AB52: 0 | AC52: 0 | AE52: Pieza
A53: 2463-ENETURGC | B53: Elegí Argentina 2026 | Registro de Prestadores Turísticos | Viernes 9/1 | C53: 46031 | D53: 46031 | E53: Otros | F53: Turismo | G53: Finalizada | H53: 0 | I53: 0 | J53: 0 | K53: 0 | L53: 0 | M53: 0 | N53: 575 | O53: 552 | P53: 217 | Q53: 52 | R53: 0 | S53: 0 | T53: 0 | U53: 0 | V53: 0 | W53: 0 | X53: 0 | Y53: 0 | Z53: 0 | AA53: 0 | AB53: 0 | AC53: 0 | AE53: Pieza
A54: 2464-ENEINFGC | B54: CAMPAÑA GCBA | INFRAESTRUCTURA | PBN García Lorca: durante de obra | C54: 46036 | D54: 46056 | E54: Movilidad | F54: Infraestructura | G54: Finalizada | H54: 4636754 | I54: 23533 | J54: 13640 | K54: 484653 | L54: 1.4793739 | M54: 9.5671625 | N54: 71838 | O54: 70767 | P54: 28370 | Q54: 747 | R54: 0 | S54: 0 | T54: 0 | U54: 0 | V54: 0 | W54: 0 | X54: 0 | Y54: 0 | Z54: 0 | AA54: 0 | AB54: 0 | AC54: 0 | AD54: https://www.facebook.com/GCBA/posts/pfbid036pqFXR7zAF8PvFnxngTEwxPE9PqKmWq4AHHELyLosNtsxKY2jxKJRGQJxGk3ecSbl | AE54: Pieza
A55: 2465-ENEJDGAG | B55: Cafe JM - Puerto Madero 16/1 | C55: 46031 | D55: 46053 | E55: Cercanía | F55: Jefatura de Gobierno | G55: Finalizada | H55: 2758449 | I55: 903317 | J55: 4118 | K55: 31114 | L55: 2.8909494 | M55: 88.6562 | N55: 2567 | O55: 2526 | P55: 990 | Q55: 81 | R55: 0 | S55: 0 | T55: 0 | U55: 0 | V55: 0 | W55: 0 | X55: 0 | Y55: 0 | Z55: 0 | AA55: 0 | AB55: 0 | AC55: 0 | AD55: https://www.facebook.com/GCBA/posts/pfbid0BsWeHieuJG1uGtxTuMBe5GYGU77PsY829qhF8HeGWpSsWmLpxTT9CTzWTUa3pxfbl | AE55: Pieza
A56: 2466-ENEFESGC | B56: Verano en la Ciudad | Parque de la Ciudad | C56: 46041 | D56: 46066 | E56: Ciudad Atractiva | F56: Festivales y Eventos | G56: Finalizada | H56: 7612586 | I56: 230619 | J56: 9111 | L56: 0 | M56: 0 | N56: 243518 | O56: 238203 | P56: 60526 | Q56: 2710 | R56: 0 | S56: 0 | T56: 0 | U56: 0 | V56: 0 | W56: 0 | X56: 0 | Y56: 0 | Z56: 0 | AA56: 0 | AB56: 0 | AC56: 0 | AD56: https://www.facebook.com/reel/1985348935347886 | AE56: Pieza
A57: 2467-ENEFESGC | B57: Verano en la Ciudad | Verano Joven BA enero | C57: 46050 | D57: 46053 | E57: Ciudad Atractiva | F57: Festivales y Eventos | G57: Finalizada | H57: 13260814 | I57: 1700132 | J57: 13721 | K57: 176068 | L57: 40.108441 | M57: 75.316435 | N57: 191896 | O57: 188174 | P57: 63834 | Q57: 1357 | R57: 0 | S57: 0 | T57: 0 | U57: 0 | V57: 0 | W57: 0 | X57: 0 | Y57: 0 | Z57: 0 | AA57: 0 | AB57: 0 | AC57: 0 | AE57: Pieza
A58: 2468-ENEINFGC | B58: CAMPAÑA GCBA | INFRAESTRUCTURA | Cierre estación Piedras - Línea A | 12/1 | C58: 46031 | D58: 46045 | E58: Movilidad | F58: Infraestructura | G58: Finalizada | H58: 2008143 | I58: 0 | J58: 2313 | K58: 138774 | L58: 1.9878291 | M58: 14.4706 | N58: 69307 | O58: 68518 | P58: 27095 | Q58: 193 | R58: 0 | S58: 0 | T58: 0 | U58: 0 | V58: 0 | W58: 0 | X58: 0 | Y58: 0 | Z58: 0 | AA58: 0 | AB58: 0 | AC58: 0 | AD58: https://www.facebook.com/GCBA/posts/pfbid034yhPZN5yb3JKe4gVWvnfg3JxEqjRYwvE5KVfa8FhtU9xnt4fvGGv6PfcJxxWU5qNl | AE58: Pieza
A59: 2469-ENEPCCVC | B59: Reunion de Cocreación Parque Ferroviario Palermo | C59: 46049 | D59: 46050 | E59: Cercanía | F59: Cercanía y PC | G59: Finalizada | H59: 0 | I59: 0 | J59: 0 | K59: 0 | L59: 0 | M59: 0 | N59: 84765 | O59: 83136 | P59: 30285 | Q59: 289 | R59: 0 | S59: 0 | T59: 0 | U59: 0 | V59: 0 | W59: 0 | X59: 0 | Y59: 0 | Z59: 0 | AA59: 0 | AB59: 0 | AC59: 0 | AE59: Pieza
A60: 2470-ENEINFGC | B60: CAMPAÑA GCBA | INFRAESTRUCTURA | Corte AU Illia | C60: 46031 | D60: 46045 | E60: Movilidad | F60: Infraestructura | G60: Finalizada | H60: 270415 | I60: 0 | J60: 11 | K60: 270165 | L60: 1.0009254 | M60: 1.0009254 | N60: 133380 | O60: 131124 | P60: 51525 | Q60: 206 | R60: 0 | S60: 0 | T60: 0 | U60: 0 | V60: 0 | W60: 0 | X60: 0 | Y60: 0 | Z60: 0 | AA60: 0 | AB60: 0 | AC60: 0 | AD60: https://fb.me/adspreview/facebook/27utMxPibDIBULh | AE60: Pieza
A61: 2471-ENEINFGC | B61: CAMPAÑA GCBA | INFRAESTRUCTURA | PBN Irigoyen: durante de obra | C61: 46035 | D61: 46049 | E61: Movilidad | F61: Infraestructura | G61: Finalizada | H61: 5445044 | I61: 1315669 | J61: 12536 | K61: 24740 | L61: 1.1219483 | M61: 220.0907 | N61: 26442 | O61: 26188 | P61: 12713 | Q61: 753 | R61: 0 | S61: 0 | T61: 0 | U61: 0 | V61: 0 | W61: 0 | X61: 0 | Y61: 0 | Z61: 0 | AA61: 0 | AB61: 0 | AC61: 0 | AD61: https://www.facebook.com/GCBA/posts/pfbid02skUdtrbsimuTryUG4RHgFZofPSnLrmz2LKHSqBZbBiyVryTXEaMk43DgH54kd2xbl | AE61: Pieza
A62: 2472-ENEINFGC | B62: CAMPAÑA GCBA | Infraestructura | Cortes y desvíos en Palermo por trabajos en vías | C62: 46035 | D62: 46036 | E62: Movilidad | F62: Infraestructura | G62: Finalizada | H62: 428813 | I62: 0 | J62: 704 | K62: 427850 | L62: 1.0022508 | M62: 1.0022508 | N62: 61921 | O62: 61010 | P62: 27996 | Q62: 209 | R62: 0 | S62: 0 | T62: 0 | U62: 0 | V62: 0 | W62: 0 | X62: 0 | Y62: 0 | Z62: 0 | AA62: 0 | AB62: 0 | AC62: 0 | AD62: https://fb.me/adspreview/facebook/xMT36MnFuXZIDzt | AE62: Pieza
A63: 2474-ENEINFGC | B63: Campaña GCBA I Infraestructura I Nuevo ramal línea 42 | C63: 46041 | D63: 46055 | E63: Movilidad | F63: Infraestructura | G63: Finalizada | H63: 3771995 | I63: 0 | J63: 17133 | K63: 1236622 | L63: 0.48297297 | M63: 3.0502409 | N63: 99866 | O63: 97981 | P63: 38813 | Q63: 4158 | R63: 0 | S63: 0 | T63: 0 | U63: 0 | V63: 0 | W63: 0 | X63: 0 | Y63: 0 | Z63: 0 | AA63: 0 | AB63: 0 | AC63: 0 | AD63: https://www.facebook.com/GCBA/posts/pfbid0337UG4zRXFbMrDgWhEvo65XfwWurZKf1GK8RZQ5Pka9jErhk36TCLtEoR98b6H6GGl | AE63: Pieza
A64: 2475-ENESEGAG | B64: RECORRIDA POR SERVICIO PENITENCIARIO de Marcos Paz | C64: 46038 | D64: 46055 | E64: M2 | F64: Seguridad | G64: Finalizada | H64: 4108318 | I64: 362022 | J64: 22820 | K64: 324234 | L64: 2.4565376 | M64: 12.670843 | N64: 79361 | O64: 78087 | P64: 22745 | Q64: 87 | R64: 0 | S64: 0 | T64: 0 | U64: 0 | V64: 0 | W64: 0 | X64: 0 | Y64: 0 | Z64: 0 | AA64: 0 | AB64: 0 | AC64: 0 | AD64: https://www.facebook.com/reel/25959631640339458 | AE64: Pieza
A65: 2476-ENEFESGC | B65: Verano en la Ciudad | Corrientes 24h | C65: 46043 | D65: 46081 | E65: Ciudad Atractiva | F65: Festivales y Eventos | G65: Finalizada | H65: 19987991 | I65: 4636267 | J65: 26588 | K65: 467329 | L65: 6.5961475 | M65: 42.770705 | N65: 131580 | O65: 130254 | P65: 67844 | Q65: 3426 | R65: 0 | S65: 0 | T65: 0 | U65: 0 | V65: 0 | W65: 0 | X65: 0 | Y65: 0 | Z65: 0 | AA65: 0 | AB65: 0 | AC65: 0 | AD65: https://www.facebook.com/reel/1376298900359413 | AE65: Pieza
A66: 2477-ENEPCCVC | B66: Refuncionalización Calle Necochea y entorno | C66: 46041 | D66: 46041 | E66: Cercanía | F66: Cercanía y PC | G66: Finalizada | H66: 0 | I66: 0 | J66: 0 | K66: 0 | L66: 0 | M66: 0 | N66: 13427 | O66: 13123 | P66: 2286 | Q66: 83 | R66: 0 | S66: 0 | T66: 0 | U66: 0 | V66: 0 | W66: 0 | X66: 0 | Y66: 0 | Z66: 0 | AA66: 0 | AB66: 0 | AC66: 0 | AE66: Pieza
A67: 2478-ENEINNGC | B67: Lanzamiento BAX | C67: 46205 | D67: 46265 | E67: Reforma del Estado | F67: Innovación | G67: Activa | H67: 21389768 | I67: 5608558 | J67: 290709 | K67: 1151860 | L67: 3.694521 | M67: 18.569764 | N67: 561058 | O67: 553314 | P67: 168616 | Q67: 10926 | R67: 0 | S67: 0 | T67: 0 | U67: 0 | V67: 0 | W67: 0 | X67: 0 | Y67: 0 | Z67: 0 | AA67: 0 | AB67: 0 | AC67: 0 | AE67: Pieza
A68: 2480-ENEINFGC | B68: Campaña GCBA | Infraestructura: Obras en La Boca: calle Necochea | C68: 46083 | D68: 46112 | E68: M2 | F68: Infraestructura | G68: Finalizada | H68: 381747 | I68: 0 | J68: 6705 | K68: 78939 | L68: 1.8810221 | M68: 4.8359746 | N68: 10370 | O68: 10174 | P68: 2757 | Q68: 178 | R68: 0 | S68: 0 | T68: 0 | U68: 0 | V68: 0 | W68: 0 | X68: 0 | Y68: 0 | Z68: 0 | AA68: 0 | AB68: 0 | AC68: 0 | AE68: Pieza
A69: 2481-ENETURGC | B69: Informe mensual Observatorio | Diciembre 2025 | Viernes 16/01 | C69: 46037 | D69: 46037 | E69: Otros | F69: Turismo | G69: Finalizada | H69: 0 | I69: 0 | J69: 0 | K69: 0 | L69: 0 | M69: 0 | N69: 311 | O69: 305 | P69: 146 | Q69: 17 | R69: 0 | S69: 0 | T69: 0 | U69: 0 | V69: 0 | W69: 0 | X69: 0 | Y69: 0 | Z69: 0 | AA69: 0 | AB69: 0 | AC69: 0 | AE69: Pieza
A70: 2482-ENEINFGC | B70: VTV - Recordatorio de turno 2026 | C70: 46042 | D70: 46205 | E70: M2 | F70: Infraestructura | G70: Finalizada | H70: 0 | I70: 0 | J70: 0 | K70: 0 | L70: 0 | M70: 0 | N70: 236790 | O70: 236474 | P70: 96019 | Q70: 18061 | R70: 0 | S70: 0 | T70: 0 | U70: 0 | V70: 0 | W70: 0 | X70: 0 | Y70: 0 | Z70: 0 | AA70: 0 | AB70: 0 | AC70: 0 | AE70: Pieza
A71: 2483-ENESEGGC | B71: Campaña GCBA I Seguridad | Desalojo Constitución | C71: 46038 | D71: 46056 | E71: M2 | F71: Seguridad | G71: Finalizada | H71: 1143474 | I71: 145591 | J71: 2412 | K71: 355943 | L71: 2.8286889 | M71: 3.21252 | N71: 179393 | O71: 176101 | P71: 42189 | Q71: 823 | R71: 0 | S71: 0 | T71: 0 | U71: 0 | V71: 0 | W71: 0 | X71: 0 | Y71: 0 | Z71: 0 | AA71: 0 | AB71: 0 | AC71: 0 | AD71: https://www.facebook.com/reel/1332009022300877 | AE71: Pieza
A72: 2486-ENEDHHGC | B72: MDHYH | Programa Adolescencia | C72: 46049 | D72: 46049 | E72: Cuidado | F72: Desarrollo Humano y Hábitat | G72: Finalizada | H72: 0 | I72: 0 | J72: 0 | K72: 0 | L72: 0 | M72: 0 | N72: 82441 | O72: 80581 | P72: 22327 | Q72: 5566 | R72: 0 | S72: 0 | T72: 0 | U72: 0 | V72: 0 | W72: 0 | X72: 0 | Y72: 0 | Z72: 0 | AA72: 0 | AB72: 0 | AC72: 0 | AE72: Pieza
A73: 2487-ENEVINGC | B73: CAMPAÑA GCBA | VINCULO CIUDADANO | Mas servicios en tu barrio 2026: Parque Chacabuco 02/02 | C73: 46051 | D73: 46051 | E73: M2 | F73: Vínculo Ciudadano | G73: Finalizada | H73: 0 | I73: 0 | J73: 0 | K73: 0 | L73: 0 | M73: 0 | N73: 15253 | O73: 14992 | P73: 5465 | Q73: 252 | R73: 0 | S73: 0 | T73: 0 | U73: 0 | V73: 0 | W73: 0 | X73: 0 | Y73: 0 | Z73: 0 | AA73: 0 | AB73: 0 | AC73: 0 | AE73: Pieza
A74: 2488-ENEVINGC | B74: CAMPAÑA GCBA | VINCULO CIUDADANO | Mas servicios en tu barrio 2026: Caballito 04/02 | C74: 46052 | D74: 46052 | E74: M2 | F74: Vínculo Ciudadano | G74: Finalizada | H74: 0 | I74: 0 | J74: 0 | K74: 0 | L74: 0 | M74: 0 | N74: 30581 | O74: 30053 | P74: 10808 | Q74: 399 | R74: 0 | S74: 0 | T74: 0 | U74: 0 | V74: 0 | W74: 0 | X74: 0 | Y74: 0 | Z74: 0 | AA74: 0 | AB74: 0 | AC74: 0 | AE74: Pieza
A75: 2489-ENEVINGC | B75: CAMPAÑA GCBA | VINCULO CIUDADANO | Mas servicios en tu barrio 2026: Villa Riachuelo 06/02 | C75: 46055 | D75: 46055 | E75: M2 | F75: Vínculo Ciudadano | G75: Finalizada | H75: 0 | I75: 0 | J75: 0 | K75: 0 | L75: 0 | M75: 0 | N75: 10310 | O75: 10090 | P75: 2994 | Q75: 170 | R75: 0 | S75: 0 | T75: 0 | U75: 0 | V75: 0 | W75: 0 | X75: 0 | Y75: 0 | Z75: 0 | AA75: 0 | AB75: 0 | AC75: 0 | AE75: Pieza
A76: 2490-ENEVINGC | B76: CAMPAÑA GCBA | VINCULO CIUDADANO | Mas servicios en tu barrio 2026: Villa Devoto 09/02 | C76: 46062 | D76: 46062 | E76: M2 | F76: Vínculo Ciudadano | G76: Finalizada | H76: 0 | I76: 0 | J76: 0 | K76: 0 | L76: 0 | M76: 0 | N76: 10019 | O76: 9829 | P76: 4405 | Q76: 210 | R76: 0 | S76: 0 | T76: 0 | U76: 0 | V76: 0 | W76: 0 | X76: 0 | Y76: 0 | Z76: 0 | AA76: 0 | AB76: 0 | AC76: 0 | AE76: Pieza
A77: 2491-ENEVINGC | B77: CAMPAÑA GCBA | VINCULO CIUDADANO | Mas servicios en tu barrio 2026: Mataderos 11/02 | C77: 46062 | D77: 46062 | E77: M2 | F77: Vínculo Ciudadano | G77: Finalizada | H77: 0 | I77: 0 | J77: 0 | K77: 0 | L77: 0 | M77: 0 | N77: 9931 | O77: 9762 | P77: 3403 | Q77: 223 | R77: 0 | S77: 0 | T77: 0 | U77: 0 | V77: 0 | W77: 0 | X77: 0 | Y77: 0 | Z77: 0 | AA77: 0 | AB77: 0 | AC77: 0 | AE77: Pieza
A78: 2492-ENEVINGC | B78: CAMPAÑA GCBA | VINCULO CIUDADANO | Mas servicios en tu barrio 2026: Villa Crespo 13/02 | C78: 46063 | D78: 46063 | E78: M2 | F78: Vínculo Ciudadano | G78: Finalizada | H78: 0 | I78: 0 | J78: 0 | K78: 0 | L78: 0 | M78: 0 | N78: 19496 | O78: 19166 | P78: 6746 | Q78: 239 | R78: 0 | S78: 0 | T78: 0 | U78: 0 | V78: 0 | W78: 0 | X78: 0 | Y78: 0 | Z78: 0 | AA78: 0 | AB78: 0 | AC78: 0 | AE78: Pieza
A79: 2493-ENEVINGC | B79: CAMPAÑA GCBA | VINCULO CIUDADANO | Mas servicios en tu barrio 2026: Villa Luro 18/02 | C79: 46067 | D79: 46067 | E79: M2 | F79: Vínculo Ciudadano | G79: Finalizada | H79: 0 | I79: 0 | J79: 0 | K79: 0 | L79: 0 | M79: 0 | N79: 11830 | O79: 11398 | P79: 4126 | Q79: 15 | R79: 0 | S79: 0 | T79: 0 | U79: 0 | V79: 0 | W79: 0 | X79: 0 | Y79: 0 | Z79: 0 | AA79: 0 | AB79: 0 | AC79: 0 | AE79: Pieza
A80: 2496-ENEVINGC | B80: CAMPAÑA GCBA | VINCULO CIUDADANO | Mas servicios en tu barrio 2026: Recoleta 25/02 | C80: 46071 | D80: 46265 | E80: M2 | F80: Vínculo Ciudadano | G80: Activa | H80: 7822741 | I80: 0 | J80: 27788 | K80: 1977609 | L80: 3.955656 | M80: 3.955656 | N80: 0 | O80: 0 | P80: 0 | Q80: 0 | R80: 0 | S80: 0 | T80: 0 | U80: 0 | V80: 0 | W80: 0 | X80: 0 | Y80: 0 | Z80: 0 | AA80: 0 | AB80: 0 | AC80: 0 | AD80: https://www.facebook.com/GCBA/posts/pfbid02BLwc5PnG5EYzbVeS3qNZ6Nb5in3PifakagmTh6BFX3zNQZ1rLsJ3FsQx9JDG2gFdl
A81: 2497-ENEVINGC | B81: CAMPAÑA GCBA | VINCULO CIUDADANO | Mas servicios en tu barrio 2026: Palermo 27/02 | C81: 46077 | D81: 46077 | E81: M2 | F81: Vínculo Ciudadano | G81: Finalizada | H81: 0 | I81: 0 | J81: 0 | K81: 0 | L81: 0 | M81: 0 | N81: 33785 | O81: 33409 | P81: 13633 | Q81: 347 | R81: 0 | S81: 0 | T81: 0 | U81: 0 | V81: 0 | W81: 0 | X81: 0 | Y81: 0 | Z81: 0 | AA81: 0 | AB81: 0 | AC81: 0 | AE81: Pieza
A82: 2498-ENEEPHGC | B82: CAMPAÑA GCBA | CONVIVENCIA | Genérica | C82: 46063 | D82: 46112 | E82: M2 | F82: Espacio Público e Higiene Urbana | G82: Finalizada | H82: 11971276 | I82: 4057311 | J82: 70881 | K82: 25626 | L82: 169.10965 | M82: 467.15352 | N82: 103961 | O82: 103286 | P82: 52535 | Q82: 360 | R82: 0 | S82: 0 | T82: 0 | U82: 0 | V82: 0 | W82: 0 | X82: 0 | Y82: 0 | Z82: 0 | AA82: 0 | AB82: 0 | AC82: 0 | AE82: Pieza
A83: 2499-ENEEPHGC | B83: CAMPAÑA GCBA | CONVIVENCIA | Cuidado de perros | C83: 46063 | D83: 46112 | E83: M2 | F83: Espacio Público e Higiene Urbana | G83: Finalizada | H83: 6958541 | I83: 0 | J83: 54847 | K83: 421569 | L83: 6.5486148 | M83: 16.506292 | N83: 87630 | O83: 86596 | P83: 33826 | Q83: 192 | R83: 0 | S83: 0 | T83: 0 | U83: 0 | V83: 0 | W83: 0 | X83: 0 | Y83: 0 | Z83: 0 | AA83: 0 | AB83: 0 | AC83: 0 | AE83: Pieza
A84: 2500-ENEEPHGC | B84: CAMPAÑA GCBA | CONVIVENCIA | Doble Fila | C84: 46064 | D84: 46112 | E84: M2 | F84: Espacio Público e Higiene Urbana | G84: Finalizada | H84: 9961877 | I84: 0 | J84: 64850 | K84: 317029 | L84: 17.055843 | M84: 31.422605 | N84: 181226 | O84: 180694 | P84: 113730 | Q84: 1220 | R84: 0 | S84: 0 | T84: 0 | U84: 0 | V84: 0 | W84: 0 | X84: 0 | Y84: 0 | Z84: 0 | AA84: 0 | AB84: 0 | AC84: 0 | AE84: Pieza
A85: 2501-ENEJDGAG | B85: RDV JM Flores 30/01 | C85: 46045 | D85: 46067 | E85: Cercanía | F85: Jefatura de Gobierno | G85: Finalizada | H85: 2825033 | I85: 1642319 | J85: 6937 | K85: 75466 | L85: 3.4477778 | M85: 37.434514 | N85: 118035 | O85: 115928 | P85: 20333 | Q85: 873 | R85: 9405 | S85: 7521 | T85: 1735 | U85: 1312 | V85: 32361 | W85: 32361 | X85: 25759 | Y85: 10328 | Z85: 108 | AA85: 0 | AB85: 0 | AC85: 0 | AD85: https://www.facebook.com/reel/1297793642108690 | AE85: Pieza
A86: 2502-ENEJDGAG | B86: CAFE JM Versalles 29/01 | C86: 46048 | D86: 46073 | E86: Cercanía | F86: Jefatura de Gobierno | G86: Finalizada | H86: 124669 | I86: 3423 | J86: 1975 | K86: 17945 | L86: 2.4849262 | M86: 6.9472834 | N86: 6610 | O86: 6518 | P86: 1169 | Q86: 169 | R86: 0 | S86: 0 | T86: 0 | U86: 0 | V86: 0 | W86: 0 | X86: 0 | Y86: 0 | Z86: 0 | AA86: 0 | AB86: 0 | AC86: 0 | AE86: Pieza
A87: 2503-ENEPCCVC | B87: Reunión de Co-creación - Eventos Masivos Huracán | C87: 46055 | D87: 46055 | E87: Cercanía | F87: Cercanía y PC | G87: Finalizada | H87: 0 | I87: 0 | J87: 0 | K87: 0 | L87: 0 | M87: 0 | N87: 31878 | O87: 31183 | P87: 5171 | Q87: 112 | R87: 0 | S87: 0 | T87: 0 | U87: 0 | V87: 0 | W87: 0 | X87: 0 | Y87: 0 | Z87: 0 | AA87: 0 | AB87: 0 | AC87: 0 | AE87: Pieza
A88: 2504-ENEFESGC | B88: La Ciudad Más Linda del Mundo | Etapa 2 | C88: 46087 | D88: 46112 | E88: Ciudad Atractiva | F88: Festivales y Eventos | G88: Finalizada | H88: 26387070 | I88: 1127725 | J88: 16601 | K88: 672600 | L88: 18.517806 | M88: 39.231445 | N88: 0 | O88: 0 | P88: 0 | Q88: 0 | R88: 0 | S88: 0 | T88: 0 | U88: 0 | V88: 0 | W88: 0 | X88: 0 | Y88: 0 | Z88: 0 | AA88: 0 | AB88: 0 | AC88: 0
A89: 2505-ENEPCCVC | B89: Verano 2026 - Misión Bomberos: Un Día en la Estación FEBRERO | C89: 46051 | D89: 46051 | E89: Cercanía | F89: Cercanía y PC | G89: Finalizada | H89: 0 | I89: 0 | J89: 0 | K89: 0 | L89: 0 | M89: 0 | N89: 57099 | O89: 56035 | P89: 16960 | Q89: 393 | R89: 0 | S89: 0 | T89: 0 | U89: 0 | V89: 0 | W89: 0 | X89: 0 | Y89: 0 | Z89: 0 | AA89: 0 | AB89: 0 | AC89: 0 | AE89: Pieza
A90: 2506-ENEPCCVC | B90: Verano 2026 - La Gran Aventura del Reciclaje | Febrero | C90: 46050 | D90: 46050 | E90: Cercanía | F90: Cercanía y PC | G90: Finalizada | H90: 0 | I90: 0 | J90: 0 | K90: 0 | L90: 0 | M90: 0 | N90: 34666 | O90: 33494 | P90: 5167 | Q90: 97 | R90: 0 | S90: 0 | T90: 0 | U90: 0 | V90: 0 | W90: 0 | X90: 0 | Y90: 0 | Z90: 0 | AA90: 0 | AB90: 0 | AC90: 0 | AE90: Pieza
A91: 2507-ENEPCCVC | B91: Verano 2026 - Expedición Botánica - 2 | C91: 46051 | D91: 46051 | E91: Cercanía | F91: Cercanía y PC | G91: Finalizada | H91: 0 | I91: 0 | J91: 0 | K91: 0 | L91: 0 | M91: 0 | N91: 49880 | O91: 48946 | P91: 15010 | Q91: 433 | R91: 0 | S91: 0 | T91: 0 | U91: 0 | V91: 0 | W91: 0 | X91: 0 | Y91: 0 | Z91: 0 | AA91: 0 | AB91: 0 | AC91: 0 | AE91: Pieza
A92: 2508-ENEINFGC | B92: Infraestructura I AU Dellepiane : durante de obra | C92: 46049 | D92: 46063 | E92: Movilidad | F92: Infraestructura | G92: Finalizada | H92: 2133201 | I92: 0 | J92: 11726 | K92: 810555 | L92: 0.56835378 | M92: 2.6317782 | N92: 150038 | O92: 146815 | P92: 34417 | Q92: 972 | R92: 0 | S92: 0 | T92: 0 | U92: 0 | V92: 0 | W92: 0 | X92: 0 | Y92: 0 | Z92: 0 | AA92: 0 | AB92: 0 | AC92: 0 | AE92: Pieza
A93: 2510-ENEINFGC | B93: Infraestructura I Cambio de sentido calle Reconquista | C93: 46048 | D93: 46062 | E93: Movilidad | F93: Infraestructura | G93: Finalizada | H93: 194515 | I93: 0 | J93: 13 | K93: 137491 | L93: 1.4147471 | M93: 1.4147471 | N93: 22322 | O93: 21947 | P93: 8823 | Q93: 203 | R93: 0 | S93: 0 | T93: 0 | U93: 0 | V93: 0 | W93: 0 | X93: 0 | Y93: 0 | Z93: 0 | AA93: 0 | AB93: 0 | AC93: 0 | AE93: Pieza
A94: 2511-ENEINFGC | B94: Infraestructura I Cortes por obras TramBus ENERO | C94: 46051 | D94: 46054 | E94: Movilidad | F94: Infraestructura | G94: Finalizada | H94: 1038637 | I94: 0 | J94: 20 | K94: 635853 | L94: 1.6334546 | M94: 1.6334546 | N94: 218884 | O94: 215091 | P94: 68978 | Q94: 2643 | R94: 0 | S94: 0 | T94: 0 | U94: 0 | V94: 0 | W94: 0 | X94: 0 | Y94: 0 | Z94: 0 | AA94: 38263 | AB94: 35939 | AC94: 182 | AE94: Pieza
A95: 2512-ENESALGC | B95: Envío Deploy GDE 27.01.2026 | C95: 46049 | D95: 46049 | E95: Cuidado | F95: Salud | G95: Finalizada | H95: 0 | I95: 0 | J95: 0 | K95: 0 | L95: 0 | M95: 0 | N95: 7062 | O95: 7019 | P95: 2964 | Q95: 229 | R95: 0 | S95: 0 | T95: 0 | U95: 0 | V95: 0 | W95: 0 | X95: 0 | Y95: 0 | Z95: 0 | AA95: 0 | AB95: 0 | AC95: 0 | AE95: Pieza
A96: 2513-ENEPCCVC | B96: Priorización de Nombre Paso Bajo Nivel Bosch | C96: 46057 | D96: 46057 | E96: Cercanía | F96: Cercanía y PC | G96: Finalizada | H96: 0 | I96: 0 | J96: 0 | K96: 0 | L96: 0 | M96: 0 | N96: 26962 | O96: 26396 | P96: 5693 | Q96: 547 | R96: 0 | S96: 0 | T96: 0 | U96: 0 | V96: 0 | W96: 0 | X96: 0 | Y96: 0 | Z96: 0 | AA96: 0 | AB96: 0 | AC96: 0 | AE96: Pieza
A97: 2514-ENEINFGC | B97: Infraestructura I Nuevo Acceso al Paseo del Bajo | C97: 46150 | D97: 46150 | E97: Movilidad | F97: Infraestructura | G97: Finalizada | H97: 0 | I97: 0 | J97: 0 | K97: 0 | L97: 0 | M97: 0 | N97: 155026 | O97: 153885 | P97: 67635 | Q97: 2686 | R97: 0 | S97: 0 | T97: 0 | U97: 0 | V97: 0 | W97: 0 | X97: 0 | Y97: 0 | Z97: 0 | AA97: 0 | AB97: 0 | AC97: 0 | AE97: Pieza
A98: 2515-ENEINFGJ | B98: Infraestructura I Anillo Pampa: Inicio de obra + Cortes | C98: 46049 | D98: 46167 | E98: Movilidad | F98: Infraestructura | G98: Finalizada | H98: 10369425 | I98: 3848246 | J98: 31546 | K98: 316958 | L98: 2.6814625 | M98: 32.715454 | N98: 399242 | O98: 394575 | P98: 134230 | Q98: 5084 | R98: 0 | S98: 0 | T98: 0 | U98: 0 | V98: 0 | W98: 0 | X98: 0 | Y98: 0 | Z98: 0 | AA98: 0 | AB98: 0 | AC98: 0 | AD98: https://www.facebook.com/reel/26974859272149704 | AE98: Pieza
A99: 2516-ENESALCG | B99: Carrusel Refugios climáticos | C99: 46049 | D99: 46066 | E99: Cuidado | F99: Salud | G99: Finalizada | H99: 1502590 | I99: 0 | J99: 2460 | K99: 1034589 | L99: 1.4523545 | M99: 1.4523545 | N99: 0 | O99: 0 | P99: 0 | Q99: 0 | R99: 0 | S99: 0 | T99: 0 | U99: 0 | V99: 0 | W99: 0 | X99: 0 | Y99: 0 | Z99: 0 | AA99: 0 | AB99: 0 | AC99: 0
A100: 2517-ENEINFGC | B100: Infraestructura I PAN: inicio de obra | C100: 46052 | D100: 46072 | E100: Movilidad | F100: Infraestructura | G100: Finalizada | H100: 0 | I100: 0 | J100: 0 | K100: 0 | L100: 0 | M100: 0 | N100: 75358 | O100: 74094 | P100: 27113 | Q100: 1359 | R100: 0 | S100: 0 | T100: 0 | U100: 0 | V100: 0 | W100: 0 | X100: 0 | Y100: 0 | Z100: 0 | AA100: 65784 | AB100: 62454 | AC100: 987 | AE100: Pieza
...

Sheet Cuentas
A1: id_cuentas | B1: nombre_campaña | C1: fecha_inicio | D1: fecha_fin | E1: eje | F1: area | G1: estado | H1: estado_cuentas
A2: 1871-AGOEDUGC | B2: Campaña GCBA | Educación | TUMO | C2: 45959 | D2: 46203 | E2: Cuidado | F2: Educación | G2: Finalizada | H2: Activa
A3: 1895-SEPEPHGC | B3: PIEZAS M2 | MEPHU | REPAVIMENTACIÓN | C3: 46052 | D3: 46178 | E3: M2 | F3: Espacio Público e Higiene Urbana | G3: Finalizada | H3: Finalizada
A4: 1896-SEPEPHGC | B4: PIEZAS M2 | MEPHU | LIMPIEZA INTENSIVA | C4: 46031 | D4: 46136 | E4: M2 | F4: Espacio Público e Higiene Urbana | G4: Finalizada | H4: Pausada
A5: 1933-SEPINFGC | B5: CAMPAÑA GCBA | INFRAESTRUCTURA | Campaña 360° Movilidad 2025 | C5: 45936 | D5: 46081 | E5: Movilidad | F5: Infraestructura | G5: Finalizada | H5: Finalizada
A6: 1942-SEPEPHGC | B6: DGPLES | MEPHU | REPARACIÓN DE VEREDAS | C6: 46031 | D6: 46223 | E6: M2 | F6: Espacio Público e Higiene Urbana | G6: Finalizada | H6: Activa
A7: 1943-SEPEPHGC | B7: DGPLES | MEPHU | READOQUINADO | C7: 46031 | D7: 46223 | E7: M2 | F7: Espacio Público e Higiene Urbana | G7: Finalizada | H7: Activa
A8: 1946-SEPEPHGC | B8: CAMPAÑA GCBA | MEPHU | PLUVIALES | C8: 46038 | D8: 46223 | E8: M2 | F8: Espacio Público e Higiene Urbana | G8: Finalizada | H8: Activa
A9: 1964-SEPEPHGC | B9: MEPHU RECAMBIO TECNOLÓGICO M2 | C9: 46071 | D9: 46220 | E9: M2 | F9: Espacio Público e Higiene Urbana | G9: Finalizada | H9: Activa
A10: 2033-SEPEPHGC | B10: M2 PODA | C10: 46035 | D10: 46216 | E10: M2 | F10: Espacio Público e Higiene Urbana | G10: Finalizada | H10: Pausada
A11: 2100-OCTSALGC | B11: Cesac 12 - Más consultorios | C11: 46013 | D11: 46027 | E11: Cuidado | F11: Salud | G11: Finalizada | H11: Finalizada
A12: 2108-OCTEDUGC | B12: Inscripción 2025 a Profesorados de la Ciudad | C12: 45952 | D12: 46073 | E12: Cuidado | F12: Educación | G12: Finalizada | H12: Finalizada
A13: 2109-OCTEPHGC | B13: LIMPIEZA DE FACHADAS | M2 | C13: 46028 | D13: 46099 | E13: M2 | F13: Espacio Público e Higiene Urbana | G13: Finalizada | H13: Finalizada
... A32: 2426-DICSALGC | B32: Deploy HIS Ambulatorio | C32: 46030 | D32: 46030 | E32: Cuidado | F32: Salud | G32: Finalizada | H32: Finalizada
A33: 2428-DICPCCGC | B33: Voluntariado: Puesta en valor Asociación Juvenil Araucana | E33: Cercanía | F33: Cercanía y PC | G33: Pendiente | H33: Finalizada
A34: 2429-DICPCCVC | B34: DGPCyC | Verano 2026 - Todo tiene vida: Museo Moderno | E34: Ciudad Atractiva | F34: Cercanía y PC | G34: Pendiente | H34: Finalizada
A35: 2430-DICPCCVC | B35: DGPCyC | Verano 2026 - Misión Bomberos: Un día en la estación | C35: 46029 | D35: 46029 | E35: Cercanía | F35: Cercanía y PC | G35: Finalizada | H35: Finalizada
A36: 2431-DICPCCVC | B36: DGPCyC | Verano 2026 - PASEO NÁUTICO POR EL RIACHUELO | E36: Cercanía | F36: Cercanía y PC | G36: Pendiente | H36: Finalizada
A37: 2433-DICFESGC | B37: Verano en la Ciudad | AftersBA | C37: 46035 | D37: 46071 | E37: Ciudad Atractiva | F37: Festivales y Eventos | G37: Finalizada | H37: Finalizada
A38: 2434-DICFESGC | B38: Verano en la Ciudad | Billboard Summer | C38: 46031 | D38: 46039 | E38: Ciudad Atractiva | F38: Festivales y Eventos | G38: Finalizada | H38: Finalizada
A39: 2435-DICFESGC | B39: Verano en la Ciudad | Atardeceres en los parques | C39: 46041 | D39: 46062 | E39: Ciudad Atractiva | F39: Festivales y Eventos | G39: Finalizada | H39: Finalizada
A40: 2437-DICFESGC | B40: Verano en la Ciudad | Verano en las plazas | C40: 46038 | D40: 46073 | E40: Ciudad Atractiva | F40: Festivales y Eventos | G40: Finalizada | H40: Finalizada
A41: 2439-DICINFGC | B41: Infraestructura I Bus Eléctricos: extensión recorrido | C41: 46028 | D41: 46042 | E41: Movilidad | F41: Infraestructura | G41: Finalizada | H41: Finalizada
A42: 2441-DICINFGC | B42: Infraestructura I Obras M2: Trambus ENERO | C42: 46035 | D42: 46053 | E42: Movilidad | F42: Infraestructura | G42: Finalizada | H42: Finalizada
A43: 2443-DICNEWAN | B43: Acciones de la Ciudad ante el calor extremo | C43: 46027 | D43: 46035 | E43: Cuidado | F43: Anuncios y Newsletter | G43: Finalizada | H43: Finalizada
A44: 2444-DICINFGC | B44: Infraestructura I Cortes en AU Dellepiane por obras | C44: 46021 | D44: 46034 | E44: Movilidad | F44: Infraestructura | G44: Finalizada | H44: Finalizada
A45: 2445-DICPCCVC | B45: Verano 2026 - Expedicion botanica | C45: 46034 | D45: 46034 | E45: Cercanía | F45: Cercanía y PC | G45: Finalizada | H45: Finalizada
A46: 2447-DICPCCVC | B46: Verano 2026 - La Gran Aventura del Reciclaje | Enero | C46: 46031 | D46: 46031 | E46: Cercanía | F46: Cercanía y PC | G46: Finalizada | H46: Finalizada
A47: 2450-ENEJDGAG | B47: RDV JM - Boedo 9/1 | C47: 46024 | D47: 46052 | E47: Cercanía | F47: Jefatura de Gobierno | G47: Finalizada | H47: Finalizada
A48: 2451-ENEPCCVC | B48: Participación Ciudadana - Verano en la Ciudad (Pauta RRSS) | C48: 46027 | D48: 46057 | E48: Cercanía | F48: Cercanía y PC | G48: Finalizada | H48: Finalizada
A49: 2452-ENEINFGC | B49: Métricas de cortes y desvíos por eventos masivos 2025 | E49: Movilidad | F49: Infraestructura | G49: Pendiente | H49: Finalizada
A50: 2453-ENEPCCVC | B50: Verano 2026 - CIFA para chicos | C50: 46043 | D50: 46049 | E50: Cercanía | F50: Cercanía y PC | G50: Finalizada | H50: Finalizada
A51: 2454-ENEPCCVC | B51: Verano 2026 - Aventura en el aire | C51: 46038 | D51: 46038 | E51: Cercanía | F51: Cercanía y PC | G51: Finalizada | H51: Finalizada
A52: 2456-ENEPCCVC | B52: Dejá tus rueditas | C52: 46035 | D52: 46035 | E52: Cercanía | F52: Cercanía y PC | G52: Finalizada | H52: Finalizada
A53: 2457-ENEPCCVC | B53: Verano 2026 - Exploradores del Ecoparque | C53: 46036 | D53: 46036 | E53: Cercanía | F53: Cercanía y PC | G53: Finalizada | H53: Finalizada
A54: 2458-ENESEGGC | B54: Campaña GCBA I Seguridad I Desalojo edificio San Telmo | C54: 46029 | D54: 46044 | E54: M2 | F54: Seguridad | G54: Finalizada | H54: Finalizada
A55: 2459-ENESEGGC | B55: Campaña GCBA I Seguridad I Desalojo predio Parque Avellaneda | C55: 46030 | D55: 46045 | E55: M2 | F55: Seguridad | G55: Finalizada | H55: Finalizada
A56: 2460-ENEFESGC | B56: Campaña verano en la ciudad | Verano en los anfiteatros | C56: 46057 | D56: 46080 | E56: Ciudad Atractiva | F56: Festivales y Eventos | G56: Finalizada | H56: Finalizada
A57: 2461-ENEEPHGC | B57: MEPHU - Informe M2 anual (sep a dic 2025) | E57: M2 | F57: Espacio Público e Higiene Urbana | G57: Pendiente | H57: Finalizada
A58: 2462-ENEVINGC | B58: GESTION COMUNAL - Informe M2 anual (sep a dic 2025) | E58: M2 | F58: Vínculo Ciudadano | G58: Pendiente | H58: Finalizada
A59: 2463-ENETURGC | B59: Elegí Argentina 2026 | Registro de Prestadores Turísticos | Viernes 9/1 | C59: 46031 | D59: 46031 | E59: Otros | F59: Turismo | G59: Finalizada | H59: Finalizada
A60: 2464-ENEINFGC | B60: CAMPAÑA GCBA | INFRAESTRUCTURA | PBN García Lorca: durante de obra | C60: 46036 | D60: 46056 | E60: Movilidad | F60: Infraestructura | G60: Finalizada | H60: Finalizada
A61: 2465-ENEJDGAG | B61: Cafe JM - Puerto Madero 16/1 | C61: 46031 | D61: 46053 | E61: Cercanía | F61: Jefatura de Gobierno | G61: Finalizada | H61: Finalizada
A62: 2466-ENEFESGC | B62: Verano en la Ciudad | Parque de la Ciudad | C62: 46041 | D62: 46066 | E62: Ciudad Atractiva | F62: Festivales y Eventos | G62: Finalizada | H62: Finalizada
A63: 2467-ENEFESGC | B63: Verano en la Ciudad | Verano Joven BA enero | C63: 46050 | D63: 46053 | E63: Ciudad Atractiva | F63: Festivales y Eventos | G63: Finalizada | H63: Finalizada
A64: 2468-ENEINFGC | B64: CAMPAÑA GCBA | INFRAESTRUCTURA | Cierre estación Piedras - Línea A | 12/1 | C64: 46031 | D64: 46045 | E64: Movilidad | F64: Infraestructura | G64: Finalizada | H64: Finalizada
A65: 2469-ENEPCCVC | B65: Reunion de Cocreación Parque Ferroviario Palermo | C65: 46049 | D65: 46050 | E65: Cercanía | F65: Cercanía y PC | G65: Finalizada | H65: Finalizada
A66: 2470-ENEINFGC | B66: CAMPAÑA GCBA | INFRAESTRUCTURA | Corte AU Illia | C66: 46031 | D66: 46045 | E66: Movilidad | F66: Infraestructura | G66: Finalizada | H66: Finalizada
A67: 2471-ENEINFGC | B67: CAMPAÑA GCBA | INFRAESTRUCTURA | PBN Irigoyen: durante de obra | C67: 46035 | D67: 46049 | E67: Movilidad | F67: Infraestructura | G67: Finalizada | H67: Finalizada
A68: 2472-ENEINFGC | B68: CAMPAÑA GCBA | Infraestructura | Cortes y desvíos en Palermo por trabajos en vías | C68: 46035 | D68: 46036 | E68: Movilidad | F68: Infraestructura | G68: Finalizada | H68: Finalizada
A69: 2473-ENECCRSGC | B69: CAMPAÑA GCBA | CUIDADO | VJ | Estaciones Saludables | E69: Cuidado | F69: Vicejefatura (Cultura Ciudadana y Responsabilidad Social) | G69: Pendiente | H69: Pausada
A70: 2474-ENEINFGC | B70: Campaña GCBA I Infraestructura I Nuevo ramal línea 42 | C70: 46041 | D70: 46055 | E70: Movilidad | F70: Infraestructura | G70: Finalizada | H70: Finalizada
A71: 2475-ENESEGAG | B71: RECORRIDA POR SERVICIO PENITENCIARIO de Marcos Paz | C71: 46038 | D71: 46055 | E71: M2 | F71: Seguridad | G71: Finalizada | H71: Finalizada
A72: 2476-ENEFESGC | B72: Verano en la Ciudad | Corrientes 24h | C72: 46043 | D72: 46081 | E72: Ciudad Atractiva | F72: Festivales y Eventos | G72: Finalizada | H72: Finalizada
A73: 2477-ENEPCCVC | B73: Refuncionalización Calle Necochea y entorno | C73: 46041 | D73: 46041 | E73: Cercanía | F73: Cercanía y PC | G73: Finalizada | H73: Finalizada
A74: 2478-ENEINNGC | B74: Lanzamiento BAX | C74: 46205 | D74: 46265 | E74: Reforma del Estado | F74: Innovación | G74: Activa | H74: Activa
A75: 2479-ENECCRSGC | B75: CAMPAÑA GCBA | CUIDADO | VJ | M2 Parque Saavedra | Estaciones Saludables | E75: M2 | F75: Vicejefatura (Cultura Ciudadana y Responsabilidad Social) | G75: Pendiente | H75: Pausada
A76: 2480-ENEINFGC | B76: Campaña GCBA | Infraestructura: Obras en La Boca: calle Necochea | C76: 46083 | D76: 46112 | E76: M2 | F76: Infraestructura | G76: Finalizada | H76: Finalizada
A77: 2481-ENETURGC | B77: Informe mensual Observatorio | Diciembre 2025 | Viernes 16/01 | C77: 46037 | D77: 46037 | E77: Otros | F77: Turismo | G77: Finalizada | H77: Finalizada
A78: 2482-ENEINFGC | B78: VTV - Recordatorio de turno 2026 | C78: 46042 | D78: 46205 | E78: M2 | F78: Infraestructura | G78: Finalizada | H78: Activa
A79: 2483-ENESEGGC | B79: Campaña GCBA I Seguridad | Desalojo Constitución | C79: 46038 | D79: 46056 | E79: M2 | F79: Seguridad | G79: Finalizada | H79: Finalizada
A80: 2486-ENEDHHGC | B80: MDHYH | Programa Adolescencia | C80: 46049 | D80: 46049 | E80: Cuidado | F80: Desarrollo Humano y Hábitat | G80: Finalizada | H80: Finalizada
A81: 2487-ENEVINGC | B81: CAMPAÑA GCBA | VINCULO CIUDADANO | Mas servicios en tu barrio 2026: Parque Chacabuco 02/02 | C81: 46051 | D81: 46051 | E81: M2 | F81: Vínculo Ciudadano | G81: Finalizada | H81: Finalizada
A82: 2488-ENEVINGC | B82: CAMPAÑA GCBA | VINCULO CIUDADANO | Mas servicios en tu barrio 2026: Caballito 04/02 | C82: 46052 | D82: 46052 | E82: M2 | F82: Vínculo Ciudadano | G82: Finalizada | H82: Finalizada
A83: 2489-ENEVINGC | B83: CAMPAÑA GCBA | VINCULO CIUDADANO | Mas servicios en tu barrio 2026: Villa Riachuelo 06/02 | C83: 46055 | D83: 46055 | E83: M2 | F83: Vínculo Ciudadano | G83: Finalizada | H83: Finalizada
A84: 2490-ENEVINGC | B84: CAMPAÑA GCBA | VINCULO CIUDADANO | Mas servicios en tu barrio 2026: Villa Devoto 09/02 | C84: 46062 | D84: 46062 | E84: M2 | F84: Vínculo Ciudadano | G84: Finalizada | H84: Finalizada
A85: 2491-ENEVINGC | B85: CAMPAÑA GCBA | VINCULO CIUDADANO | Mas servicios en tu barrio 2026: Mataderos 11/02 | C85: 46062 | D85: 46062 | E85: M2 | F85: Vínculo Ciudadano | G85: Finalizada | H85: Finalizada
A86: 2492-ENEVINGC | B86: CAMPAÑA GCBA | VINCULO CIUDADANO | Mas servicios en tu barrio 2026: Villa Crespo 13/02 | C86: 46063 | D86: 46063 | E86: M2 | F86: Vínculo Ciudadano | G86: Finalizada | H86: Finalizada
A87: 2493-ENEVINGC | B87: CAMPAÑA GCBA | VINCULO CIUDADANO | Mas servicios en tu barrio 2026: Villa Luro 18/02 | C87: 46067 | D87: 46067 | E87: M2 | F87: Vínculo Ciudadano | G87: Finalizada | H87: Finalizada
A88: 2494-ENEVINGC | B88: CAMPAÑA GCBA | VINCULO CIUDADANO | Mas servicios en tu barrio 2026: Parque Patricios 20/02 | E88: M2 | F88: Vínculo Ciudadano | G88: Pendiente | H88: Finalizada
A89: 2495-ENEVINGC | B89: CAMPAÑA GCBA | VINCULO CIUDADANO | Mas servicios en tu barrio 2026: Villa del Parque 23/02 | E89: M2 | F89: Vínculo Ciudadano | G89: Pendiente | H89: Finalizada
A90: 2496-ENEVINGC | B90: CAMPAÑA GCBA | VINCULO CIUDADANO | Mas servicios en tu barrio 2026: Recoleta 25/02 | C90: 46071 | D90: 46265 | E90: M2 | F90: Vínculo Ciudadano | G90: Activa | H90: Finalizada
A91: 2497-ENEVINGC | B91: CAMPAÑA GCBA | VINCULO CIUDADANO | Mas servicios en tu barrio 2026: Palermo 27/02 | C91: 46077 | D91: 46077 | E91: M2 | F91: Vínculo Ciudadano | G91: Finalizada | H91: Finalizada
A92: 2498-ENEEPHGC | B92: CAMPAÑA GCBA | CONVIVENCIA | Genérica | C92: 46063 | D92: 46112 | E92: M2 | F92: Espacio Público e Higiene Urbana | G92: Finalizada | H92: Finalizada
A93: 2499-ENEEPHGC | B93: CAMPAÑA GCBA | CONVIVENCIA | Cuidado de perros | C93: 46063 | D93: 46112 | E93: M2 | F93: Espacio Público e Higiene Urbana | G93: Finalizada | H93: Finalizada
A94: 2500-ENEEPHGC | B94: CAMPAÑA GCBA | CONVIVENCIA | Doble Fila | C94: 46064 | D94: 46112 | E94: M2 | F94: Espacio Público e Higiene Urbana | G94: Finalizada | H94: Finalizada
A95: 2501-ENEJDGAG | B95: RDV JM Flores 30/01 | C95: 46045 | D95: 46067 | E95: Cercanía | F95: Jefatura de Gobierno | G95: Finalizada | H95: Finalizada
A96: 2502-ENEJDGAG | B96: CAFE JM Versalles 29/01 | C96: 46048 | D96: 46073 | E96: Cercanía | F96: Jefatura de Gobierno | G96: Finalizada | H96: Finalizada
A97: 2503-ENEPCCVC | B97: Reunión de Co-creación - Eventos Masivos Huracán | C97: 46055 | D97: 46055 | E97: Cercanía | F97: Cercanía y PC | G97: Finalizada | H97: Finalizada
A98: 2504-ENEFESGC | B98: La Ciudad Más Linda del Mundo | Etapa 2 | C98: 46087 | D98: 46112 | E98: Ciudad Atractiva | F98: Festivales y Eventos | G98: Finalizada | H98: Pausada
A99: 2505-ENEPCCVC | B99: Verano 2026 - Misión Bomberos: Un Día en la Estación FEBRERO | C99: 46051 | D99: 46051 | E99: Cercanía | F99: Cercanía y PC | G99: Finalizada | H99: Finalizada
A100: 2506-ENEPCCVC | B100: Verano 2026 - La Gran Aventura del Reciclaje | Febrero | C100: 46050 | D100: 46050 | E100: Cercanía | F100: Cercanía y PC | G100: Finalizada | H100: Finalizada
A101: 2507-ENEPCCVC | B101: Verano 2026 - Expedición Botánica - 2 | C101: 46051 | D101: 46051 | E101: Cercanía | F101: Cercanía y PC | G101: Finalizada | H101: Finalizada
... A112: 2519-ENEINFGC | B112: Infraestructura I Cortes y desvíos en Larralde | C112: 46062 | D112: 46158 | E112: Movilidad | F112: Infraestructura | G112: Finalizada | H112: Finalizada
A113: 2520-ENEEPHGC | B113: Hitos Transparencia | E113: Reforma del Estado | F113: Espacio Público e Higiene Urbana | G113: Pendiente | H113: Pendiente
A114: 2521-ENEPCCVC | B114: Paseo náutico por el Riachuelo | C114: 46056 | D114: 46056 | E114: Cercanía | F114: Cercanía y PC | G114: Finalizada | H114: Finalizada
A115: 2522-ENEPCCVC | B115: Reunión Co-Creación: Eventos Masivos River | C115: 46056 | D115: 46056 | E115: Cercanía | F115: Cercanía y PC | G115: Finalizada | H115: Finalizada
A116: 2523-ENEPCCVC | B116: Verano 2026 - Perros en acción: Aventura K9 | C116: 46055 | D116: 46055 | E116: Cercanía | F116: Cercanía y PC | G116: Finalizada | H116: Finalizada
A117: 2524-ENEPCCVC | B117: Verano 2026 - Dejá que vuele tu imaginación | C117: 46052 | D117: 46052 | E117: Cercanía | F117: Cercanía y PC | G117: Finalizada | H117: Finalizada
A118: 2525-ENEPCCVC | B118: Verano 2026- Exploradores del Ecoparque | C118: 46034 | D118: 46034 | E118: Cercanía | F118: Cercanía y PC | G118: Finalizada | H118: Finalizada
A119: 2526-ENESEGGC | B119: CAMPAÑA GCBA | SEGURIDAD | Desalojo en San Nicolás | C119: 46051 | D119: 46077 | E119: M2 | F119: Seguridad | G119: Finalizada | H119: Finalizada
A120: 2527-ENEPCCVC | B120: Verano 2026- Un día perfecto | C120: 46058 | D120: 46058 | E120: Cercanía | F120: Cercanía y PC | G120: Finalizada | H120: Finalizada
A121: 2528-ENEPCCVC | B121: Verano 2026 - CIFA para chicos | C121: 46059 | D121: 46071 | E121: Cercanía | F121: Cercanía y PC | G121: Finalizada | H121: Finalizada
A122: 2529-ENESEGGC | B122: CAMPAÑA GCBA | SEGURIDAD | Nuevo equipamiento PDLC | C122: 46052 | D122: 46112 | E122: M2 | F122: Seguridad | G122: Finalizada | H122: Finalizada
A123: 2530-ENEJDGVC | B123: RDV MINISTROS | Gabriel Sanchez Zinny 04/02 | C123: 46051 | D123: 46058 | E123: Cercanía | F123: Jefatura de Gabinete | G123: Finalizada | H123: Finalizada
A124: 2531-ENEJDGVC | B124: RDV MINISTROS | Gabriel Sanchez Zinny 06/02 | C124: 46055 | D124: 46062 | E124: Cercanía | F124: Jefatura de Gabinete | G124: Finalizada | H124: Finalizada
A125: 2532-ENEJDGAG | B125: RDV JM | VILLA URQUIZA 2/2 | C125: 46051 | D125: 46075 | E125: Cercanía | F125: Jefatura de Gobierno | G125: Finalizada | H125: Finalizada
... A236: 2648-FEBPCCVC | B236: Experiencia BA: Brigada canina K | C236: 46084 | D236: 46084 | E236: Cercanía | F236: Cercanía y PC | G236: Finalizada | H236: Finalizada
A237: 2649-FEBPCCVC | B237: Experiencias BA - Visita guiada al palacio legislativo | E237: Cercanía | F237: Cercanía y PC | G237: Pendiente | H237: Finalizada
A238: 2650-FEBVINGC | B238: CAMPAÑA GCBA | VINCULO CIUDADANO | Mas servicios en tu barrio 2026: Flores 02/03 | C238: 46080 | D238: 46080 | E238: M2 | F238: Vínculo Ciudadano | G238: Finalizada | H238: Finalizada
...

Sheet MAIL
A1: ID cuentas | B1: Enviados | C1: Entregados | D1: Aperturas | E1: Clics
A2: 0005-DICINFGC | B2: 117336 | C2: 115944 | D2: 50494 | E2: 3698
A3: 0005-DICINFGC | B3: 8695 | C3: 8600 | D3: 3680 | E3: 186
A4: 0010-ENESEGGC | B4: 28643 | C4: 28318 | D4: 12529 | E4: 4139
A5: 0006-ENESALGC | B5: 174485 | C5: 172239 | D5: 54736 | E5: 131
A6: 0006-ENESALGC | B6: 73853 | C6: 73516 | D6: 40110 | E6: 778
A7: 0126-MAYINFGC | B7: 118970 | C7: 117853 | D7: 42923 | E7: 2310
A8: 0126-MAYINFGC | B8: 123434 | C8: 122100 | D8: 33075 | E8: 638
A9: 0012-ENEFESGC | B9: 87104 | C9: 86107 | D9: 27769 | E9: 1185
A10: 0012-ENEFESGC | B10: 86490 | C10: 85359 | D10: 25191 | E10: 1205
A11: 0012-ENEFESGC | B11: 172692 | C11: 170705 | D11: 52278 | E11: 2891
A12: 0014-ENESALGC | B12: 15937 | C12: 15802 | D12: 8857 | E12: 365
A13: 0016-ENEDHHGC | B13: 142 | C13: 142 | D13: 124 | E13: 110
... A3042: 1754-AGOFESGC | B3042: 72479 | C3042: 72268 | D3042: 52911 | E3042: 2166
A3043: 1933-SEPINFGC | B3043: 220.840‬ | C3043: 217490 | D3043: 88610 | E3043: 2213
A3044: 2247-NOVSEGGC | B3044: 4224 | C3044: 4143 | D3044: 1388 | E3044: 44
A3045: 2192-OCTINFGC | B3045: 79627 | C3045: 78563 | D3045: 32924 | E3045: 174
A3046: 2220-NOVPCCVC | B3046: 52548 | C3046: 51616 | D3046: 16607 | E3046: 400
A3047: 2225-NOVSEGVC | B3047: 75830 | C3047: 74137 | D3047: 13045 | E3047: 252
A3048: 2224-NOVSEGVC | B3048: 72041 | C3048: 70756 | D3048: 17175 | E3048: 235
A3049: 2233-NOVEPHVC | B3049: 352 | C3049: 352 | D3049: 214 | E3049: 2
A3050: 2219-NOVJDGVC | B3050: 139 | C3050: 138 | D3050: 71 | E3050: 1
A3051: 2232-NOVJDGVC | B3051: 62 | C3051: 61 | D3051: 27 | E3051: 1
A3052: 2235-NOVINFVC | B3052: 187 | C3052: 187 | D3052: 102 | E3052: 1
A3053: 1871-AGOEDUGC | B3053: 95 | C3053: 94 | D3053: 73 | E3053: 49
A3054: 1921-SEPAMBGC | B3054: 83648 | C3054: 81981 | D3054: 28051 | E3054: 803
A3055: 2244-NOVPCCVC | B3055: 19314 | C3055: 18958 | D3055: 4212 | E3055: 45
... A3139: 2267-NOVSEGVC | B3139: 61131 | C3139: 59567 | D3139: 7860 | E3139: 107
A3140: 2269-NOVSEGVC | B3140: 72,.423 | C3140: 71166 | D3140: 14739 | E3140: 270
A3141: 2268-NOVSEGVC | B3141: 68780 | C3141: 67355 | D3141: 12905 | E3141: 173
A3142: 2263-NOVEPHVC | B3142: 185 | C3142: 185 | D3142: 155 | E3142: 2
A3143: 2228-NOVTURGC | B3143: 376 | C3143: 366 | D3143: 190 | E3143: 61
A3144: 1871-AGOEDUGC | B3144: 126956 | C3144: 124867 | D3144: 37662 | E3144: 826
A3145: 1921-SEPAMBGC | B3145: 20270 | C3145: 19814 | D3145: 5530 | E3145: 437
A3146: 2277-NOVEDUVC | B3146: 61 | C3146: 60 | D3146: 34 | E3146: 1
A3147: 2296-NOVINFGC | B3147: 63373 | C3147: 62267 | D3147: 16336 | E3147: 81
A3148: 2271-NOVPCCVC | B3148: 19202 | C3148: 18735 | D3148: 3250 | E3148: 103
A3149: 2271-NOVPCCVC | B3149: 3946 | C3149: 3824 | D3149: 747 | E3149: 20
A3150: 2260-NOVPCCVC | B3150: 55097 | C3150: 54087 | D3150: 14838 | E3150: 471
A3151: 2262-NOVJDGVC | B3151: 122 | C3151: 121 | D3151: 65 | E3151: 1
A3152: 2230-NOVJDGAG | B3152: 2163 | C3152: 2150 | D3152: 805 | E3152: 3
... A5225: 3125-MAYPCCVC | B5225: 134868 | C5225: 133039 | D5225: 30753 | E5225: 1664
A5226: 3194-JUNSEGVC
A5227: 3192-JUNSEGVC | B5227: 102 | C5227: 101 | D5227: 56 | E5227: 1
A5228: 3161-JUNJDGGC | B5228: 54690 | C5228: 54110 | D5228: 17062 | E5228: 235
A5229: 3230-JUNINFGJ | B5229: 86102 | C5229: 85317 | D5229: 30739 | E5229: 782
A5230: 3186-JUNFESGC | B5230: 145739 | C5230: 144142 | D5230: 49575 | E5230: 6822
A5231: 3193-JUNSEGVC | B5231: 124 | C5231: 123 | D5231: 69 | E5231: 1
A5232: 3184-JUNEDUGC | B5232: 218405 | C5232: 215828 | D5232: 59201 | E5232: 394
A5233: 3203-JUNTURGC | B5233: 26646 | C5233: 26646 | D5233: 6 | E5233: 0
A5234: 2425-DICEPHGC | B5234: 1879 | C5234: 1857 | D5234: 497 | E5234: 16
A5235: 2425-DICEPHGC | B5235: 9533 | C5235: 9449 | D5235: 3382 | E5235: 76
A5236: 3156-JUNJDGAG | B5236: 3108 | C5236: 3100 | D5236: 2033 | E5236: 6
A5237: 3156-JUNJDGAG | B5237: 182 | C5237: 181 | D5237: 77 | E5237: 2
A5238: 3195-JUNSEGVC | B5238: 171 | C5238: 170 | D5238: 87 | E5238: 2
... A5576: 3374-JULEDUGC | B5576: 130721 | C5576: 129459 | D5576: 46151 | E5576: 1975
A5577: 3371-JULSEGVC
A5578: 3245-JUNFESGC
A5579: 3245-JUNFESGC
A5580: 3333-JULINFGC
A5581: 3016-MAYFESGC
A5582: 3214-JUNAMBVC | B5582: 42 | C5582: 41 | D5582: 12 | E5582: 2
A5583: 3232-JUNDHHVC | B5583: 174 | C5583: 173 | D5583: 94 | E5583: 2
A5584: 3276-JUNDECGC
A5585: 3310-JULPCCVC
A5586: 1921-SEPAMBGC | B5586: 56909 | C5586: 56053 | D5586: 14052 | E5586: 438
A5587: 3358-JULPCCVC
A5588: 2478-ENEINNGC
A5589: 2478-ENEINNGC
A5590: 3293-JULPCCVC
A5591: 2681-MARINFGC
A5592: 2742-MARFESGC
A5593: 1907-SEPINFGC
A5594: 3045-MAYFESGC
A5595: 3245-JUNFESGC
A5596: 3245-JUNFESGC
A5597: 3243-JUNFESGC
A5598: 3336-JULJDGGC
... A5603: 3366-JULEPHVC
A5604: 3372-JULSEGVC | B5604: 101 | C5604: 101 | D5604: 35 | E5604: 1
A5605: 3372-JULSEGVC
A5606: 3373-JULSEGVC | B5606: 125 | C5606: 124 | D5606: 40 | E5606: 2
A5607: 3373-JULSEGVC
A5608: 3385-JULVINGC
A5609: 3393-JULVINGC
A5610: 3394-JULVINGC
A5611: 3396-JULVINGC
A5612: 3395-JULVINGC
A5613: 3397-JULVINGC
A5614: 3398-JULVINGC
A5615: 3383-JULVINGC
A5616: 3392-JULVINGC
A5617: 3386-JULVINGC
A5618: 3384-JULVINGC
A5619: 2746-MARDECGC
A5620: 3289-JUNJDGAG | B5620: 277445 | C5620: 273543 | D5620: 49242 | E5620: 1658
A5621: 3289-JUNJDGAG
A5622: 3289-JUNJDGAG
A5623: 3268-JUNHYFGC
A5624: 3340-JULAMBVC | B5624: 45 | C5624: 44 | D5624: 11 | E5624: 1
...

Sheet IVR
A1: ID cuentas | B1: Audiencia | C1: Llamados Realizados | D1: Llamados Atendidos | E1: Escucharon +75% | F1: Marque 1
A2: 0781-NOVINFGC | B2: 68237 | C2: 75758 | D2: 65795 | E2: 20401 | F2: 394
A3: 0872-ENENEWAN | B3: 56899 | C3: 64158 | D3: 53701 | E3: 9305 | F3: 122
A4: 0942-FEBNEWAN | B4: 28071 | C4: 34949 | D4: 25011 | E4: 7950 | F4: 15
A5: 0955-FEBNEWAG | B5: 34339 | C5: 36357 | D5: 32892 | E5: 4370 | F5: 31
A6: 0942-FEBNEWAN | B6: 27475 | C6: 29856 | D6: 26311 | E6: 6267 | F6: 58
A7: 0942-FEBNEWAN | B7: 16521 | C7: 17285 | D7: 13468 | E7: 1518 | F7: 19
A8: 0979-FEBNEWAN | B8: 74231 | C8: 109612 | D8: 58134 | E8: 25747 | F8: 25
A9: 0979-FEBNEWAN | B9: 94510 | C9: 104301 | D9: 91168 | E9: 29331 | F9: 51
A10: 0979-FEBNEWAN | B10: 68406 | C10: 93416 | D10: 59300 | E10: 25915 | F10: 23
A11: 0979-FEBNEWAN | B11: 47369 | C11: 54662 | D11: 43309 | E11: 14227 | F11: 22
A12: 1080-MARNEWAN | B12: 209068 | C12: 233915 | D12: 196526 | E12: 65326 | F12: 219
A13: 1078-MARINFAG | B13: 5801 | C13: 6264 | D13: 5378 | E13: 2552 | F13: 2
... A189: 3347-JULJDGAG | B189: 37763 | C189: 6700 | D189: 6161 | E189: 2229 | F189: 67
A190: 3387-JULJDGGC
A191: 3387-JULJDGGC

Sheet SMS
A1: ID cuentas | B1: Enviados | C1: Entregados | D1: Clics
A2: 0005-DICINFGC | B2: 64884 | C2: 62515 | D2: 0
A3: 0006-ENESALGC | B3: 27072 | C3: 2705 | D3: 0
A4: 0012-ENEFESGC | B4: 39974 | C4: 36774 | D4: 0
A5: 0012-ENEFESGC | B5: 187171 | C5: 178891 | D5: 0
A6: 0008-ENESALGC | B6: 174484 | C6: 167161 | D6: 0
A7: 0008-ENESALGC | B7: 120809 | C7: 114751 | D7: 0
A8: 0063-MARDHHGC | B8: 2828 | C8: 2601 | D8: 0
A9: 0038-FEBSALGC | B9: 62983 | C9: 59162 | D9: 0
A10: 0038-FEBSALGC | B10: 72625 | C10: 69533 | D10: 0
A11: 0038-FEBSALGC | B11: 73523 | C11: 698 | D11: 0
A12: 0038-FEBSALGC | B12: 62382 | C12: 59792 | D12: 0
A13: 0038-FEBSALGC | B13: 39423 | C13: 37885 | D13: 0
... A85: 3278-JUNVINGC | B85: 23 | C85: 21 | D85: 4
A86: 3365-JULINFGC

Sheet CC
A1: ID Cuentas | B1: Base enviada | C1: Base barrida | D1: Contactados | E1: Efectivos
A2: 0002-DICEDUGC | B2: 3346 | C2: 3346 | D2: 1140 | E2: 953
A3: 0001-DICSALGC | B3: 11606 | C3: 9785 | D3: 2911 | E3: 2297
A4: 0009-ENEVINGC | B4: 12124 | C4: 11014 | D4: 2919 | E4: 2420
A5: 0003-DICSECGC | B5: 1500 | C5: 116 | D5: 31 | E5: 27
A6: 0004-DICEPHGC | B6: 2500 | C6: 2500 | D6: 747 | E6: 680
A7: 0015-ENESALGC | B7: 4005 | C7: 4005 | D7: 1051 | E7: 1306
A8: 0012-ENEFESGC | B8: 9281 | C8: 8390 | D8: 1447 | E8: 1306
A9: 0023-FEBCULGC | B9: 5933 | C9: 5919 | D9: 1785 | E9: 1998
A10: 0045-MARSALGC | B10: 4700 | C10: 4228 | D10: 1194 | E10: 974
A11: 0023-FEBCULGC | B11: 7378 | C11: 7041 | D11: 1901 | E11: 1868
A12: 0054-MARINFGC | B12: 2100 | C12: 2062 | D12: 767 | E12: 699
A13: 0040-MARVINVC | B13: 3351 | C13: 2518 | D13: 994 | E13: 908
... A1285: 3373-JULSEGVC | B1285: 0 | C1285: 0 | D1285: 0 | E1285: 0

Sheet DIGITAL
A1: Id cuentas | B1: Plataforma | C1: Impresiones | D1: Visualizaciones | E1: Clics | F1: nombre_campaña | G1: eje | H1: area | I1: estado
A2: 1933-SEPINFGC | B2: Meta | C2: 1170879 | D2: 16592 | E2: 1347 | F2: CAMPAÑA GCBA | INFRAESTRUCTURA | Campaña 360° Movilidad 2025 | G2: Movilidad | H2: Infraestructura | I2: Finalizada
A3: 1933-SEPINFGC | B3: Meta | C3: 1010417 | D3: 8603 | E3: 1529 | F3: CAMPAÑA GCBA | INFRAESTRUCTURA | Campaña 360° Movilidad 2025 | G3: Movilidad | H3: Infraestructura | I3: Finalizada
A4: 1933-SEPINFGC | B4: Meta | C4: 869942 | D4: 4525 | E4: 790 | F4: CAMPAÑA GCBA | INFRAESTRUCTURA | Campaña 360° Movilidad 2025 | G4: Movilidad | H4: Infraestructura | I4: Finalizada
A5: 1933-SEPINFGC | B5: Meta | C5: 1327029 | D5: 0 | E5: 1584 | F5: CAMPAÑA GCBA | INFRAESTRUCTURA | Campaña 360° Movilidad 2025 | G5: Movilidad | H5: Infraestructura | I5: Finalizada
A6: 1933-SEPINFGC | B6: Meta | C6: 972190 | D6: 49700 | E6: 909 | F6: CAMPAÑA GCBA | INFRAESTRUCTURA | Campaña 360° Movilidad 2025 | G6: Movilidad | H6: Infraestructura | I6: Finalizada
A7: 1933-SEPINFGC | B7: Meta | C7: 440836 | D7: 0 | E7: 796 | F7: CAMPAÑA GCBA | INFRAESTRUCTURA | Campaña 360° Movilidad 2025 | G7: Movilidad | H7: Infraestructura | I7: Finalizada
A8: 1933-SEPINFGC | B8: Meta | C8: 517507 | D8: 0 | E8: 669 | F8: CAMPAÑA GCBA | INFRAESTRUCTURA | Campaña 360° Movilidad 2025 | G8: Movilidad | H8: Infraestructura | I8: Finalizada
A9: 1933-SEPINFGC | B9: Meta | C9: 696900 | D9: 52396 | E9: 459 | F9: CAMPAÑA GCBA | INFRAESTRUCTURA | Campaña 360° Movilidad 2025 | G9: Movilidad | H9: Infraestructura | I9: Finalizada
A10: 1933-SEPINFGC | B10: Meta | C10: 437010 | D10: 31477 | E10: 253 | F10: CAMPAÑA GCBA | INFRAESTRUCTURA | Campaña 360° Movilidad 2025 | G10: Movilidad | H10: Infraestructura | I10: Finalizada
A11: 1933-SEPINFGC | B11: Meta | C11: 382512 | D11: 40213 | E11: 384 | F11: CAMPAÑA GCBA | INFRAESTRUCTURA | Campaña 360° Movilidad 2025 | G11: Movilidad | H11: Infraestructura | I11: Finalizada
A12: 1933-SEPINFGC | B12: Meta | C12: 537616 | D12: 56507 | E12: 864 | F12: CAMPAÑA GCBA | INFRAESTRUCTURA | Campaña 360° Movilidad 2025 | G12: Movilidad | H12: Infraestructura | I12: Finalizada
A13: 1933-SEPINFGC | B13: Meta | C13: 529325 | D13: 76554 | E13: 259 | F13: CAMPAÑA GCBA | INFRAESTRUCTURA | Campaña 360° Movilidad 2025 | G13: Movilidad | H13: Infraestructura | I13: Finalizada
... A133: 2255-NOVSALGC | B133: Meta | C133: 0 | D133: 0 | E133: 0 | F133: Sistema de Salud Público - Geolocalizado | G133: Cuidado | H133: Salud | I133: Finalizada
A134: 2255-NOVSALGC | B134: Meta | F134: Sistema de Salud Público - Geolocalizado | G134: Cuidado | H134: Salud | I134: Finalizada
A135: 2255-NOVSALGC | B135: Meta | C135: 68656 | D135: 0 | E135: 439 | F135: Sistema de Salud Público - Geolocalizado | G135: Cuidado | H135: Salud | I135: Finalizada
A136: 2255-NOVSALGC | B136: Meta | C136: 154398 | D136: 0 | E136: 193 | F136: Sistema de Salud Público - Geolocalizado | G136: Cuidado | H136: Salud | I136: Finalizada
A137: 2255-NOVSALGC | B137: Meta | C137: 63067 | D137: 0 | E137: 463 | F137: Sistema de Salud Público - Geolocalizado | G137: Cuidado | H137: Salud | I137: Finalizada
A138: 2255-NOVSALGC | B138: Meta | C138: 80656 | D138: 0 | E138: 489 | F138: Sistema de Salud Público - Geolocalizado | G138: Cuidado | H138: Salud | I138: Finalizada
A139: 2255-NOVSALGC | B139: Meta | C139: 86215 | D139: 0 | E139: 378 | F139: Sistema de Salud Público - Geolocalizado | G139: Cuidado | H139: Salud | I139: Finalizada
A140: 2255-NOVSALGC | B140: Meta | C140: 86729 | D140: 0 | E140: 381 | F140: Sistema de Salud Público - Geolocalizado | G140: Cuidado | H140: Salud | I140: Finalizada
A141: 2255-NOVSALGC | B141: Meta | C141: 69167 | D141: 0 | E141: 488 | F141: Sistema de Salud Público - Geolocalizado | G141: Cuidado | H141: Salud | I141: Finalizada
A142: 2255-NOVSALGC | B142: Meta | C142: 143692 | D142: 0 | E142: 268 | F142: Sistema de Salud Público - Geolocalizado | G142: Cuidado | H142: Salud | I142: Finalizada
A143: 2444-DICINFGC | B143: Meta | C143: 51390 | D143: 0 | E143: 8 | F143: Infraestructura I Cortes en AU Dellepiane por obras | G143: Movilidad | H143: Infraestructura | I143: Finalizada
A144: 1933-SEPINFGC | B144: TikTok | C144: 414652 | D144: 4626 | E144: 564 | F144: CAMPAÑA GCBA | INFRAESTRUCTURA | Campaña 360° Movilidad 2025 | G144: Movilidad | H144: Infraestructura | I144: Finalizada
A145: 1933-SEPINFGC | B145: TikTok | C145: 414652 | D145: 4626 | E145: 564 | F145: CAMPAÑA GCBA | INFRAESTRUCTURA | Campaña 360° Movilidad 2025 | G145: Movilidad | H145: Infraestructura | I145: Finalizada
A146: 1871-AGOEDUGC | B146: TikTok | C146: 717782 | D146: 7216 | E146: 1195 | F146: Campaña GCBA | Educación | TUMO | G146: Cuidado | H146: Educación | I146: Activa
... A779: 2424-DICFESGC | B779: Meta | C779: 1388575 | D779: 68641 | E779: 2111 | F779: Verano en Buenos Aires 2026 | Generico | G779: Ciudad Atractiva | H779: Festivales y Eventos | I779: Finalizada
A780: 2514-ENEINFGJ | B780: Meta | C780: 422848 | D780: 0 | E780: 22
A781: 2533-ENEJDGAG | B781: Meta | C781: 23972 | D781: 3218 | E781: 50 | F781: RDV JM | CONSTITUCIÓN 6/2 | G781: Cercanía | H781: Jefatura de Gobierno | I781: Finalizada
A782: 2519-ENEINFGC | B782: Meta | C782: 21349 | D782: 0 | E782: 4 | F782: Infraestructura I Cortes y desvíos en Larralde | G782: Movilidad | H782: Infraestructura | I782: Finalizada
A783: 2130-OCTSALGC | B783: Meta | C783: 379335 | D783: 0 | E783: 1140 | F783: Hospital Pirovano: Remodelaciones | G783: Cuidado | H783: Salud | I783: Finalizada
A784: 2451-ENEPCCVC | B784: Meta | C784: 572630 | D784: 0 | E784: 40 | F784: Participación Ciudadana - Verano en la Ciudad (Pauta RRSS) | G784: Cercanía | H784: Cercanía y PC | I784: Finalizada
A785: 2451-ENEPCCVC | B785: Meta | C785: 514622 | D785: 0 | E785: 311 | F785: Participación Ciudadana - Verano en la Ciudad (Pauta RRSS) | G785: Cercanía | H785: Cercanía y PC | I785: Finalizada
A786: 2460-ENEFESGC | B786: Meta | C786: 1070371 | D786: 0 | E786: 1650 | F786: Campaña verano en la ciudad | Verano en los anfiteatros | G786: Ciudad Atractiva | H786: Festivales y Eventos | I786: Finalizada
A787: 2460-ENEFESGC | B787: Meta | C787: 1131301 | D787: 0 | E787: 1834 | F787: Campaña verano en la ciudad | Verano en los anfiteatros | G787: Ciudad Atractiva | H787: Festivales y Eventos | I787: Finalizada
A788: 2460-ENEFESGC | B788: Meta | C788: 167013 | D788: 0 | E788: 355 | F788: Campaña verano en la ciudad | Verano en los anfiteatros | G788: Ciudad Atractiva | H788: Festivales y Eventos | I788: Finalizada
A789: 2435-DICFESGC | B789: Meta | C789: 449503 | D789: 0 | E789: 1195 | F789: Verano en la Ciudad | Atardeceres en los parques | G789: Ciudad Atractiva | H789: Festivales y Eventos | I789: Finalizada
A790: 2435-DICFESGC | B790: Meta | C790: 396725 | D790: 0 | E790: 758 | F790: Verano en la Ciudad | Atardeceres en los parques | G790: Ciudad Atractiva | H790: Festivales y Eventos | I790: Finalizada
A791: 2435-DICFESGC | B791: Meta | C791: 776654 | D791: 0 | E791: 2186 | F791: Verano en la Ciudad | Atardeceres en los parques | G791: Ciudad Atractiva | H791: Festivales y Eventos | I791: Finalizada
A792: 2435-DICFESGC | B792: Meta | C792: 137532 | D792: 0 | E792: 1261 | F792: Verano en la Ciudad | Atardeceres en los parques | G792: Ciudad Atractiva | H792: Festivales y Eventos | I792: Finalizada
... A937: 2596-FEBJDGAG | B937: Meta | C937: 7666 | D937: 2029 | E937: 40 | F937: RDV JM | 20/02 Villa Luro | G937: Cercanía | H937: Jefatura de Gobierno | I937: Finalizada
B938: Meta | C938: 18666 | D938: 0 | E938: 74
A939: 2597-FEBJDGAG | B939: Meta | C939: 38191 | D939: 7075 | E939: 61 | F939: RDV JM | 21/02 Floresta | G939: Cercanía | H939: Jefatura de Gobierno | I939: Finalizada
A940: 2658-FEBJDGVC | B940: Meta | C940: 112857 | D940: 0 | E940: 122 | F940: RDV MINISTROS | GABRIEL SÁNCHEZ ZINNY 2/3 RECOLETA | G940: Cercanía | H940: Jefatura de Gabinete | I940: Finalizada
A941: 2645-FEBINFGC | B941: Meta | C941: 38563 | D941: 0 | E941: 472 | F941: CAMPAÑA GCBA | INFRAESTRUCTURA | Cambio de sentido calle Culpina | G941: Movilidad | H941: Infraestructura | I941: Finalizada
A942: 2496-ENEVINGC | B942: Meta | C942: 24306 | D942: 0 | E942: 321 | F942: CAMPAÑA GCBA | VINCULO CIUDADANO | Mas servicios en tu barrio 2026: Recoleta 25/02 | G942: M2 | H942: Vínculo Ciudadano | I942: Finalizada
A943: 2651-FEBINFGC | B943: Meta | C943: 54530 | D943: 0 | E943: 234 | F943: CAMPAÑA GCBA | Infraestructura | Cierre estación Tribunales | G943: Movilidad | H943: Infraestructura | I943: Finalizada
A944: 2651-FEBINFGC | B944: Meta | C944: 245910 | D944: 0 | E944: 438 | F944: CAMPAÑA GCBA | Infraestructura | Cierre estación Tribunales | G944: Movilidad | H944: Infraestructura | I944: Finalizada
A945: 2654-FEBJDGAG | B945: Meta | C945: 27443 | D945: 7641 | E945: 79 | F945: RDV JM | 4/3 VILLA GENERAL MITRE | G945: Cercanía | H945: Jefatura de Gobierno | I945: Finalizada
A946: 2656-FEBINFVC | B946: Meta | C946: 159731 | D946: 0 | E946: 194 | F946: RDV MINISTROS | PABLO BERECIARTUA 2/3 COMUNA 5 | G946: Cercanía | H946: Infraestructura | I946: Finalizada
A947: 2657-FEBVINVC | B947: Meta | C947: 53906 | D947: 0 | E947: 245 | F947: RDV MINISTROS | EZEQUIEL SABOR 2/3 COMUNA 6 | G947: Cercanía | H947: Vínculo Ciudadano | I947: Finalizada
A948: Falta ID | B948: Meta | C948: 7964 | D948: 0 | E948: 0
A949: 2583-FEBSALGC | B949: Meta | C949: 63329 | D949: 0 | E949: 161 | F949: Durante de obra - Htal. Rocca | G949: Cuidado | H949: Salud | I949: Finalizada
A950: 2583-FEBSALGC | B950: Meta | C950: 100840 | D950: 0 | E950: 99 | F950: Durante de obra - Htal. Rocca | G950: Cuidado | H950: Salud | I950: Finalizada
A951: 2585-FEBEPHGC | B951: Meta | C951: 47754 | D951: 0 | E951: 0 | F951: CAMPAÑA GCBA | MEPHU | FIN DE OBRA CALLE TUCUMÁN | G951: M2 | H951: Espacio Público e Higiene Urbana | I951: Finalizada
A952: 2592-FEBSEGGC | B952: Meta | C952: 889422 | D952: 86657 | E952: 1598 | F952: CAMPAÑA GCBA | SEGURIDAD | Megaoperativo motochorros PDLC | G952: M2 | H952: Seguridad | I952: Finalizada
A953: 2592-FEBSEGGC | B953: Meta | C953: 745368 | D953: 105486 | E953: 2066 | F953: CAMPAÑA GCBA | SEGURIDAD | Megaoperativo motochorros PDLC | G953: M2 | H953: Seguridad | I953: Finalizada
A954: 2415-DICINFGC | B954: Meta | C954: 345155 | D954: 0 | E954: 263 | F954: INFRAESTRUCTURA | Cortes y Desvíos del finde 13 y 14 Dic | G954: Movilidad | H954: Infraestructura | I954: Finalizada
A955: 2519-ENEINFGC | B955: Meta | C955: 181001 | D955: 0 | E955: 20 | F955: Infraestructura I Cortes y desvíos en Larralde | G955: Movilidad | H955: Infraestructura | I955: Finalizada
A956: 2623-FEBAMBGC | B956: Meta | C956: 1144733 | D956: 0 | E956: 2300 | F956: Puntos Verdes Fijos y Móviles | G956: Cuidado | H956: Vicejefatura (Ambiente) | I956: Finalizada
A957: 2623-FEBAMBGC | B957: Meta | C957: 1070127 | D957: 0 | E957: 1458 | F957: Puntos Verdes Fijos y Móviles | G957: Cuidado | H957: Vicejefatura (Ambiente) | I957: Finalizada
A958: 2644-FEBINFGC | B958: Meta | C958: 707292 | D958: 0 | E958: 996 | F958: CAMPAÑA GCBA | Infraestructura | Reapertura estación Uruguay | G958: Movilidad | H958: Infraestructura | I958: Finalizada
A959: 2644-FEBINFGC | B959: Meta | C959: 116249 | D959: 0 | E959: 383 | F959: CAMPAÑA GCBA | Infraestructura | Reapertura estación Uruguay | G959: Movilidad | H959: Infraestructura | I959: Finalizada
A960: 2498-ENEEPHGC | B960: Meta | C960: 2173066 | D960: 36837 | E960: 2700 | F960: CAMPAÑA GCBA | CONVIVENCIA | Genérica | G960: M2 | H960: Espacio Público e Higiene Urbana | I960: Finalizada
... A1001: 2665-FEBSEGVC | B1001: Meta | C1001: 492445 | D1001: 0 | E1001: 601 | F1001: RDV Ministros | Gabino Tapia 5/3 Comuna 3 | G1001: Cercanía | H1001: Seguridad | I1001: Finalizada
A1002: 2671-FEBJDGVC | B1002: Meta | C1002: 47331 | D1002: 0 | E1002: 114
A1003: 2480-ENEINFGC | B1003: Meta | C1003: 148486 | D1003: 0 | E1003: 670 | F1003: Campaña GCBA | Infraestructura: Obras en La Boca: calle Necochea | G1003: M2 | H1003: Infraestructura | I1003: Finalizada
A1004: 2614-FEBDUDGC | B1004: Meta | C1004: 746356 | D1004: 20037 | E1004: 2487 | F1004: DEPORTES CALLEJERO DE BUENOS AIRES de TC2000 | G1004: Ciudad Atractiva | H1004: Desarrollo Urbano + Deportes | I1004: Finalizada
A1005: 2614-FEBDUDGC | B1005: Meta | C1005: 1246993 | D1005: 133500 | E1005: 1396 | F1005: DEPORTES CALLEJERO DE BUENOS AIRES de TC2000 | G1005: Ciudad Atractiva | H1005: Desarrollo Urbano + Deportes | I1005: Finalizada
A1006: 2676-MARAMBGC | B1006: Meta | C1006: 225544 | D1006: 0 | E1006: 367 | F1006: RDV Ministros | Clara Muzzio - 6/03 | G1006: Cercanía | H1006: Vicejefatura (Ambiente) | I1006: Finalizada
A1007: 2587-FEBCULGC | B1007: Meta | C1007: 502187 | D1007: 3605 | E1007: 22865 | F1007: Campaña Suscripciones 2026 | G1007: Ciudad Atractiva | H1007: Cultura | I1007: Activa
A1008: 2587-FEBCULGC | B1008: Meta | C1008: 285429 | D1008: 5058 | E1008: 15949 | F1008: Campaña Suscripciones 2026 | G1008: Ciudad Atractiva | H1008: Cultura | I1008: Activa
A1009: 2667-FEBAMBVC | B1009: Meta | C1009: 201113 | D1009: 0 | E1009: 549 | F1009: RDV Ministros | Gabriel Mraida - 6/03 | G1009: Cercanía | H1009: Vicejefatura (Ambiente) | I1009: Finalizada
A1010: 2582-FEBSALGC | B1010: Meta | C1010: 191811 | D1010: 0 | E1010: 625 | F1010: Htal. Tornu - Remodelación Sala Tomografía | G1010: Cuidado | H1010: Salud | I1010: Finalizada
A1011: 2582-FEBSALGC | B1011: Meta | C1011: 578771 | D1011: 0 | E1011: 1010 | F1011: Htal. Tornu - Remodelación Sala Tomografía | G1011: Cuidado | H1011: Salud | I1011: Finalizada
A1012: 2596-FEBJDGAG | B1012: Meta | C1012: 18463 | D1012: 2905 | E1012: 62 | F1012: RDV JM | 20/02 Villa Luro | G1012: Cercanía | H1012: Jefatura de Gobierno | I1012: Finalizada
A1013: 2663-FEBSEGVC | B1013: Meta | C1013: 135156 | D1013: 0 | E1013: 335 | F1013: RDV Ministros | Maximiliano Piñeiro 5/3 Comuna 1 Norte | G1013: Cercanía | H1013: Seguridad | I1013: Finalizada
A1014: 2677-MAREDUCG | B1014: Meta | C1014: 204241 | D1014: 40520 | E1014: 226 | F1014: Comienzo Ciclo Lectivo en la Ciudad | G1014: Cuidado | H1014: Educación | I1014: Finalizada
... A1356: 2863-ABRSALGC | B1356: Meta | C1356: 359413 | D1356: 0 | E1356: 476 | F1356: CESAC 40 - Fin de obra | G1356: Cuidado | H1356: Salud | I1356: Finalizada
B1357: Meta | C1357: 0 | D1357: 0 | E1357: 0
A1358: 2868-ABRFESGC | B1358: Meta | C1358: 68741 | D1358: 2834 | E1358: 239 | F1358: Retiro Abierto | Edición Galerias | G1358: Ciudad Atractiva | H1358: Festivales y Eventos | I1358: Finalizada
A1359: 2868-ABRFESGC | B1359: Meta | C1359: 493389 | D1359: 6979 | E1359: 647 | F1359: Retiro Abierto | Edición Galerias | G1359: Ciudad Atractiva | H1359: Festivales y Eventos | I1359: Finalizada
A1360: 2886-ABRDECGC | B1360: Meta | C1360: 237181 | D1360: 973 | E1360: 445 | F1360: CAFECITO BA ABRIL | G1360: Ciudad Atractiva | H1360: Desarrollo Económico | I1360: Finalizada
A1361: 2496-ENEVINGC | B1361: Meta | C1361: 76991 | D1361: 0 | E1361: 393 | F1361: CAMPAÑA GCBA | VINCULO CIUDADANO | Mas servicios en tu barrio 2026: Recoleta 25/02 | G1361: M2 | H1361: Vínculo Ciudadano | I1361: Finalizada
A1362: 2496-ENEVINGC | B1362: Meta | C1362: 42831 | D1362: 0 | E1362: 233 | F1362: CAMPAÑA GCBA | VINCULO CIUDADANO | Mas servicios en tu barrio 2026: Recoleta 25/02 | G1362: M2 | H1362: Vínculo Ciudadano | I1362: Finalizada
A1363: 2496-ENEVINGC | B1363: Meta | C1363: 90091 | D1363: 0 | E1363: 319 | F1363: CAMPAÑA GCBA | VINCULO CIUDADANO | Mas servicios en tu barrio 2026: Recoleta 25/02 | G1363: M2 | H1363: Vínculo Ciudadano | I1363: Finalizada
A1364: 2496-ENEVINGC | B1364: Meta | C1364: 40015 | D1364: 0 | E1364: 210 | F1364: CAMPAÑA GCBA | VINCULO CIUDADANO | Mas servicios en tu barrio 2026: Recoleta 25/02 | G1364: M2 | H1364: Vínculo Ciudadano | I1364: Finalizada
A1365: 2909-ABRJDGAG | B1365: Meta | C1365: 217532 | D1365: 0 | E1365: 292 | F1365: RDV JM Primera Persona | Comuna 1 27/04 Gastón Pauls | G1365: Cercanía | H1365: Jefatura de Gobierno | I1365: Finalizada
A1366: 2909-ABRJDGAG | B1366: Meta | C1366: 217431 | D1366: 0 | E1366: 329 | F1366: RDV JM Primera Persona | Comuna 1 27/04 Gastón Pauls | G1366: Cercanía | H1366: Jefatura de Gobierno | I1366: Finalizada
A1367: 2909-ABRJDGAG | B1367: Meta | C1367: 45694 | D1367: 0 | E1367: 2547 | F1367: RDV JM Primera Persona | Comuna 1 27/04 Gastón Pauls | G1367: Cercanía | H1367: Jefatura de Gobierno | I1367: Finalizada
A1368: 2909-ABRJDGAG | B1368: Meta | C1368: 39449 | D1368: 0 | E1368: 2616 | F1368: RDV JM Primera Persona | Comuna 1 27/04 Gastón Pauls | G1368: Cercanía | H1368: Jefatura de Gobierno | I1368: Finalizada
A1369: 2785-MARSALGC | B1369: Meta | C1369: 480524 | D1369: 5154 | E1369: 680 | F1369: Centro de Cuidados Integrales | G1369: Cuidado | H1369: Salud | I1369: Finalizada
... A1516: 3006-MAYSEGVC | B1516: Meta | C1516: 180622 | D1516: 0 | E1516: 460 | F1516: RDV Ministros | Ignacio Baistrocchi 13/5 Comuna 13 | G1516: Cercanía | H1516: Seguridad | I1516: Finalizada
B1517: Meta | C1517: 0 | D1517: 0 | E1517: 0
A1518: 3007-MAYJDGVC | B1518: Meta | C1518: 24980 | D1518: 0 | E1518: 140 | F1518: RDV Ministros | Gabriel Sánchez Zinny - 13/5 | G1518: Cercanía | H1518: Jefatura de Gabinete | I1518: Finalizada
A1519: 2997-MAYJDGAG | B1519: Meta | C1519: 1173 | D1519: 0 | E1519: 49 | F1519: RDV JM TEMÁTICA | TE CUENTO BS AS 14/05 ORDEN PÚBLICO EJE SUR | G1519: Cercanía | H1519: Jefatura de Gobierno | I1519: Cancelada
A1520: 2997-MAYJDGAG | B1520: Meta | C1520: 54848 | D1520: 0 | E1520: 2200 | F1520: RDV JM TEMÁTICA | TE CUENTO BS AS 14/05 ORDEN PÚBLICO EJE SUR | G1520: Cercanía | H1520: Jefatura de Gobierno | I1520: Cancelada
A1521: 2974-MAYSEGGJ | B1521: Meta | C1521: 922615 | D1521: 50073 | E1521: 1652 | F1521: Nueva Patrulla de Control de Accesos a la Ciudad | G1521: M2 | H1521: Seguridad | I1521: Finalizada
A1522: 2988-MAYJDGAG | B1522: Meta | C1522: 12053 | D1522: 0 | E1522: 554 | F1522: 1 A 1 JM | Comuna 14 13/05 | G1522: Cercanía | H1522: Jefatura de Gobierno | I1522: Finalizada
...

Sheet ALCANCE
A1: ID Cuentas | B1: Alcance | C1: Frecuencia | D1: eje | E1: area | F1: nombre_campaña
A2: 2444-DICINFGC | B2: 140179 | C2: 1.1381591 | D2: Infraestructura | E2: Dellepiane | F2: Infraestructura I Cortes en AU Dellepiane por obras
A3: 2239-NOVSALGC | B3: 3270088 | C3: 3.1020116 | D3: Salud | E3: Emergencias | F3: Cuidados del Calor 2025 - Prevención
A4: 2240-NOVSALGC | B4: 1979868 | C4: 3.4276906 | D4: Salud | E4: Emergencias | F4: Cuidados del Calor 2025 - Síntomas
A5: 2407-DICDHHGC | B5: 345688 | C5: 1.5532706 | D5: Desarrollo Humano y Hábitat | E5: Red de Atención en Comuna 14 | F5: Red de atención - Comuna 14
A6: 2145-OCTVINGC | B6: 1084144 | C6: 1.9502769 | D6: Vínculo Ciudadano | E6: Obras en parques y plazas | F6: PIEZAS M2 | VINCULO CIUDADANO (GESTIÓN COMUNAL) | OBRAS EN PARQUES Y PLAZAS (PATIOS DE JUEGOS) Plan 2025
A7: 2108-OCTEDUGC | B7: 1745904 | C7: 1.3171446 | D7: Educación | F7: Inscripción 2025 a Profesorados de la Ciudad
A8: 2241-NOVSALGC | B8: 2394484 | C8: 1.3164298 | D8: Salud | E8: Emergencias | F8: Cuidados del Calor 2025 - Alertas Meteorológicas
A9: 2183-OCTSALGC | B9: 2510514 | C9: 2.9775759 | D9: Salud | E9: Sistema de Salud | F9: Sistema de Salud Público - Genérico
A10: 2227-NOVINFGC | B10: 2996348 | C10: 1.9993095 | D10: Infraestructura | E10: Seguridad en subte | F10: Infraestructura - SBASE | Campaña GCBA | Seguridad en Subte
A11: 2255-NOVSALGC | B11: 1566896 | C11: 3.6226406 | D11: Salud | E11: Sistema de Salud | F11: Sistema de Salud Público - Geolocalizado
A12: 1933-SEPINFGC | B12: 6681997 | C12: 0.9273355 | D12: Infraestructura | E12: Movilidad | F12: CAMPAÑA GCBA | INFRAESTRUCTURA | Campaña 360° Movilidad 2025
A13: 2415-DICINFGC | B13: 1608283 | C13: 1.8438975 | D13: Infraestructura | E13: Cortes y desvíos por eventos | F13: INFRAESTRUCTURA | Cortes y Desvíos del finde 13 y 14 Dic
A14: 2293-NOVFESGC | B14: 7843297 | C14: 1.9541976 | D14: Festivales y Eventos | E14: La Ciudad más linda del mundo | F14: LA CIUDAD MAS LINDA DEL MUNDO
A15: 2450-ENEJDGAG | B15: 79990 | C15: 4.04008 | D15: Jefatura de Gobierno | E15: ECVs Jorge Macri | F15: RDV JM - Boedo 9/1
A16: 2443-DICNEWAN | B16: 682062 | C16: 1.5975703 | D16: Anuncios y Newsletter | F16: Acciones de la Ciudad ante el calor extremo
A17: 2411-DICJDGAG | B17: 583776 | C17: 1.4922813 | D17: Jefatura de Gobierno | E17: ECVs Jorge Macri | F17: RDV JM | Caballito 17/12
A18: 2451-ENEPCCVC | B18: 655062 | C18: 3.8065649 | D18: Cercanía y PC | E18: Reels Experiencias BA | F18: Participación Ciudadana - Verano en la Ciudad (Pauta RRSS)
A19: 2039-SEPDHHGC | B19: 843069 | C19: 0.53888828 | D19: Desarrollo Humano y Hábitat | E19: Red de Atención en Comuna 2 | F19: Red de Atención - Comuna 2
A20: 2439-DICINFGC | B20: 355350 | C20: 1.8718503 | D20: Infraestructura | F20: Infraestructura I Bus Eléctricos: extensión recorrido
A21: 2424-DICFESGC | B21: 3975434 | C21: 2.6766625 | D21: Festivales y Eventos | E21: Verano en la Ciudad | F21: Verano en Buenos Aires 2026 | Generico
A22: 2256-NOVSALGC | B22: 1318610 | C22: 2.6421224 | D22: Salud | E22: Sistema de Salud | F22: Sistema de Salud Público - Diferenciado x Audiencias
A23: 1871-AGOEDUGC | B23: 9405671 | C23: 1.211467 | D23: Educación | E23: TUMO | F23: Campaña GCBA | Educación | TUMO
A24: 2322-NOVEDUGC | B24: 845956 | C24: 2.7451924 | D24: Educación | E24: TUMO | F24: TUMO Parque de la Innovación
A25: 2458-ENESEGGC | B25: 208110 | C25: 1.7622507 | D25: Seguridad | E25: Recuperación de propiedades | F25: Campaña GCBA I Seguridad I Desalojo edificio San Telmo
A26: 2459-ENESEGGC | B26: 550772 | C26: 1.8618212 | D26: Seguridad | E26: Recuperación de propiedades | F26: Campaña GCBA I Seguridad I Desalojo predio Parque Avellaneda
A27: 2465-ENEJDGAG | B27: 31114 | C27: 2.8909494 | D27: Jefatura de Gobierno | E27: ECVs Jorge Macri | F27: Cafe JM - Puerto Madero 16/1
A28: 2468-ENEINFGC | B28: 138774 | C28: 1.9878291 | D28: Infraestructura | E28: Estaciones de subte | F28: CAMPAÑA GCBA | INFRAESTRUCTURA | Cierre estación Piedras - Línea A | 12/1
A29: 2062-OCTINFGC | B29: 378593 | C29: 1.7210434 | D29: Infraestructura | E29: Estaciones de subte | F29: Infraestructura | Cierre Estación Loria Línea A
A30: 2434-DICFESGC | B30: 29161 | C30: 137.44429 | D30: Festivales y Eventos | E30: Verano en la Ciudad | F30: Verano en la Ciudad | Billboard Summer
A31: 2455-ENEDHHGC | B31: 1548468 | C31: 0.88227138 | D31: Desarrollo Humano y Hábitat | E31: Estaciones amigables | F31: Inauguración Estación Amigable
A32: 2470-ENEINFGC | B32: 270165 | C32: 1.0009254 | D32: Infraestructura | E32: Cortes y desvíos por obras | F32: CAMPAÑA GCBA | INFRAESTRUCTURA | Corte AU Illia
... A38: 2437-DICFESGC | B38: 1292752 | C38: 5.5283542 | D38: Festivales y Eventos | E38: Verano en la Ciudad | F38: Verano en la Ciudad | Verano en las plazas
A39: 2466-ENEFESGC | C39: 0 | D39: Festivales y Eventos | E39: Verano en la Ciudad | F39: Verano en la Ciudad | Parque de la Ciudad
A40: 2474-ENEINFGC | B40: 1236622 | C40: 0.48297297 | D40: Infraestructura | E40: Líneas de colectivo | F40: Campaña GCBA I Infraestructura I Nuevo ramal línea 42
A41: 2318-ENEINFGC | B41: 293307 | C41: 2.2370826 | D41: Infraestructura | E41: Cambio de sentido de calles | F41: Infraestructura I Cambio de sentido Avelino Díaz y Las Casas
A42: 2475-ENESEGAG | B42: 324234 | C42: 2.4565376 | D42: Seguridad | F42: RECORRIDA POR SERVICIO PENITENCIARIO de Marcos Paz
A43: 2464-ENEINFGC | B43: 484653 | C43: 1.4793739 | D43: Infraestructura | E43: PBN | Inicio, durante o fin de obra | F43: CAMPAÑA GCBA | INFRAESTRUCTURA | PBN García Lorca: durante de obra
A44: 2450-ENEJDGAG | B44: 81521 | C44: 3.9642055 | D44: Jefatura de Gobierno | E44: ECVs Jorge Macri | F44: RDV JM - Boedo 9/1
A45: 2483-ENESEGGC | B45: 355943 | C45: 2.8286889 | D45: Seguridad | E45: Recuperación de propiedades | F45: Campaña GCBA I Seguridad | Desalojo Constitución
A46: 2476-ENEFESGC | B46: 467329 | C46: 6.5961475 | D46: Festivales y Eventos | E46: Verano en la Ciudad | F46: Verano en la Ciudad | Corrientes 24h
A47: 2465-ENEJDGAG | B47: 31927 | C47: 2.8173333 | D47: Jefatura de Gobierno | E47: ECVs Jorge Macri | F47: Cafe JM - Puerto Madero 16/1
A48: 2501-ENEJDGAG | B48: 75466 | C48: 3.4477778 | D48: Jefatura de Gobierno | E48: ECVs Jorge Macri | F48: RDV JM Flores 30/01
A49: 2510-ENEINFGC | B49: 137491 | C49: 1.4147471 | D49: Infraestructura | E49: Cambio de sentido de calles | F49: Infraestructura I Cambio de sentido calle Reconquista
A50: 2502-ENEJDGAG | B50: 17945 | C50: 2.4849262 | D50: Jefatura de Gobierno | E50: ECVs Jorge Macri | F50: CAFE JM Versalles 29/01
A51: 2516-ENESALCG | B51: 1034589 | C51: 1.4523545 | D51: Salud | E51: Emergencias | F51: Carrusel Refugios climáticos
A52: 2496-ENEVINGC | B52: 1977609 | C52: 3.955656 | D52: Vínculo Ciudadano | E52: Más servicios en tu barrio | F52: CAMPAÑA GCBA | VINCULO CIUDADANO | Mas servicios en tu barrio 2026: Recoleta 25/02
A53: 2508-ENEINFGC | B53: 810555 | C53: 0.56835378 | D53: Infraestructura | E53: Dellepiane | F53: Infraestructura I AU Dellepiane : durante de obra
A54: 2467-ENEFESGC | B54: 176068 | C54: 40.108441 | D54: Festivales y Eventos | E54: Verano en la Ciudad | F54: Verano en la Ciudad | Verano Joven BA enero
... A62: 2533-ENEJDGAG | B62: 39417 | C62: 1.2497907 | D62: Jefatura de Gobierno | E62: ECVs Jorge Macri | F62: RDV JM | CONSTITUCIÓN 6/2
A63: 2529-ENESEGGC | B63: 26089 | C63: 72.777032 | D63: Seguridad | F63: CAMPAÑA GCBA | SEGURIDAD | Nuevo equipamiento PDLC
A64: 2542-ENESEGVC | B64: 90763 | C64: 1.2654055 | D64: Seguridad | E64: ECVs Gabino Tapia | F64: RDV MINISTROS | GABINO TAPIA 5/2 COMUNA 2
A65: 2538-ENEINFGC | B65: 21071 | C65: 0 | D65: Infraestructura | E65: Cortes y desvíos por eventos | F65: Infraestructura I Corte en Huracán por evento musical MY CHEMICAL ROMANCE
A66: 2543-ENESEGVC | B66: 100262 | C66: 1.3331272 | D66: Seguridad | E66: ECVs Ruth Landerreche | F66: RDV MINISTROS | RUTH LANDERRECHE 5/2 COMUNA 3
A67: 2540-ENESEGVC | B67: 82374 | C67: 1.505208 | D67: Seguridad | E67: ECVs Maximiliano Piñeiro | F67: RDV MINISTROS | MAXIMILIANO PIÑEIRO 5/2 COMUNA 1 SUR
A68: 2541-ENESEGVC | B68: 89771 | C68: 1.5582315 | D68: Seguridad | E68: ECVs Horacio Giménez | F68: RDV MINISTROS | HORACIO GIMÉNEZ 5/2 COMUNA 1 NORTE
A69: 2531-ENEJDGVC | B69: 20763 | C69: 1.5483312 | D69: Jefatura de Gabinete | E69: ECVs Gabriel Sánchez Zinny | F69: RDV MINISTROS | Gabriel Sanchez Zinny 06/02
A70: 2549-FEBDHHVC | B70: 117960 | C70: 1.593786 | D70: Desarrollo Humano y Hábitat | E70: ECVs Gabriel Mraida | F70: RDV Ministros | Gabriel Mraida - 6/2
A71: 2514-ENEINFGJ | B71: 156710 | C71: 2.6982835
A72: 2519-ENEINFGC | B72: 134621 | C72: 3.1275878 | D72: Infraestructura | E72: Cortes y desvíos por obras | F72: Infraestructura I Cortes y desvíos en Larralde
A73: 2460-ENEFESGC | B73: 297850 | C73: 8.6866577 | D73: Festivales y Eventos | E73: Verano en la Ciudad | F73: Campaña verano en la ciudad | Verano en los anfiteatros
A74: 2501-ENEJDGAG | B74: 63796 | C74: 4.0784689 | D74: Jefatura de Gobierno | E74: ECVs Jorge Macri | F74: RDV JM Flores 30/01
A75: 2569-FEBVINVC | B75: 274739 | C75: 1.5542642 | D75: Vínculo Ciudadano | E75: ECVs Ezequiel Sabor | F75: RDV MINISTROS | Ezequiel Sabor 9/2
A76: 2553-FEBINFGC | B76: 205020 | C76: 1.3852551 | D76: Infraestructura | E76: Cortes y desvíos por obras | F76: Infraestructura I Cortes por obras TramBus FEBRERO
A77: 2570-FEBJDGVC | B77: 24074 | C77: 1.6656559 | D77: Jefatura de Gabinete | E77: ECVs Gabriel Sánchez Zinny | F77: RDV MINISTROS | Gabriel Sanchez Zinny 10/2
A78: 2572-FEBEDUVC | B78: 143474 | C78: 1.5561356 | D78: Educación | E78: ECVs Mercedes Miguel | F78: RDV MINISTROS | Mercedes Miguel 10/2 COMUNA 1
A79: 2571-FEBJDGVC | B79: 37372 | C79: 1.5763941 | D79: Jefatura de Gabinete | E79: ECVs Gabriel Sánchez Zinny | F79: RDV MINISTROS | Gabriel Sanchez Zinny 11/2
A80: 2556-FEBINFGC | B80: 849495 | C80: 1.3372604 | D80: Infraestructura | E80: Estaciones de subte | F80: Infraestructura | Apertura estación Agüero
A81: 2568-FEBJDGAG | B81: 42089 | C81: 5.1738934 | D81: Jefatura de Gobierno | E81: ECVs Jorge Macri | F81: RDV JM 12/2 Villa Soldati
A82: 2561-FEBPCCVC | B82: 176920 | C82: 1.5348576 | D82: Cercanía y PC | E82: ECVs Gabino Tapia | F82: Café con vecinos | Lombardi | Piragine | Tapia 9/2
A83: 2555-FEBSALGC | B83: 557979 | C83: 2.7565894 | D83: Salud | E83: Obras en hospitales | F83: Hospital Muñiz - Finalización de obra
... A102: 2548-ENEFESGC | B102: 1282165 | C102: 0.59584999 | D102: Festivales y Eventos | E102: Verano en la Ciudad | F102: Verano BA | Noche de Verano: Villa Crespo
A103: 2580-FEBSEGGC | C103: 0 | D103: Seguridad | E103: Recuperación de propiedades | F103: CAMPAÑA GCBA | SEGURIDAD | Desalojo en Palermo
A104: 2590-FEBINFGC | B104: 1907063 | C104: 0.13515967 | D104: Infraestructura | E104: Cortes y desvíos por obras | F104: Cortes y desvíos en MTB por obras
A105: 2558-FEBFESGC | B105: 677074 | C105: 3.8506589 | D105: Festivales y Eventos | E105: Verano en la Ciudad | F105: Verano BA | Buenos Aires Extremo
A106: 2534-ENEJDGAG | B106: 22208 | C106: 2.7866535 | D106: Jefatura de Gobierno | E106: ECVs Jorge Macri | F106: RDV JM | VILLA RIACHUELO 5/2
A107: 2532-ENEJDGAG | B107: 42874 | C107: 2.8136166 | D107: Jefatura de Gobierno | E107: ECVs Jorge Macri | F107: RDV JM | VILLA URQUIZA 2/2
A108: 2604-FEBINFVC | B108: 233746 | C108: 1.5917449 | D108: Infraestructura | E108: ECVs Pablo Bereciartua | F108: RDV MINISTROS | Pablo Bereciartua 18/2 COMUNA 14
A109: 2595-FEBJDGAG | B109: 84069 | C109: 4.1326529 | D109: Jefatura de Gobierno | E109: ECVs Jorge Macri | F109: RDV JM | 19/02 Villa Lugano
A110: 2597-FEBJDGAG | B110: 30612 | C110: 5.0376323 | D110: Jefatura de Gobierno | E110: ECVs Jorge Macri | F110: RDV JM | 21/02 Floresta
A111: 2598-FEBEPHVC | B111: 135581 | C111: 1.6408568 | D111: Espacio Público e Higiene Urbana | E111: ECVs Ignacio Baistrocchi | F111: RDV MINISTROS | IGNACIO BAISTROCCHI 18/2 COMUNA 12
A112: 2596-FEBJDGAG | B112: 30128 | C112: 2.5816848 | D112: Jefatura de Gobierno | E112: ECVs Jorge Macri | F112: RDV JM | 20/02 Villa Luro
A113: 2581-FEBFESGC | B113: 318767 | C113: 3.8833223 | D113: Festivales y Eventos | E113: Verano en la Ciudad | F113: Verano BA | Día de los Enamorados
A114: 2593-FEBSEGGC | B114: 156446 | C114: 13.380323 | D114: Seguridad | E114: Recuperación de espacios públicos | F114: CAMPAÑA GCBA | SEGURIDAD | Un año sin manteros en Flores
A115: 2599-FEBDHHVC | B115: 287774 | C115: 1.3931592 | D115: Desarrollo Humano y Hábitat | E115: ECVs Gabriel Mraida | F115: RDV Ministros | Gabriel Mraida - 20/02
A116: 2545-ENEEDUGC | B116: 993671 | C116: 0.60526271 | D116: Educación | F116: Formacion profesional
A117: 2608-FEBAMBVC | B117: 343375 | C117: 1.3759709 | D117: Vicejefatura (Ambiente) | E117: ECVs Clara Muzzio | F117: RDV Ministros | Clara Muzzio - 18/02
A118: 2615-FEBINFCG | B118: 71769 | C118: 1.3987237 | D118: Infraestructura | F118: CONTENIDO ADICIONAL GCBA | Infraestructura | Extensión horaria Línea D - Bad Bunny
A119: 2600-FEBSEGVC | B119: 103246 | C119: 1.5779498 | D119: Seguridad | E119: ECVs Horacio Giménez | F119: RDV Ministros | Horacio Giménez 19/2 Comuna 11
A120: 2601-FEBSEGVC | B120: 107726 | C120: 1.5570429 | D120: Seguridad | E120: ECVs Maximiliano Piñeiro | F120: RDV Ministros | Maximiliano Piñeiro 19/2 Comuna 9
A121: 2603-FEBSEGVC | B121: 100677 | C121: 1.5730902 | D121: Seguridad | E121: ECVs Ruth Landerreche | F121: RDV Ministros | Ruth Landerreche 19/2 Comuna 10
A122: 2602-FEBSEGVC | B122: 140853 | C122: 1.5240854 | D122: Seguridad | E122: ECVs Gabino Tapia | F122: RDV Ministros | Gabino Tapia 19/2 Comuna 8
A123: 2612-FEBINFGC | B123: 41428 | C123: 1.4847688 | D123: Infraestructura | E123: Cortes y desvíos por eventos | F123: INFRAESTRUCTURA | Cortes y desvíos por año nuevo chino - Belgrano
